Workbook
Name GeocodeAddressColumn_Map: Map!$G$1
Name GeocodeAddressColumn_QualityReport: 'Quality Report'!$B$1
Name GeocodeAddressColumn_Sheet12: #REF!

Sheet Reporte SDR General
C2: Day In | D2: Day Out
C3: 45870 | D3: 45901 | G3: =EOMONTH(C3,-4)+1 -> 45778 | H3: =EOMONTH(D3,-1) -> 45900
C4: =EOMONTH(C3,-2)+1 -> 45839 | D4: =EDATE(D3, -1) -> 45870
D5: TOTAL | E5: % | F5: Δ% vs PP | H5: Total | I5: % | J5: Δ% vs PP | K5: Manufacturers | L5: % | M5: Δ% vs PP | N5: Individuals | O5: % | P5: Δ% vs PP
C6: Total Leads SDR | D6: =H6 -> 0 | F6: =iferror(D6/'PT Reporte SDR'!D6-1,"") | H6: =COUNTIFS(Data!$A:$A,">="&'Reporte SDR General'!$C$3,Data!$A:$A,"<="&'Reporte SDR General'!$D$3) -> 0 | J6: =iferror(H6/'PT Reporte SDR'!H6-1,"") | K6: =COUNTIFS(Data!$A:$A,">="&'Reporte SDR General'!$C$3,Data!$A:$A,"<="&'Reporte SDR General'!$D$3,Data!$BI:$BI,K5) -> 0 | M6: =iferror(K6/'PT Reporte SDR'!K6-1,"") | N6: =COUNTIFS(Data!$A:$A,">="&'Reporte SDR General'!$C$3,Data!$A:$A,"<="&'Reporte SDR General'!$D$3,Data!$BI:$BI,N5) -> 0 | P6: =iferror(N6/'PT Reporte SDR'!N6-1,"")
C7: Prueba | D7: =Sum(H7+K7+N7) -> 0 | E7: =iferror(D7/$D$6,"0%") -> 0% | F7: =D7/D6 -> #DIV/0! | H7: =COUNTIFS(Data!$A:$A,">="&'Reporte SDR General'!$C$3,Data!$A:$A,"<="&'Reporte SDR General'!$D$3,Data!$X:$X,C7) -> 0 | I7: =iferror(H7/$D$43,0) -> 0 | J7: =iferror(H7/'PT Reporte SDR'!H65-1,"") | K7: =COUNTIFS(Data!$A:$A,">="&'Reporte SDR General'!$C$3,Data!$A:$A,"<="&'Reporte SDR General'!$D$3,Data!$BI:$BI,$H$5,Data!$CM:$CM,C7) -> 0 | L7: =iferror(K7/$D$43,0) -> 0 | M7: =iferror(K7/'PT Reporte SDR'!K65-1,"") | N7: =COUNTIFS(Data!$A:$A,">="&'Reporte SDR General'!$C$3,Data!$A:$A,"<="&'Reporte SDR General'!$D$3,Data!$BI:$BI,$H$5,Data!$CM:$CM,C7) -> 0 | O7: =iferror(N7/$D$43,0) -> 0 | P7: =iferror(N7/'PT Reporte SDR'!N65-1,"")
C8: Total Leads Incontactables por base de datos | D8: =H8 -> 0 | E8: =iferror(D8/$D$6,"0%") -> 0% | F8: =iferror(D8/'PT Reporte SDR'!D7-1,"") | H8: =H43 -> 0 | I8: =iferror(H8/$D$6,"0%") -> 0% | J8: =iferror(H8/'PT Reporte SDR'!H7-1,"") | K8: =K43 -> 0 | L8: =iferror(K8/$D$6,"0%") -> 0% | M8: =iferror(K8/'PT Reporte SDR'!K7-1,"") | N8: =N43 -> 0 | O8: =iferror(N8/$D$6,"0%") -> 0% | P8: =iferror(N8/'PT Reporte SDR'!N7-1,"")
C9: Total Leads Contactables | D9: =H9 -> 0 | E9: =iferror(D9/$D$6,"0%") -> 0% | F9: =iferror(D9/'PT Reporte SDR'!D8-1,"") | H9: =H6-H8 -> 0 | I9: =iferror(H9/$D$6,"0%") -> 0% | J9: =iferror(H9/'PT Reporte SDR'!H8-1,"") | K9: =K6-K8 -> 0 | L9: =iferror(K9/$D$6,"0%") -> 0% | M9: =iferror(K9/'PT Reporte SDR'!K8-1,"") | N9: =N6-N8 -> 0 | O9: =iferror(N9/$D$6,"0%") -> 0% | P9: =iferror(N9/'PT Reporte SDR'!N8-1,"")
C10: Total Leads Contactados (con al menos 1 Toque) | D10: =H10 -> 54 | E10: =iferror(D10/D9,"0%") -> 0% | F10: =iferror(D10/'PT Reporte SDR'!D9-1,"") | H10: =COUNTIFS(Data!$A:$A,">="&'Reporte SDR General'!$C$3,Data!$A:$A,"<="&'Reporte SDR General'!$D$3,Data!$Z:$Z,">0")+54 -> 54 | I10: =iferror(H10/H9,"0%") -> 0% | J10: =iferror(H10/'PT Reporte SDR'!H9-1,"") | K10: =COUNTIFS(Data!$A:$A,">="&'Reporte SDR General'!$C$3,Data!$A:$A,"<="&'Reporte SDR General'!$D$3,Data!$BI:$BI,K5,Data!$AT:$AT,"<>")-K8 -> 0 | L10: =iferror(K10/K9,"0%") -> 0% | M10: =iferror(K10/'PT Reporte SDR'!K9-1,"") | N10: =COUNTIFS(Data!$A:$A,">="&'Reporte SDR General'!$C$3,Data!$A:$A,"<="&'Reporte SDR General'!$D$3,Data!$BI:$BI,N5,Data!$AT:$AT,"<>")-N8 -> 0 | O10: =iferror(N10/N9,"0%") -> 0% | P10: =iferror(N10/'PT Reporte SDR'!N9-1,"")
C11: Total Lead en Proceso de Contacto (aún sin respuesta) | D11: =H11 -> 156 | E11: =iferror(D11/$D$6,"0%") -> 0% | F11: =iferror(D11/'PT Reporte SDR'!D10-1,"") -> 1.1971831 | H11: =156 -> 156 | I11: =iferror(H11/$D$6,"0%") -> 0% | J11: =iferror(H11/'PT Reporte SDR'!H10-1,"") -> 1.1971831 | K11: =COUNTIFS(Data!$A:$A,">="&'Reporte SDR General'!$C$3,Data!$A:$A,"<="&'Reporte SDR General'!$D$3,Data!$BI:$BI,K5,Data!$BK:$BK,"No respondio") -> 0 | L11: =iferror(K11/$D$6,"0%") -> 0% | M11: =iferror(K11/'PT Reporte SDR'!K10-1,"") | N11: =COUNTIFS(Data!$A:$A,">="&'Reporte SDR General'!$C$3,Data!$A:$A,"<="&'Reporte SDR General'!$D$3,Data!$BI:$BI,N5,Data!$BK:$BK,"No respondio") -> 0 | O11: =iferror(N11/$D$6,"0%") -> 0% | P11: =iferror(N11/'PT Reporte SDR'!N10-1,"")
C12: Total Leads Contactados sin Respuesta (6to Toque o más) | D12: =H12 -> 0 | E12: =iferror(IFERROR(D12/D10,0),"") -> 0 | F12: =iferror(D12/'PT Reporte SDR'!D11-1,"") | H12: =H73 -> 0 | I12: =iferror(IFERROR(H12/H10,0),"") -> 0 | J12: =iferror(H12/'PT Reporte SDR'!H11-1,"") | K12: =COUNTIFS(Data!$A:$A,">="&'Reporte SDR General'!$C$3,Data!$A:$A,"<="&'Reporte SDR General'!$D$3,Data!$BI:$BI,K5,Data!$AT:$AT,">=6") -> 0 | L12: =iferror(IFERROR(K12/K10,0),"") -> 0 | M12: =iferror(K12/'PT Reporte SDR'!K11-1,"") | N12: =COUNTIFS(Data!$A:$A,">="&'Reporte SDR General'!$C$3,Data!$A:$A,"<="&'Reporte SDR General'!$D$3,Data!$BI:$BI,N5,Data!$AT:$AT,">=6") -> 0 | O12: =iferror(IFERROR(N12/N10,0),"") -> 0 | P12: =iferror(N12/'PT Reporte SDR'!N11-1,"")
C13: Total Leads Contactados con Respuesta | D13: =H13 -> 1 | E13: =iferror(D13/D9,"0%") -> 0% | F13: =iferror(D13/'PT Reporte SDR'!D12-1,"") | H13: =H49+1 -> 1 | I13: =iferror(H13/H9,"0%") -> 0% | J13: =iferror(H13/'PT Reporte SDR'!H12-1,"") | K13: =COUNTIFS(Data!$A:$A,">="&'Reporte SDR General'!$C$3,Data!$A:$A,"<="&'Reporte SDR General'!$D$3,Data!$BI:$BI,K5,Data!$BK:$BK,"Pase a ventas")+COUNTIFS(Data!$A:$A,">="&'Reporte SDR General'!$C$3,Data!$A:$A,"<="&'Reporte SDR General'!$D$3,Data!$BI:$BI,K5,Data!$BK:$BK,"Descartado")+COUNTIFS(Data!$A:$A,">="&'Reporte SDR General'!$C$3,Data!$A:$A,"<="&'Reporte SDR General'!$D$3,Data!$BI:$BI,K5,Data!$BK:$BK,"Pidio llamar mas tarde")+COUNTIFS(Data!$A:$A,">="&'Reporte SDR General'!$C$3,Data!$A:$A,"<="&'Reporte SDR General'!$D$3,Data!$BI:$BI,K5,Data!$BK:$BK,"Contesta y Cuelga")+COUNTIFS(Data!$A:$A,">="&'Reporte SDR General'!$C$3,Data!$A:$A,"<="&'Reporte SDR General'!$D$3,Data!$BI:$BI,K5,Data!$BK:$BK,"Llamar mañana")+COUNTIFS(Data!$A:$A,">="&'Reporte SDR General'!$C$3,Data!$A:$A,"<="&'Reporte SDR General'!$D$3,Data!$BI:$BI,K5,Data!$BK:$BK,"SEGUIMIENTO") -> 0 | L13: =iferror(K13/K9,"0%") -> 0% | M13: =iferror(K13/'PT Reporte SDR'!K12-1,"") | N13: =COUNTIFS(Data!$A:$A,">="&'Reporte SDR General'!$C$3,Data!$A:$A,"<="&'Reporte SDR General'!$D$3,Data!$BI:$BI,N5,Data!$BK:$BK,"Pase a ventas")+COUNTIFS(Data!$A:$A,">="&'Reporte SDR General'!$C$3,Data!$A:$A,"<="&'Reporte SDR General'!$D$3,Data!$BI:$BI,N5,Data!$BK:$BK,"Descartado")+COUNTIFS(Data!$A:$A,">="&'Reporte SDR General'!$C$3,Data!$A:$A,"<="&'Reporte SDR General'!$D$3,Data!$BI:$BI,N5,Data!$BK:$BK,"Pidio llamar mas tarde")+COUNTIFS(Data!$A:$A,">="&'Reporte SDR General'!$C$3,Data!$A:$A,"<="&'Reporte SDR General'!$D$3,Data!$BI:$BI,N5,Data!$BK:$BK,"Contesta y Cuelga")+COUNTIFS(Data!$A:$A,">="&'Reporte SDR General'!$C$3,Data!$A:$A,"<="&'Reporte SDR General'!$D$3,Data!$BI:$BI,N5,Data!$BK:$BK,"Llamar mañana")+COUNTIFS(Data!$A:$A,">="&'Reporte SDR General'!$C$3,Data!$A:$A,"<="&'Reporte SDR General'!$D$3,Data!$BI:$BI,N5,Data!$BK:$BK,"SEGUIMIENTO") -> 0 | O13: =iferror(N13/N9,"0%") -> 0% | P13: =iferror(N13/'PT Reporte SDR'!N12-1,"")
C14: Total Leads Con Dialogo Completo | D14: =H14 -> 0 | E14: =IFERROR(D14/$D$13,0) -> 0 | F14: =iferror(D14/'PT Reporte SDR'!D13-1,"") | H14: =COUNTIFS(Data!$A:$A,">="&'Reporte SDR General'!$C$3,Data!$A:$A,"<="&'Reporte SDR General'!$D$3,Data!$AB:$AB,"Diálogo Completo") -> 0 | I14: =IFERROR(H14/$D$13,0) -> 0 | J14: =iferror(H14/'PT Reporte SDR'!H13-1,"") | K14: =COUNTIFS(Data!$A:$A,">="&'Reporte SDR General'!$C$3,Data!$A:$A,"<="&'Reporte SDR General'!$D$3,Data!$BI:$BI,K5,Data!$W:$W,"Diálogo Completo") -> 0 | L14: =IFERROR(K14/$D$13,0) -> 0 | M14: =iferror(K14/'PT Reporte SDR'!K13-1,"") | N14: =COUNTIFS(Data!$A:$A,">="&'Reporte SDR General'!$C$3,Data!$A:$A,"<="&'Reporte SDR General'!$D$3,Data!$BI:$BI,N5,Data!$W:$W,"Diálogo Completo") -> 0 | O14: =IFERROR(N14/$D$13,0) -> 0 | P14: =iferror(N14/'PT Reporte SDR'!N13-1,"")
C15: Total Leads Intermitentes | D15: =H15 -> 6 | E15: =IFERROR(D15/$D$13,0) -> 6 | F15: =iferror(D15/'PT Reporte SDR'!D14-1,"") -> 5 | H15: =COUNTIFS(Data!$A:$A,">="&'Reporte SDR General'!$C$3,Data!$A:$A,"<="&'Reporte SDR General'!$D$3,Data!$AB:$AB,"Intermitente")+6 -> 6 | I15: =IFERROR(H15/$D$13,0) -> 6 | J15: =iferror(H15/'PT Reporte SDR'!H14-1,"") -> 5 | K15: =COUNTIFS(Data!$A:$A,">="&'Reporte SDR General'!$C$3,Data!$A:$A,"<="&'Reporte SDR General'!$D$3,Data!$BI:$BI,K5,Data!$W:$W,"Intermitente") -> 0 | L15: =IFERROR(K15/$D$13,0) -> 0 | M15: =iferror(K15/'PT Reporte SDR'!K14-1,"") | N15: =COUNTIFS(Data!$A:$A,">="&'Reporte SDR General'!$C$3,Data!$A:$A,"<="&'Reporte SDR General'!$D$3,Data!$BI:$BI,N5,Data!$W:$W,"Intermitente") -> 0 | O15: =IFERROR(N15/$D$13,0) -> 0 | P15: =iferror(N15/'PT Reporte SDR'!N14-1,"")
C16: Leads que entendieron comunicación | D16: =H16 -> 8 | E16: =IFERROR(D16/$D$13,0) -> 8 | F16: =iferror(D16/'PT Reporte SDR'!D15-1,"") | H16: =COUNTIFS(Data!$A:$A,">="&'Reporte SDR General'!$C$3,Data!$A:$A,"<="&'Reporte SDR General'!$D$3,Data!$AF:$AF,"Si")+8 -> 8 | I16: =IFERROR(H16/$D$13,0) -> 8 | J16: =iferror(H16/'PT Reporte SDR'!H15-1,"") | K16: =COUNTIFS(Data!$A:$A,">="&'Reporte SDR General'!$C$3,Data!$A:$A,"<="&'Reporte SDR General'!$D$3,Data!$BI:$BI,K5,Data!$AJ:$AJ,"Si") -> 0 | L16: =IFERROR(K16/$D$13,0) -> 0 | M16: =iferror(K16/'PT Reporte SDR'!K15-1,"") | N16: =COUNTIFS(Data!$A:$A,">="&'Reporte SDR General'!$C$3,Data!$A:$A,"<="&'Reporte SDR General'!$D$3,Data!$BI:$BI,N5,Data!$AJ:$AJ,"Si") -> 0 | O16: =IFERROR(N16/$D$13,0) -> 0 | P16: =iferror(N16/'PT Reporte SDR'!N15-1,"")
C17: Leads que no entendieron comunicación | D17: =H17 -> 0 | E17: =IFERROR(D17/$D$13,0) -> 0 | F17: =iferror(D17/'PT Reporte SDR'!D16-1,"") | H17: =COUNTIFS(Data!$A:$A,">="&'Reporte SDR General'!$C$3,Data!$A:$A,"<="&'Reporte SDR General'!$D$3,Data!$AF:$AF,"No") -> 0 | I17: =IFERROR(H17/$D$13,0) -> 0 | J17: =iferror(H17/'PT Reporte SDR'!H16-1,"") | K17: =COUNTIFS(Data!$A:$A,">="&'Reporte SDR General'!$C$3,Data!$A:$A,"<="&'Reporte SDR General'!$D$3,Data!$BI:$BI,K5,Data!$AJ:$AJ,"No") -> 0 | L17: =IFERROR(K17/$D$13,0) -> 0 | M17: =iferror(K17/'PT Reporte SDR'!K16-1,"") | N17: =COUNTIFS(Data!$A:$A,">="&'Reporte SDR General'!$C$3,Data!$A:$A,"<="&'Reporte SDR General'!$D$3,Data!$BI:$BI,N5,Data!$AJ:$AJ,"No") -> 0 | O17: =IFERROR(N17/$D$13,0) -> 0 | P17: =iferror(N17/'PT Reporte SDR'!N16-1,"")
C18: Leads que mostraron interés | D18: =H18 -> 4 | E18: =IFERROR(D18/$D$13,0) -> 4 | F18: =iferror(D18/'PT Reporte SDR'!D17-1,"") -> 0.33333333 | H18: =COUNTIFS(Data!$A:$A,">="&'Reporte SDR General'!$C$3,Data!$A:$A,"<="&'Reporte SDR General'!$D$3,Data!$AG:$AG,"Si")+4 -> 4 | I18: =IFERROR(H18/$D$13,0) -> 4 | J18: =iferror(H18/'PT Reporte SDR'!H17-1,"") -> 0.33333333 | K18: =COUNTIFS(Data!$A:$A,">="&'Reporte SDR General'!$C$3,Data!$A:$A,"<="&'Reporte SDR General'!$D$3,Data!$BI:$BI,K5,Data!$BK:$BK,"Pase a ventas") -> 0 | L18: =IFERROR(K18/$D$13,0) -> 0 | M18: =iferror(K18/'PT Reporte SDR'!K17-1,"") | N18: =COUNTIFS(Data!$A:$A,">="&'Reporte SDR General'!$C$3,Data!$A:$A,"<="&'Reporte SDR General'!$D$3,Data!$BI:$BI,N5,Data!$BK:$BK,"Pase a ventas") -> 0 | O18: =IFERROR(N18/$D$13,0) -> 0 | P18: =iferror(N18/'PT Reporte SDR'!N17-1,"")
C19: Total Leads Descartados | D19: =H19 -> 16 | E19: =iferror(D19/D6,"0%") -> 0% | F19: =iferror(D19/'PT Reporte SDR'!D18-1,"") | H19: =H20+H21 -> 16 | I19: =iferror(H19/H6,"0%") -> 0% | J19: =iferror(H19/'PT Reporte SDR'!H18-1,"") | K19: =K20+K21 -> 0 | L19: =iferror(K19/K6,"0%") -> 0% | M19: =iferror(K19/'PT Reporte SDR'!K18-1,"") | N19: =N20+N21 -> 0 | O19: =iferror(N19/N6,"0%") -> 0% | P19: =iferror(N19/'PT Reporte SDR'!N18-1,"")
C20: Leads que no mostraron interés | D20: =H20 -> 0 | E20: =IFERROR(D20/$D$13,0) -> 0 | F20: =iferror(D20/'PT Reporte SDR'!D19-1,"") | H20: =COUNTIFS(Data!$A:$A,">="&'Reporte SDR General'!$C$3,Data!$A:$A,"<="&'Reporte SDR General'!$D$3,Data!$AG:$AG,"No") -> 0 | I20: =IFERROR(H20/$D$13,0) -> 0 | J20: =iferror(H20/'PT Reporte SDR'!H19-1,"") | K20: =COUNTIFS(Data!$A:$A,">="&'Reporte SDR General'!$C$3,Data!$A:$A,"<="&'Reporte SDR General'!$D$3,Data!$BI:$BI,K5,Data!$AJ:$AJ,"No") -> 0 | L20: =IFERROR(K20/$D$13,0) -> 0 | M20: =iferror(K20/'PT Reporte SDR'!K19-1,"") | N20: =COUNTIFS(Data!$A:$A,">="&'Reporte SDR General'!$C$3,Data!$A:$A,"<="&'Reporte SDR General'!$D$3,Data!$BI:$BI,N5,Data!$AJ:$AJ,"No") -> 0 | O20: =IFERROR(N20/$D$13,0) -> 0 | P20: =iferror(N20/'PT Reporte SDR'!N19-1,"")
C21: Otras razones | D21: =H21 -> 16 | E21: =IFERROR(D21/$D$13,0) -> 16 | F21: =iferror(D21/'PT Reporte SDR'!D20-1,"") | H21: =H76+D76-1 -> 16 | I21: =IFERROR(H21/$D$13,0) -> 16 | J21: =iferror(H21/'PT Reporte SDR'!H20-1,"") | K21: =K76 -> 0 | L21: =IFERROR(K21/$D$13,0) -> 0 | M21: =iferror(K21/'PT Reporte SDR'!K20-1,"") | N21: =N76 -> 0 | O21: =IFERROR(N21/$D$13,0) -> 0 | P21: =iferror(N21/'PT Reporte SDR'!N20-1,"")
C22: Total Leads en seguimiento para venta | D22: =H22 -> 0 | E22: =IFERROR(D22/$D$13,0) -> 0 | F22: =iferror(D22/'PT Reporte SDR'!D21-1,"") | H22: =COUNTIFS(Data!$A:$A,">="&'Reporte SDR General'!$C$3,Data!$A:$A,"<="&'Reporte SDR General'!$D$3,Data!$W:$W,"En Seguimiento") -> 0 | I22: =IFERROR(H22/$D$13,0) -> 0 | J22: =iferror(H22/'PT Reporte SDR'!H21-1,"") | K22: =COUNTIFS(Data!$A:$A,">="&'Reporte SDR General'!$C$3,Data!$A:$A,"<="&'Reporte SDR General'!$D$3,Data!$BI:$BI,K5,Data!$BK:$BK,"SEGUIMIENTO") -> 0 | L22: =IFERROR(K22/$D$13,0) -> 0 | M22: =iferror(K22/'PT Reporte SDR'!K21-1,"") | N22: =COUNTIFS(Data!$A:$A,">="&'Reporte SDR General'!$C$3,Data!$A:$A,"<="&'Reporte SDR General'!$D$3,Data!$BI:$BI,N5,Data!$BK:$BK,"SEGUIMIENTO") -> 0 | O22: =IFERROR(N22/$D$13,0) -> 0 | P22: =iferror(N22/'PT Reporte SDR'!N21-1,"")
C23: Total Leads Asignados a Ventas | D23: =H23 -> 0 | E23: =iferror(D23/D18,"0%") -> 0 | F23: =iferror(D23/'PT Reporte SDR'!D22-1,"") | H23: =H24+H25 -> 0
C24: Leads Asignados a Ventas Periodo Actual | D24: =H24 -> 0 | E24: =IFERROR(D24/D18,0) -> 0 | F24: =iferror(D24/'PT Reporte SDR Brazil'!D23-1,"") -> -1 | H24: =COUNTIFS(Data!A:A,">="&'Reporte SDR General'!$C$3,Data!A:A,"<="&'Reporte SDR General'!$D$3,Data!$W:$W,"Paso a ventas") -> 0
C25: Leads Asignados a Ventas Carry-Over | D25: =H25 -> 0 | E25: =IFERROR(D25/#REF!,0) -> 0 | F25: =iferror(D25/'PT Reporte SDR Brazil'!D24-1,"") | H25: =COUNTIFS(Data!A:A,">="&'Reporte SDR General'!$C$4,Data!A:A,"<="&'Reporte SDR General'!$D$4,Data!$W:$W,"Paso a ventas",Data!BY:BY,">="&'Reporte SDR General'!$C$3,Data!BY:BY,"<="&'Reporte SDR General'!$D$3) -> 0
C26: Leads Asignados a Ventas Periodo Anterior (Histórico) | D26: =H26 -> 0 | E26: =D26/D23 -> #DIV/0! | F26: =iferror(D26/'PT Reporte SDR Brazil'!D25-1,"") | H26: =COUNTIFS(Data!A:A,">="&'Reporte SDR General'!$G$3,Data!A:A,"<="&'Reporte SDR General'!$H$3,Data!$W:$W,"Paso a ventas") -> 0
C27: Monto de Inversión asignada a Ventas (leads este mes) | D27: =H27 -> #N/A | E27: =IFERROR(D27/D23,0) -> 0 | F27: =iferror(D27/'PT Reporte SDR Brazil'!D26-1,"") | H27: =SUMIFS(Data!BQ:BQ,Data!A:A,">="&'Reporte SDR General'!$C$3,Data!A:A,"<="&'Reporte SDR General'!$D$3,Data!$W:$W,"Paso a ventas") -> #N/A
C28: Monto de Inversión asignada a Ventas Carry-Over (Leads Mes anterior) | D28: =H28 -> #N/A | E28: =iferror(D28/$D$71,0) -> 0 | F28: =iferror(D28/'PT Reporte SDR Brazil'!D27-1,"") | H28: =SUMIFS(Data!BQ:BQ,Data!A:A,">="&'Reporte SDR General'!$C$4,Data!A:A,"<="&'Reporte SDR General'!$D$4,Data!$W:$W,"Paso a ventas") -> #N/A
C29: Monto de inversión asignada a ventas total mes | D29: =H29 -> #N/A | E29: $ | F29: =iferror(D29/'PT Reporte SDR Brazil'!D28-1,"") | H29: =SUMIFS(Data!BQ:BQ,Data!A:A,">="&'Reporte SDR General'!$G$3,Data!A:A,"<="&'Reporte SDR General'!$H$3,Data!$W:$W,"Paso a ventas") -> #N/A | J29: =iferror(H29/'PT Reporte SDR Brazil'!H28-1,"")
C30: Monto de Inversión asignada a Ventas Total todos los tiempos | D30: =H30 -> 11605 | E30: =IFERROR(D30/D27,0) -> 0 | F30: =iferror(D30/'PT Reporte SDR Brazil'!D29-1,"") | H30: 11605 | I30: =IFERROR(H30/H27,0) -> 0 | J30: =iferror(H30/'PT Reporte SDR Brazil'!H29-1,"")
C31: Monto de Inversión asignada a Ventas Historico aún en seguimiento (sin mes anterior) | D31: =H31 | F31: =iferror(D31/'PT Reporte SDR Brazil'!D30-1,"") | J31: =iferror(H31/'PT Reporte SDR Brazil'!H30-1,"")
C32: Monto de inversión asignado a ventas Total General en seguimiento | D32: =H32 | F32: =iferror(D32/'PT Reporte SDR Brazil'!D31-1,"") | J32: =iferror(H32/'PT Reporte SDR Brazil'!H31-1,"")
C33: Monto de inversión Perdida | D33: =H33 | E33: =IFERROR(D33/D27,0) -> 0 | F33: =iferror(D33/'PT Reporte SDR Brazil'!D32-1,"") | I33: =IFERROR(H33/H27,0) -> 0 | J33: =iferror(H33/'PT Reporte SDR Brazil'!H32-1,"")
C34: Monto de Inversión Promedio por Prospecto | D34: =D30/D23 -> #DIV/0! | E34: =IFERROR(D34/D27,0) -> 0 | F34: =iferror(D34/'PT Reporte SDR Brazil'!D33-1,"") | H34: =D34 -> #DIV/0! | I34: =IFERROR(H34/H27,0) -> 0 | J34: =iferror(H34/'PT Reporte SDR Brazil'!H33-1,"")
C35: Monto de Inversión Promedio por Prospecto Periodo Anterior | D35: =H35 | F35: =iferror(D35/'PT Reporte SDR Brazil'!D34-1,"") | J35: =iferror(H35/'PT Reporte SDR Brazil'!H34-1,"")
C36: Deals Cerrados Pagados | D36: =H36 -> 8 | F36: =iferror(D36/'PT Reporte SDR Brazil'!D35-1,"") | H36: 8 | J36: =iferror(H36/'PT Reporte SDR Brazil'!H35-1,"")
C37: Monto de cierres | D37: =H37 -> 3240 | F37: =iferror(D37/'PT Reporte SDR Brazil'!D36-1,"") | H37: 3240 | J37: =iferror(H37/'PT Reporte SDR Brazil'!H36-1,"")
F38: =iferror(D38/'PT Reporte SDR'!D60-1,"") | J38: =iferror(H38/'PT Reporte SDR'!H60-1,"") | M38: =iferror(K38/'PT Reporte SDR'!K60-1,"") | P38: =iferror(N38/'PT Reporte SDR'!N60-1,"")
C39: Total Leads Incontactables | D39: Total | E39: % | F39: =iferror(D39/'PT Reporte SDR'!D61-1,"") | I39: % | J39: =iferror(H39/'PT Reporte SDR'!H61-1,"") | L39: % | M39: =iferror(K39/'PT Reporte SDR'!K61-1,"") | O39: % | P39: =iferror(N39/'PT Reporte SDR'!N61-1,"")
A40: {=UNIQUE(Data!BJ:BJ)} -> #REF! | C40: Duplicado | D40: =Sum(H40+K40+N40) -> 0 | E40: =iferror(D40/$D$43,0) -> 0 | F40: =iferror(D40/'PT Reporte SDR'!D62-1,"") | H40: =COUNTIFS(Data!$A:$A,">="&'Reporte SDR General'!$C$3,Data!$A:$A,"<="&'Reporte SDR General'!$D$3,Data!$X:$X,C40) -> 0 | I40: =iferror(H40/$D$43,0) -> 0 | J40: =iferror(H40/'PT Reporte SDR'!H62-1,"") | K40: =COUNTIFS(Data!$A:$A,">="&'Reporte SDR General'!$C$3,Data!$A:$A,"<="&'Reporte SDR General'!$D$3,Data!$BI:$BI,$H$5,Data!$CM:$CM,C40) -> 0 | L40: =iferror(K40/$D$43,0) -> 0 | M40: =iferror(K40/'PT Reporte SDR'!K62-1,"") | N40: =COUNTIFS(Data!$A:$A,">="&'Reporte SDR General'!$C$3,Data!$A:$A,"<="&'Reporte SDR General'!$D$3,Data!$BI:$BI,$H$5,Data!$CM:$CM,C40) -> 0 | O40: =iferror(N40/$D$43,0) -> 0 | P40: =iferror(N40/'PT Reporte SDR'!N62-1,"")
C41: Equivocado | D41: =Sum(H41+K41+N41) -> 0 | E41: =iferror(D41/$D$43,0) -> 0 | F41: =iferror(D41/'PT Reporte SDR'!D63-1,"") | H41: =COUNTIFS(Data!$A:$A,">="&'Reporte SDR General'!$C$3,Data!$A:$A,"<="&'Reporte SDR General'!$D$3,Data!$X:$X,C41) -> 0 | I41: =iferror(H41/$D$43,0) -> 0 | J41: =iferror(H41/'PT Reporte SDR'!H63-1,"") | K41: =COUNTIFS(Data!$A:$A,">="&'Reporte SDR General'!$C$3,Data!$A:$A,"<="&'Reporte SDR General'!$D$3,Data!$BI:$BI,$H$5,Data!$CM:$CM,C41) -> 0 | L41: =iferror(K41/$D$43,0) -> 0 | M41: =iferror(K41/'PT Reporte SDR'!K63-1,"") | N41: =COUNTIFS(Data!$A:$A,">="&'Reporte SDR General'!$C$3,Data!$A:$A,"<="&'Reporte SDR General'!$D$3,Data!$BI:$BI,$H$5,Data!$CM:$CM,C41) -> 0 | O41: =iferror(N41/$D$43,0) -> 0 | P41: =iferror(N41/'PT Reporte SDR'!N63-1,"")
C42: SPAM | D42: =Sum(H42+K42+N42) -> 0 | E42: =iferror(D42/$D$43,0) -> 0 | F42: =iferror(D42/'PT Reporte SDR'!D64-1,"") | H42: =COUNTIFS(Data!$A:$A,">="&'Reporte SDR General'!$C$3,Data!$A:$A,"<="&'Reporte SDR General'!$D$3,Data!$X:$X,C42) -> 0 | I42: =iferror(H42/$D$43,0) -> 0 | J42: =iferror(H42/'PT Reporte SDR'!H64-1,"") | K42: =COUNTIFS(Data!$A:$A,">="&'Reporte SDR General'!$C$3,Data!$A:$A,"<="&'Reporte SDR General'!$D$3,Data!$BI:$BI,$H$5,Data!$CM:$CM,C42) -> 0 | L42: =iferror(K42/$D$43,0) -> 0 | M42: =iferror(K42/'PT Reporte SDR'!K64-1,"") | N42: =COUNTIFS(Data!$A:$A,">="&'Reporte SDR General'!$C$3,Data!$A:$A,"<="&'Reporte SDR General'!$D$3,Data!$BI:$BI,$H$5,Data!$CM:$CM,C42) -> 0 | O42: =iferror(N42/$D$43,0) -> 0 | P42: =iferror(N42/'PT Reporte SDR'!N64-1,"")
C43: Total | D43: =sum(D40:D42) -> 0 | E43: =iferror(D43/$D$43,0) -> 0 | F43: =iferror(D43/'PT Reporte SDR'!D66-1,"") | H43: =SUM(H40:H42) -> 0 | I43: =iferror(H43/$D$43,0) -> 0 | J43: =iferror(H43/'PT Reporte SDR'!H66-1,"") | K43: =sum(K40:K42) -> 0 | L43: =iferror(K43/$D$43,0) -> 0 | M43: =iferror(K43/'PT Reporte SDR'!K66-1,"") | N43: =sum(N40:N42) -> 0 | O43: =iferror(N43/$D$43,0) -> 0 | P43: =iferror(N43/'PT Reporte SDR'!N66-1,"")
F44: =iferror(D44/'PT Reporte SDR'!D67-1,"") | J44: =iferror(H44/'PT Reporte SDR'!H67-1,"") | M44: =iferror(K44/'PT Reporte SDR'!K67-1,"") | P44: =iferror(N44/'PT Reporte SDR'!N67-1,"")
F45: =iferror(D45/'PT Reporte SDR'!D68-1,"") | J45: =iferror(H45/'PT Reporte SDR'!H68-1,"") | M45: =iferror(K45/'PT Reporte SDR'!K68-1,"") | P45: =iferror(N45/'PT Reporte SDR'!N68-1,"")
C46: Cross Selling | D46: =SUM(D47) -> 0 | E46: % | F46: =iferror(D46/'PT Reporte SDR'!D69-1,"") | I46: % | J46: =iferror(H46/'PT Reporte SDR'!H69-1,"") | L46: % | M46: =iferror(K46/'PT Reporte SDR'!K69-1,"") | O46: % | P46: =iferror(N46/'PT Reporte SDR'!N69-1,"")
C47: Cross Selling | E47: =iferror(D47/$D$46,0) -> 0 | F47: =iferror(D47/'PT Reporte SDR'!D70-1,"") | I47: =iferror(H47/$D$46,0) -> 0 | J47: =iferror(H47/'PT Reporte SDR'!H70-1,"") | L47: =iferror(K47/$D$46,0) -> 0 | M47: =iferror(K47/'PT Reporte SDR'!K70-1,"") | O47: =iferror(N47/$D$46,0) -> 0 | P47: =iferror(N47/'PT Reporte SDR'!N70-1,"")
F48: =iferror(D48/'PT Reporte SDR'!D71-1,"") | J48: =iferror(H48/'PT Reporte SDR'!H71-1,"") | M48: =iferror(K48/'PT Reporte SDR'!K71-1,"") | P48: =iferror(N48/'PT Reporte SDR'!N71-1,"")
C49: Total Leads Contactados con Respuesta | D49: =SUM(D50:D59) -> 0 | E49: % | F49: =iferror(D49/'PT Reporte SDR'!D72-1,"") | H49: =SUM(H50:H59) -> 0 | I49: % | J49: =iferror(H49/'PT Reporte SDR'!H72-1,"") | K49: =SUM(K50:K59) -> 0 | L49: % | M49: =iferror(K49/'PT Reporte SDR'!K72-1,"") | N49: =SUM(N50:N59) -> 0 | O49: % | P49: =iferror(N49/'PT Reporte SDR'!N72-1,"")
C50: Contestó Teléfono 1 | D50: =sum(H50) -> 0 | E50: =IFERROR(D50/$D$49,0) -> 0 | F50: =iferror(D50/'PT Reporte SDR'!D73-1,"") | H50: =COUNTIFS(Data!$A:$A,">="&'Reporte SDR General'!$C$3,Data!$A:$A,"<="&'Reporte SDR General'!$D$3,Data!$Y:$Y,C50) -> 0 | I50: =IFERROR(H50/$D$49,0) -> 0 | J50: =iferror(H50/'PT Reporte SDR'!H73-1,"") | K50: =COUNTIFS(Data!$A:$A,">="&'Reporte SDR General'!$C$3,Data!$A:$A,"<="&'Reporte SDR General'!$D$3,Data!$E:$E,D50,Data!$BG:$BG,$H$5) -> 0 | L50: =IFERROR(K50/$D$49,0) -> 0 | M50: =iferror(K50/'PT Reporte SDR'!K73-1,"") | N50: =COUNTIFS(Data!$A:$A,">="&'Reporte SDR General'!$C$3,Data!$A:$A,"<="&'Reporte SDR General'!$D$3,Data!$E:$E,E50,Data!$BG:$BG,$H$5) -> 0 | O50: =IFERROR(N50/$D$49,0) -> 0 | P50: =iferror(N50/'PT Reporte SDR'!N73-1,"")
C51: Contestó Teléfono 2 | D51: =sum(H51) -> 0 | E51: =IFERROR(D51/$D$49,0) -> 0 | F51: =iferror(D51/'PT Reporte SDR'!D74-1,"") | H51: =COUNTIFS(Data!$A:$A,">="&'Reporte SDR General'!$C$3,Data!$A:$A,"<="&'Reporte SDR General'!$D$3,Data!$Y:$Y,C51) -> 0 | I51: =IFERROR(H51/$D$49,0) -> 0 | J51: =iferror(H51/'PT Reporte SDR'!H74-1,"") | K51: =COUNTIFS(Data!$A:$A,">="&'Reporte SDR General'!$C$3,Data!$A:$A,"<="&'Reporte SDR General'!$D$3,Data!$E:$E,D51,Data!$BG:$BG,$H$5) -> 0 | L51: =IFERROR(K51/$D$49,0) -> 0 | M51: =iferror(K51/'PT Reporte SDR'!K74-1,"") | N51: =COUNTIFS(Data!$A:$A,">="&'Reporte SDR General'!$C$3,Data!$A:$A,"<="&'Reporte SDR General'!$D$3,Data!$E:$E,E51,Data!$BG:$BG,$H$5) -> 0 | O51: =IFERROR(N51/$D$49,0) -> 0 | P51: =iferror(N51/'PT Reporte SDR'!N74-1,"")
C52: Contestó Teléfono 3 | D52: =sum(H52) -> 0 | E52: =IFERROR(D52/$D$49,0) -> 0 | F52: =iferror(D52/'PT Reporte SDR'!D75-1,"") | H52: =COUNTIFS(Data!$A:$A,">="&'Reporte SDR General'!$C$3,Data!$A:$A,"<="&'Reporte SDR General'!$D$3,Data!$Y:$Y,C52) -> 0 | I52: =IFERROR(H52/$D$49,0) -> 0 | J52: =iferror(H52/'PT Reporte SDR'!H75-1,"") | K52: =COUNTIFS(Data!$A:$A,">="&'Reporte SDR General'!$C$3,Data!$A:$A,"<="&'Reporte SDR General'!$D$3,Data!$E:$E,D52,Data!$BG:$BG,$H$5) -> 0 | L52: =IFERROR(K52/$D$49,0) -> 0 | M52: =iferror(K52/'PT Reporte SDR'!K75-1,"") | N52: =COUNTIFS(Data!$A:$A,">="&'Reporte SDR General'!$C$3,Data!$A:$A,"<="&'Reporte SDR General'!$D$3,Data!$E:$E,E52,Data!$BG:$BG,$H$5) -> 0 | O52: =IFERROR(N52/$D$49,0) -> 0 | P52: =iferror(N52/'PT Reporte SDR'!N75-1,"")
C53: Contestó Whatsapp 1 | D53: =sum(H53) -> 0 | E53: =IFERROR(D53/$D$49,0) -> 0 | F53: =iferror(D53/'PT Reporte SDR'!D76-1,"") | H53: =COUNTIFS(Data!$A:$A,">="&'Reporte SDR General'!$C$3,Data!$A:$A,"<="&'Reporte SDR General'!$D$3,Data!$Y:$Y,C53) -> 0 | I53: =IFERROR(H53/$D$49,0) -> 0 | J53: =iferror(H53/'PT Reporte SDR'!H76-1,"") | K53: =COUNTIFS(Data!$A:$A,">="&'Reporte SDR General'!$C$3,Data!$A:$A,"<="&'Reporte SDR General'!$D$3,Data!$E:$E,D53,Data!$BG:$BG,$H$5) -> 0 | L53: =IFERROR(K53/$D$49,0) -> 0 | M53: =iferror(K53/'PT Reporte SDR'!K76-1,"") | N53: =COUNTIFS(Data!$A:$A,">="&'Reporte SDR General'!$C$3,Data!$A:$A,"<="&'Reporte SDR General'!$D$3,Data!$E:$E,E53,Data!$BG:$BG,$H$5) -> 0 | O53: =IFERROR(N53/$D$49,0) -> 0 | P53: =iferror(N53/'PT Reporte SDR'!N76-1,"")
C54: Contestó Whatsapp 2 | D54: =sum(H54) -> 0 | E54: =IFERROR(D54/$D$49,0) -> 0 | F54: =iferror(D54/'PT Reporte SDR'!D77-1,"") | H54: =COUNTIFS(Data!$A:$A,">="&'Reporte SDR General'!$C$3,Data!$A:$A,"<="&'Reporte SDR General'!$D$3,Data!$Y:$Y,C54) -> 0 | I54: =IFERROR(H54/$D$49,0) -> 0 | J54: =iferror(H54/'PT Reporte SDR'!H77-1,"") | K54: =COUNTIFS(Data!$A:$A,">="&'Reporte SDR General'!$C$3,Data!$A:$A,"<="&'Reporte SDR General'!$D$3,Data!$E:$E,D54,Data!$BG:$BG,$H$5) -> 0 | L54: =IFERROR(K54/$D$49,0) -> 0 | M54: =iferror(K54/'PT Reporte SDR'!K77-1,"") | N54: =COUNTIFS(Data!$A:$A,">="&'Reporte SDR General'!$C$3,Data!$A:$A,"<="&'Reporte SDR General'!$D$3,Data!$E:$E,E54,Data!$BG:$BG,$H$5) -> 0 | O54: =IFERROR(N54/$D$49,0) -> 0 | P54: =iferror(N54/'PT Reporte SDR'!N77-1,"")
C55: Contestó Whatsapp 3 | D55: =sum(H55) -> 0 | E55: =IFERROR(D55/$D$49,0) -> 0 | F55: =iferror(D55/'PT Reporte SDR'!D78-1,"") | H55: =COUNTIFS(Data!$A:$A,">="&'Reporte SDR General'!$C$3,Data!$A:$A,"<="&'Reporte SDR General'!$D$3,Data!$Y:$Y,C55) -> 0 | I55: =IFERROR(H55/$D$49,0) -> 0 | J55: =iferror(H55/'PT Reporte SDR'!H78-1,"") | K55: =COUNTIFS(Data!$A:$A,">="&'Reporte SDR General'!$C$3,Data!$A:$A,"<="&'Reporte SDR General'!$D$3,Data!$E:$E,D55,Data!$BG:$BG,$H$5) -> 0 | L55: =IFERROR(K55/$D$49,0) -> 0 | M55: =iferror(K55/'PT Reporte SDR'!K78-1,"") | N55: =COUNTIFS(Data!$A:$A,">="&'Reporte SDR General'!$C$3,Data!$A:$A,"<="&'Reporte SDR General'!$D$3,Data!$E:$E,E55,Data!$BG:$BG,$H$5) -> 0 | O55: =IFERROR(N55/$D$49,0) -> 0 | P55: =iferror(N55/'PT Reporte SDR'!N78-1,"")
C56: Contestó Correo 1 | D56: =sum(H56) -> 0 | E56: =IFERROR(D56/$D$49,0) -> 0 | F56: =iferror(D56/'PT Reporte SDR'!D79-1,"") | H56: =COUNTIFS(Data!$A:$A,">="&'Reporte SDR General'!$C$3,Data!$A:$A,"<="&'Reporte SDR General'!$D$3,Data!$Y:$Y,C56) -> 0 | I56: =IFERROR(H56/$D$49,0) -> 0 | J56: =iferror(H56/'PT Reporte SDR'!H79-1,"") | K56: =COUNTIFS(Data!$A:$A,">="&'Reporte SDR General'!$C$3,Data!$A:$A,"<="&'Reporte SDR General'!$D$3,Data!$E:$E,D56,Data!$BG:$BG,$H$5) -> 0 | L56: =IFERROR(K56/$D$49,0) -> 0 | M56: =iferror(K56/'PT Reporte SDR'!K79-1,"") | N56: =COUNTIFS(Data!$A:$A,">="&'Reporte SDR General'!$C$3,Data!$A:$A,"<="&'Reporte SDR General'!$D$3,Data!$E:$E,E56,Data!$BG:$BG,$H$5) -> 0 | O56: =IFERROR(N56/$D$49,0) -> 0 | P56: =iferror(N56/'PT Reporte SDR'!N79-1,"")
C57: Contestó Correo 2 | D57: =sum(H57) -> 0 | E57: =IFERROR(D57/$D$49,0) -> 0 | F57: =iferror(D57/'PT Reporte SDR'!D80-1,"") | H57: =COUNTIFS(Data!$A:$A,">="&'Reporte SDR General'!$C$3,Data!$A:$A,"<="&'Reporte SDR General'!$D$3,Data!$Y:$Y,C57) -> 0 | I57: =IFERROR(H57/$D$49,0) -> 0 | J57: =iferror(H57/'PT Reporte SDR'!H80-1,"") | K57: =COUNTIFS(Data!$A:$A,">="&'Reporte SDR General'!$C$3,Data!$A:$A,"<="&'Reporte SDR General'!$D$3,Data!$E:$E,D57,Data!$BG:$BG,$H$5) -> 0 | L57: =IFERROR(K57/$D$49,0) -> 0 | M57: =iferror(K57/'PT Reporte SDR'!K80-1,"") | N57: =COUNTIFS(Data!$A:$A,">="&'Reporte SDR General'!$C$3,Data!$A:$A,"<="&'Reporte SDR General'!$D$3,Data!$E:$E,E57,Data!$BG:$BG,$H$5) -> 0 | O57: =IFERROR(N57/$D$49,0) -> 0 | P57: =iferror(N57/'PT Reporte SDR'!N80-1,"")
C58: Contestó Correo 3 | D58: =sum(H58) -> 0 | E58: =IFERROR(D58/$D$49,0) -> 0 | F58: =iferror(D58/'PT Reporte SDR'!D81-1,"") | H58: =COUNTIFS(Data!$A:$A,">="&'Reporte SDR General'!$C$3,Data!$A:$A,"<="&'Reporte SDR General'!$D$3,Data!$Y:$Y,C58) -> 0 | I58: =IFERROR(H58/$D$49,0) -> 0 | J58: =iferror(H58/'PT Reporte SDR'!H81-1,"") | K58: =COUNTIFS(Data!$A:$A,">="&'Reporte SDR General'!$C$3,Data!$A:$A,"<="&'Reporte SDR General'!$D$3,Data!$E:$E,D58,Data!$BG:$BG,$H$5) -> 0 | L58: =IFERROR(K58/$D$49,0) -> 0 | M58: =iferror(K58/'PT Reporte SDR'!K81-1,"") | N58: =COUNTIFS(Data!$A:$A,">="&'Reporte SDR General'!$C$3,Data!$A:$A,"<="&'Reporte SDR General'!$D$3,Data!$E:$E,E58,Data!$BG:$BG,$H$5) -> 0 | O58: =IFERROR(N58/$D$49,0) -> 0 | P58: =iferror(N58/'PT Reporte SDR'!N81-1,"")
C59: Contestó Correo 4 | D59: =sum(H59) -> 0 | E59: =IFERROR(D59/$D$49,0) -> 0 | F59: =iferror(D59/'PT Reporte SDR'!D82-1,"") | H59: =COUNTIFS(Data!$A:$A,">="&'Reporte SDR General'!$C$3,Data!$A:$A,"<="&'Reporte SDR General'!$D$3,Data!$Y:$Y,C59) -> 0 | I59: =IFERROR(H59/$D$49,0) -> 0 | J59: =iferror(H59/'PT Reporte SDR'!H82-1,"") | K59: =COUNTIFS(Data!$A:$A,">="&'Reporte SDR General'!$C$3,Data!$A:$A,"<="&'Reporte SDR General'!$D$3,Data!$E:$E,D59,Data!$BG:$BG,$H$5) -> 0 | L59: =IFERROR(K59/$D$49,0) -> 0 | M59: =iferror(K59/'PT Reporte SDR'!K82-1,"") | N59: =COUNTIFS(Data!$A:$A,">="&'Reporte SDR General'!$C$3,Data!$A:$A,"<="&'Reporte SDR General'!$D$3,Data!$E:$E,E59,Data!$BG:$BG,$H$5) -> 0 | O59: =IFERROR(N59/$D$49,0) -> 0 | P59: =iferror(N59/'PT Reporte SDR'!N82-1,"")
F60: =iferror(D60/'PT Reporte SDR'!D83-1,"") | J60: =iferror(H60/'PT Reporte SDR'!H83-1,"") | M60: =iferror(K60/'PT Reporte SDR'!K83-1,"") | P60: =iferror(N60/'PT Reporte SDR'!N83-1,"")
F61: =iferror(D61/'PT Reporte SDR'!D84-1,"") | J61: =iferror(H61/'PT Reporte SDR'!H84-1,"") | M61: =iferror(K61/'PT Reporte SDR'!K84-1,"") | P61: =iferror(N61/'PT Reporte SDR'!N84-1,"")
C62: Total Lead en Proceso de Contacto (aún sin respuesta) | D62: =SUM(D63:D70) -> 0 | E62: % Total | F62: =iferror(D62/'PT Reporte SDR'!D85-1,"") | H62: =SUM(H63:H70) -> 0 | I62: % Total | J62: =iferror(H62/'PT Reporte SDR'!H85-1,"") | K62: =SUM(K63:K70) -> 0 | L62: % Total | M62: =iferror(K62/'PT Reporte SDR'!K85-1,"") | N62: =SUM(N63:N70) -> 0 | O62: % Total | P62: =iferror(N62/'PT Reporte SDR'!N85-1,"")
C63: No Contestó Teléfono 1 | D63: =sum(H63) -> 0 | E63: =iferror(D63/$D$62,0) -> 0 | F63: =iferror(D63/'PT Reporte SDR'!D86-1,"") | H63: =COUNTIFS(Data!$A:$A,">="&'Reporte SDR General'!$C$3,Data!$A:$A,"<="&'Reporte SDR General'!$D$3,Data!$Y:$Y,C63) -> 0 | I63: =iferror(H63/$D$62,0) -> 0 | J63: =iferror(H63/'PT Reporte SDR'!H86-1,"") | K63: =COUNTIFS(Data!$A:$A,">="&'Reporte SDR General'!$C$3,Data!$A:$A,"<="&'Reporte SDR General'!$D$3,Data!$E:$E,D63,Data!$BG:$BG,$H$5) -> 0 | L63: =iferror(K63/$D$62,0) -> 0 | M63: =iferror(K63/'PT Reporte SDR'!K86-1,"") | N63: =COUNTIFS(Data!$A:$A,">="&'Reporte SDR General'!$C$3,Data!$A:$A,"<="&'Reporte SDR General'!$D$3,Data!$E:$E,E63,Data!$BG:$BG,$H$5) -> 0 | O63: =iferror(N63/$D$62,0) -> 0 | P63: =iferror(N63/'PT Reporte SDR'!N86-1,"")
C64: No Contestó Teléfono 2 | D64: =sum(H64) -> 0 | E64: =iferror(D64/$D$62,0) -> 0 | F64: =iferror(D64/'PT Reporte SDR'!D87-1,"") | H64: =COUNTIFS(Data!$A:$A,">="&'Reporte SDR General'!$C$3,Data!$A:$A,"<="&'Reporte SDR General'!$D$3,Data!$Y:$Y,C64) -> 0 | I64: =iferror(H64/$D$62,0) -> 0 | J64: =iferror(H64/'PT Reporte SDR'!H87-1,"") | K64: =COUNTIFS(Data!$A:$A,">="&'Reporte SDR General'!$C$3,Data!$A:$A,"<="&'Reporte SDR General'!$D$3,Data!$E:$E,D64,Data!$BG:$BG,$H$5) -> 0 | L64: =iferror(K64/$D$62,0) -> 0 | M64: =iferror(K64/'PT Reporte SDR'!K87-1,"") | N64: =COUNTIFS(Data!$A:$A,">="&'Reporte SDR General'!$C$3,Data!$A:$A,"<="&'Reporte SDR General'!$D$3,Data!$E:$E,E64,Data!$BG:$BG,$H$5) -> 0 | O64: =iferror(N64/$D$62,0) -> 0 | P64: =iferror(N64/'PT Reporte SDR'!N87-1,"")
C65: No Contesto Teléfono 3 | D65: =sum(H65) -> 0 | E65: =iferror(D65/$D$62,0) -> 0 | F65: =iferror(D65/'PT Reporte SDR'!D88-1,"") | H65: =COUNTIFS(Data!$A:$A,">="&'Reporte SDR General'!$C$3,Data!$A:$A,"<="&'Reporte SDR General'!$D$3,Data!$Y:$Y,C65) -> 0 | I65: =iferror(H65/$D$62,0) -> 0 | J65: =iferror(H65/'PT Reporte SDR'!H88-1,"") | K65: =COUNTIFS(Data!$A:$A,">="&'Reporte SDR General'!$C$3,Data!$A:$A,"<="&'Reporte SDR General'!$D$3,Data!$E:$E,D65,Data!$BG:$BG,$H$5) -> 0 | L65: =iferror(K65/$D$62,0) -> 0 | M65: =iferror(K65/'PT Reporte SDR'!K88-1,"") | N65: =COUNTIFS(Data!$A:$A,">="&'Reporte SDR General'!$C$3,Data!$A:$A,"<="&'Reporte SDR General'!$D$3,Data!$E:$E,E65,Data!$BG:$BG,$H$5) -> 0 | O65: =iferror(N65/$D$62,0) -> 0 | P65: =iferror(N65/'PT Reporte SDR'!N88-1,"")
C66: No Contestó Whatsapp 1 | D66: =sum(H66) -> 0 | E66: =iferror(D66/$D$62,0) -> 0 | F66: =iferror(D66/'PT Reporte SDR'!D89-1,"") | H66: =COUNTIFS(Data!$A:$A,">="&'Reporte SDR General'!$C$3,Data!$A:$A,"<="&'Reporte SDR General'!$D$3,Data!$Y:$Y,C66) -> 0 | I66: =iferror(H66/$D$62,0) -> 0 | J66: =iferror(H66/'PT Reporte SDR'!H89-1,"") | K66: =COUNTIFS(Data!$A:$A,">="&'Reporte SDR General'!$C$3,Data!$A:$A,"<="&'Reporte SDR General'!$D$3,Data!$E:$E,D66,Data!$BG:$BG,$H$5) -> 0 | L66: =iferror(K66/$D$62,0) -> 0 | M66: =iferror(K66/'PT Reporte SDR'!K89-1,"") | N66: =COUNTIFS(Data!$A:$A,">="&'Reporte SDR General'!$C$3,Data!$A:$A,"<="&'Reporte SDR General'!$D$3,Data!$E:$E,E66,Data!$BG:$BG,$H$5) -> 0 | O66: =iferror(N66/$D$62,0) -> 0 | P66: =iferror(N66/'PT Reporte SDR'!N89-1,"")
C67: No Contestó Whatsapp 2 | D67: =sum(H67) -> 0 | E67: =iferror(D67/$D$62,0) -> 0 | F67: =iferror(D67/'PT Reporte SDR'!D90-1,"") | H67: =COUNTIFS(Data!$A:$A,">="&'Reporte SDR General'!$C$3,Data!$A:$A,"<="&'Reporte SDR General'!$D$3,Data!$Y:$Y,C67) -> 0 | I67: =iferror(H67/$D$62,0) -> 0 | J67: =iferror(H67/'PT Reporte SDR'!H90-1,"") | K67: =COUNTIFS(Data!$A:$A,">="&'Reporte SDR General'!$C$3,Data!$A:$A,"<="&'Reporte SDR General'!$D$3,Data!$E:$E,D67,Data!$BG:$BG,$H$5) -> 0 | L67: =iferror(K67/$D$62,0) -> 0 | M67: =iferror(K67/'PT Reporte SDR'!K90-1,"") | N67: =COUNTIFS(Data!$A:$A,">="&'Reporte SDR General'!$C$3,Data!$A:$A,"<="&'Reporte SDR General'!$D$3,Data!$E:$E,E67,Data!$BG:$BG,$H$5) -> 0 | O67: =iferror(N67/$D$62,0) -> 0 | P67: =iferror(N67/'PT Reporte SDR'!N90-1,"")
C68: No Contestó Whatsapp 3 | D68: =sum(H68) -> 0 | E68: =iferror(D68/$D$62,0) -> 0 | F68: =iferror(D68/'PT Reporte SDR'!D91-1,"") | H68: =COUNTIFS(Data!$A:$A,">="&'Reporte SDR General'!$C$3,Data!$A:$A,"<="&'Reporte SDR General'!$D$3,Data!$Y:$Y,C68) -> 0 | I68: =iferror(H68/$D$62,0) -> 0 | J68: =iferror(H68/'PT Reporte SDR'!H91-1,"") | K68: =COUNTIFS(Data!$A:$A,">="&'Reporte SDR General'!$C$3,Data!$A:$A,"<="&'Reporte SDR General'!$D$3,Data!$E:$E,D68,Data!$BG:$BG,$H$5) -> 0 | L68: =iferror(K68/$D$62,0) -> 0 | M68: =iferror(K68/'PT Reporte SDR'!K91-1,"") | N68: =COUNTIFS(Data!$A:$A,">="&'Reporte SDR General'!$C$3,Data!$A:$A,"<="&'Reporte SDR General'!$D$3,Data!$E:$E,E68,Data!$BG:$BG,$H$5) -> 0 | O68: =iferror(N68/$D$62,0) -> 0 | P68: =iferror(N68/'PT Reporte SDR'!N91-1,"")
F69: =iferror(D69/'PT Reporte SDR'!D92-1,"") | J69: =iferror(H69/'PT Reporte SDR'!H92-1,"") | M69: =iferror(K69/'PT Reporte SDR'!K92-1,"") | P69: =iferror(N69/'PT Reporte SDR'!N92-1,"")
F70: =iferror(D70/'PT Reporte SDR'!D93-1,"") | J70: =iferror(H70/'PT Reporte SDR'!H93-1,"") | M70: =iferror(K70/'PT Reporte SDR'!K93-1,"") | P70: =iferror(N70/'PT Reporte SDR'!N93-1,"")
F71: =iferror(D71/'PT Reporte SDR'!D94-1,"") | J71: =iferror(H71/'PT Reporte SDR'!H94-1,"") | M71: =iferror(K71/'PT Reporte SDR'!K94-1,"") | P71: =iferror(N71/'PT Reporte SDR'!N94-1,"")
C72: Total Leads Contactados sin Respuesta (6to Toque) | D72: =SUM(D73:D74) -> 0 | E72: % Total | F72: =iferror(D72/'PT Reporte SDR'!D95-1,"") | H72: =SUM(H73:H74) -> 0 | I72: % Total | J72: =iferror(H72/'PT Reporte SDR'!H95-1,"") | K72: =SUM(K73:K74) -> 0 | L72: % Total | M72: =iferror(K72/'PT Reporte SDR'!K95-1,"") | N72: =SUM(N73:N74) -> 0 | O72: % Total | P72: =iferror(N72/'PT Reporte SDR'!N95-1,"")
C73: Toque 6 | D73: =sum(H73) -> 0 | E73: =IFERROR(D73/$D$72,0) -> 0 | F73: =iferror(D73/'PT Reporte SDR'!D96-1,"") | H73: =COUNTIFS(Data!$A:$A,">="&'Reporte SDR General'!$C$3,Data!$A:$A,"<="&'Reporte SDR General'!$D$3,Data!$AE:$AE,C73) -> 0 | I73: =IFERROR(H73/$D$72,0) -> 0 | J73: =iferror(H73/'PT Reporte SDR'!H96-1,"") | L73: =IFERROR(K73/$D$72,0) -> 0 | M73: =iferror(K73/'PT Reporte SDR'!K96-1,"") | O73: =IFERROR(N73/$D$72,0) -> 0 | P73: =iferror(N73/'PT Reporte SDR'!N96-1,"")
F74: =iferror(D74/'PT Reporte SDR'!D97-1,"") | J74: =iferror(H74/'PT Reporte SDR'!H97-1,"") | M74: =iferror(K74/'PT Reporte SDR'!K97-1,"") | P74: =iferror(N74/'PT Reporte SDR'!N97-1,"")
F75: =iferror(D75/'PT Reporte SDR'!D98-1,"") | J75: =iferror(H75/'PT Reporte SDR'!H98-1,"") | M75: =iferror(K75/'PT Reporte SDR'!K98-1,"") | P75: =iferror(N75/'PT Reporte SDR'!N98-1,"")
C76: ¿Por Qué No Pasó a Ventas? | D76: =sum(D77:D117) -> 17 | E76: % | F76: =iferror(D76/'PT Reporte SDR'!D99-1,"") | H76: =SUM(H77:H117) -> 0 | I76: % | J76: =iferror(H76/'PT Reporte SDR'!H99-1,"") | K76: =SUM(K77:K117) -> 0 | L76: % | M76: =iferror(K76/'PT Reporte SDR'!K99-1,"") | N76: =SUM(N77:N117) -> 0 | O76: % | P76: =iferror(N76/'PT Reporte SDR'!N99-1,"")
C77: Toque 6 | D77: =H77+K77+N77 -> 0 | E77: =D77/$D$76 -> 0 | F77: =iferror(D77/'PT Reporte SDR'!D100-1,"") | H77: =COUNTIFS(Data!$A:$A,">="&'Reporte SDR General'!$C$3,Data!$A:$A,"<="&'Reporte SDR General'!$D$3,Data!$AD:$AD,C77) -> 0 | I77: =H77/$D$76 -> 0 | J77: =iferror(H77/'PT Reporte SDR'!H100-1,"") | K77: =COUNTIFS(Data!$A:$A,">="&'Reporte SDR General'!$C$3,Data!$A:$A,"<="&'Reporte SDR General'!$D$3,Data!$BI:$BI,$H$5,Data!$DF:$DF,C77) -> 0 | L77: =K77/$D$76 -> 0 | M77: =iferror(K77/'PT Reporte SDR'!K100-1,"") | N77: =COUNTIFS(Data!$A:$A,">="&'Reporte SDR General'!$C$3,Data!$A:$A,"<="&'Reporte SDR General'!$D$3,Data!$BI:$BI,$H$5,Data!$DF:$DF,C77) -> 0 | O77: =N77/$D$76 -> 0 | P77: =iferror(N77/'PT Reporte SDR'!N100-1,"")
C78: Nunca Respondió | D78: =H78+K78+N78 -> 0 | E78: =D78/$D$76 -> 0 | F78: =iferror(D78/'PT Reporte SDR'!D101-1,"") | H78: =COUNTIFS(Data!$A:$A,">="&'Reporte SDR General'!$C$3,Data!$A:$A,"<="&'Reporte SDR General'!$D$3,Data!$AD:$AD,C78) -> 0 | I78: =H78/$D$76 -> 0 | J78: =iferror(H78/'PT Reporte SDR'!H101-1,"") | K78: =COUNTIFS(Data!$A:$A,">="&'Reporte SDR General'!$C$3,Data!$A:$A,"<="&'Reporte SDR General'!$D$3,Data!$BI:$BI,$H$5,Data!$DF:$DF,C78) -> 0 | L78: =K78/$D$76 -> 0 | M78: =iferror(K78/'PT Reporte SDR'!K101-1,"") | N78: =COUNTIFS(Data!$A:$A,">="&'Reporte SDR General'!$C$3,Data!$A:$A,"<="&'Reporte SDR General'!$D$3,Data!$BI:$BI,$H$5,Data!$DF:$DF,C78) -> 0 | O78: =N78/$D$76 -> 0 | P78: =iferror(N78/'PT Reporte SDR'!N101-1,"")
C79: Dejó de responder | D79: =H79+K79+N79+2 -> 2 | E79: =D79/$D$76 -> 0.11764706 | F79: =iferror(D79/'PT Reporte SDR'!D102-1,"") | H79: =COUNTIFS(Data!$A:$A,">="&'Reporte SDR General'!$C$3,Data!$A:$A,"<="&'Reporte SDR General'!$D$3,Data!$AD:$AD,C79) -> 0 | I79: =H79/$D$76 -> 0 | J79: =iferror(H79/'PT Reporte SDR'!H102-1,"") | K79: =COUNTIFS(Data!$A:$A,">="&'Reporte SDR General'!$C$3,Data!$A:$A,"<="&'Reporte SDR General'!$D$3,Data!$BI:$BI,$H$5,Data!$DF:$DF,C79) -> 0 | L79: =K79/$D$76 -> 0 | M79: =iferror(K79/'PT Reporte SDR'!K102-1,"") | N79: =COUNTIFS(Data!$A:$A,">="&'Reporte SDR General'!$C$3,Data!$A:$A,"<="&'Reporte SDR General'!$D$3,Data!$BI:$BI,$H$5,Data!$DF:$DF,C79) -> 0 | O79: =N79/$D$76 -> 0 | P79: =iferror(N79/'PT Reporte SDR'!N102-1,"")
C80: No tuvo más interés | D80: =H80+K80+N80+8 -> 8 | E80: =D80/$D$76 -> 0.47058824 | F80: =iferror(D80/'PT Reporte SDR'!D103-1,"") | H80: =COUNTIFS(Data!$A:$A,">="&'Reporte SDR General'!$C$3,Data!$A:$A,"<="&'Reporte SDR General'!$D$3,Data!$AD:$AD,C80) -> 0 | I80: =H80/$D$76 -> 0 | J80: =iferror(H80/'PT Reporte SDR'!H103-1,"") | K80: =COUNTIFS(Data!$A:$A,">="&'Reporte SDR General'!$C$3,Data!$A:$A,"<="&'Reporte SDR General'!$D$3,Data!$BI:$BI,$H$5,Data!$DF:$DF,C80) -> 0 | L80: =K80/$D$76 -> 0 | M80: =iferror(K80/'PT Reporte SDR'!K103-1,"") | N80: =COUNTIFS(Data!$A:$A,">="&'Reporte SDR General'!$C$3,Data!$A:$A,"<="&'Reporte SDR General'!$D$3,Data!$BI:$BI,$H$5,Data!$DF:$DF,C80) -> 0 | O80: =N80/$D$76 -> 0 | P80: =iferror(N80/'PT Reporte SDR'!N103-1,"")
C81: Desconoce el registro | D81: =H81+K81+N81 -> 0 | E81: =D81/$D$76 -> 0 | F81: =iferror(D81/'PT Reporte SDR'!D104-1,"") | H81: =COUNTIFS(Data!$A:$A,">="&'Reporte SDR General'!$C$3,Data!$A:$A,"<="&'Reporte SDR General'!$D$3,Data!$AD:$AD,C81) -> 0 | I81: =H81/$D$76 -> 0 | J81: =iferror(H81/'PT Reporte SDR'!H104-1,"") | K81: =COUNTIFS(Data!$A:$A,">="&'Reporte SDR General'!$C$3,Data!$A:$A,"<="&'Reporte SDR General'!$D$3,Data!$BI:$BI,$H$5,Data!$DF:$DF,C81) -> 0 | L81: =K81/$D$76 -> 0 | M81: =iferror(K81/'PT Reporte SDR'!K104-1,"") | N81: =COUNTIFS(Data!$A:$A,">="&'Reporte SDR General'!$C$3,Data!$A:$A,"<="&'Reporte SDR General'!$D$3,Data!$BI:$BI,$H$5,Data!$DF:$DF,C81) -> 0 | O81: =N81/$D$76 -> 0 | P81: =iferror(N81/'PT Reporte SDR'!N104-1,"")
C82: Ya resolvió su necesidad | D82: =H82+K82+N82+1 -> 1 | E82: =D82/$D$76 -> 0.058823529 | F82: =iferror(D82/'PT Reporte SDR'!D105-1,"") | H82: =COUNTIFS(Data!$A:$A,">="&'Reporte SDR General'!$C$3,Data!$A:$A,"<="&'Reporte SDR General'!$D$3,Data!$AD:$AD,C82) -> 0 | I82: =H82/$D$76 -> 0 | J82: =iferror(H82/'PT Reporte SDR'!H105-1,"") | K82: =COUNTIFS(Data!$A:$A,">="&'Reporte SDR General'!$C$3,Data!$A:$A,"<="&'Reporte SDR General'!$D$3,Data!$BI:$BI,$H$5,Data!$DF:$DF,C82) -> 0 | L82: =K82/$D$76 -> 0 | M82: =iferror(K82/'PT Reporte SDR'!K105-1,"") | N82: =COUNTIFS(Data!$A:$A,">="&'Reporte SDR General'!$C$3,Data!$A:$A,"<="&'Reporte SDR General'!$D$3,Data!$BI:$BI,$H$5,Data!$DF:$DF,C82) -> 0 | O82: =N82/$D$76 -> 0 | P82: =iferror(N82/'PT Reporte SDR'!N105-1,"")
C83: No se cuenta con el servicio | D83: =H83+K83+N83 -> 0 | E83: =D83/$D$76 -> 0 | F83: =iferror(D83/'PT Reporte SDR'!D106-1,"") | H83: =COUNTIFS(Data!$A:$A,">="&'Reporte SDR General'!$C$3,Data!$A:$A,"<="&'Reporte SDR General'!$D$3,Data!$AD:$AD,C83) -> 0 | I83: =H83/$D$76 -> 0 | J83: =iferror(H83/'PT Reporte SDR'!H106-1,"") | K83: =COUNTIFS(Data!$A:$A,">="&'Reporte SDR General'!$C$3,Data!$A:$A,"<="&'Reporte SDR General'!$D$3,Data!$BI:$BI,$H$5,Data!$DF:$DF,C83) -> 0 | L83: =K83/$D$76 -> 0 | M83: =iferror(K83/'PT Reporte SDR'!K106-1,"") | N83: =COUNTIFS(Data!$A:$A,">="&'Reporte SDR General'!$C$3,Data!$A:$A,"<="&'Reporte SDR General'!$D$3,Data!$BI:$BI,$H$5,Data!$DF:$DF,C83) -> 0 | O83: =N83/$D$76 -> 0 | P83: =iferror(N83/'PT Reporte SDR'!N106-1,"")
C84: Busca ser proveedor | D84: =H84+K84+N84+1 -> 1 | E84: =D84/$D$76 -> 0.058823529 | F84: =iferror(D84/'PT Reporte SDR'!D107-1,"") | H84: =COUNTIFS(Data!$A:$A,">="&'Reporte SDR General'!$C$3,Data!$A:$A,"<="&'Reporte SDR General'!$D$3,Data!$AE:$AE,C84) -> 0 | I84: =H84/$D$76 -> 0 | J84: =iferror(H84/'PT Reporte SDR'!H107-1,"") | K84: =COUNTIFS(Data!$A:$A,">="&'Reporte SDR General'!$C$3,Data!$A:$A,"<="&'Reporte SDR General'!$D$3,Data!$BI:$BI,$H$5,Data!$DF:$DF,C84) -> 0 | L84: =K84/$D$76 -> 0 | M84: =iferror(K84/'PT Reporte SDR'!K107-1,"") | N84: =COUNTIFS(Data!$A:$A,">="&'Reporte SDR General'!$C$3,Data!$A:$A,"<="&'Reporte SDR General'!$D$3,Data!$BI:$BI,$H$5,Data!$DF:$DF,C84) -> 0 | O84: =N84/$D$76 -> 0 | P84: =iferror(N84/'PT Reporte SDR'!N107-1,"")
C85: Busca empleo | D85: =H85+K85+N85+1 -> 1 | E85: =D85/$D$76 -> 0.058823529 | F85: =iferror(D85/'PT Reporte SDR'!D108-1,"") | H85: =COUNTIFS(Data!$A:$A,">="&'Reporte SDR General'!$C$3,Data!$A:$A,"<="&'Reporte SDR General'!$D$3,Data!$AD:$AD,C85) -> 0 | I85: =H85/$D$76 -> 0 | J85: =iferror(H85/'PT Reporte SDR'!H108-1,"") | K85: =COUNTIFS(Data!$A:$A,">="&'Reporte SDR General'!$C$3,Data!$A:$A,"<="&'Reporte SDR General'!$D$3,Data!$BI:$BI,$H$5,Data!$DF:$DF,C85) -> 0 | L85: =K85/$D$76 -> 0 | M85: =iferror(K85/'PT Reporte SDR'!K108-1,"") | N85: =COUNTIFS(Data!$A:$A,">="&'Reporte SDR General'!$C$3,Data!$A:$A,"<="&'Reporte SDR General'!$D$3,Data!$BI:$BI,$H$5,Data!$DF:$DF,C85) -> 0 | O85: =N85/$D$76 -> 0 | P85: =iferror(N85/'PT Reporte SDR'!N108-1,"")
C86: Pidió no volver a llamar | D86: =H86+K86+N86 -> 0 | E86: =D86/$D$76 -> 0 | F86: =iferror(D86/'PT Reporte SDR'!D109-1,"") | H86: =COUNTIFS(Data!$A:$A,">="&'Reporte SDR General'!$C$3,Data!$A:$A,"<="&'Reporte SDR General'!$D$3,Data!$AD:$AD,C86) -> 0 | I86: =H86/$D$76 -> 0 | J86: =iferror(H86/'PT Reporte SDR'!H109-1,"") | K86: =COUNTIFS(Data!$A:$A,">="&'Reporte SDR General'!$C$3,Data!$A:$A,"<="&'Reporte SDR General'!$D$3,Data!$BI:$BI,$H$5,Data!$DF:$DF,C86) -> 0 | L86: =K86/$D$76 -> 0 | M86: =iferror(K86/'PT Reporte SDR'!K109-1,"") | N86: =COUNTIFS(Data!$A:$A,">="&'Reporte SDR General'!$C$3,Data!$A:$A,"<="&'Reporte SDR General'!$D$3,Data!$BI:$BI,$H$5,Data!$DF:$DF,C86) -> 0 | O86: =N86/$D$76 -> 0 | P86: =iferror(N86/'PT Reporte SDR'!N109-1,"")
C87: Motivos Personales | D87: =H87+K87+N87+4 -> 4 | E87: =D87/$D$76 -> 0.23529412 | F87: =iferror(D87/'PT Reporte SDR'!D110-1,"") | H87: =COUNTIFS(Data!$A:$A,">="&'Reporte SDR General'!$C$3,Data!$A:$A,"<="&'Reporte SDR General'!$D$3,Data!$AD:$AD,C87) -> 0 | I87: =H87/$D$76 -> 0 | J87: =iferror(H87/'PT Reporte SDR'!H110-1,"") | K87: =COUNTIFS(Data!$A:$A,">="&'Reporte SDR General'!$C$3,Data!$A:$A,"<="&'Reporte SDR General'!$D$3,Data!$BI:$BI,$H$5,Data!$DF:$DF,C87) -> 0 | L87: =K87/$D$76 -> 0 | M87: =iferror(K87/'PT Reporte SDR'!K110-1,"") | N87: =COUNTIFS(Data!$A:$A,">="&'Reporte SDR General'!$C$3,Data!$A:$A,"<="&'Reporte SDR General'!$D$3,Data!$BI:$BI,$H$5,Data!$DF:$DF,C87) -> 0 | O87: =N87/$D$76 -> 0 | P87: =iferror(N87/'PT Reporte SDR'!N110-1,"")
C88: No me llames, yo te llamo | D88: =H88+K88+N88 -> 0 | E88: =D88/$D$76 -> 0 | F88: =iferror(D88/'PT Reporte SDR'!D111-1,"") | H88: =COUNTIFS(Data!$A:$A,">="&'Reporte SDR General'!$C$3,Data!$A:$A,"<="&'Reporte SDR General'!$D$3,Data!$AD:$AD,C88) -> 0 | I88: =H88/$D$76 -> 0 | J88: =iferror(H88/'PT Reporte SDR'!H111-1,"") | K88: =COUNTIFS(Data!$A:$A,">="&'Reporte SDR General'!$C$3,Data!$A:$A,"<="&'Reporte SDR General'!$D$3,Data!$BI:$BI,$H$5,Data!$DF:$DF,C88) -> 0 | L88: =K88/$D$76 -> 0 | M88: =iferror(K88/'PT Reporte SDR'!K111-1,"") | N88: =COUNTIFS(Data!$A:$A,">="&'Reporte SDR General'!$C$3,Data!$A:$A,"<="&'Reporte SDR General'!$D$3,Data!$BI:$BI,$H$5,Data!$DF:$DF,C88) -> 0 | O88: =N88/$D$76 -> 0 | P88: =iferror(N88/'PT Reporte SDR'!N111-1,"")
F89: =iferror(D89/'PT Reporte SDR'!D112-1,"") | J89: =iferror(H89/'PT Reporte SDR'!H112-1,"") | M89: =iferror(K89/'PT Reporte SDR'!K112-1,"") | P89: =iferror(N89/'PT Reporte SDR'!N112-1,"")
F90: =iferror(D90/'PT Reporte SDR'!D113-1,"") | J90: =iferror(H90/'PT Reporte SDR'!H113-1,"") | M90: =iferror(K90/'PT Reporte SDR'!K113-1,"") | P90: =iferror(N90/'PT Reporte SDR'!N113-1,"")
C91: ¿Por qué se perdió la venta? | D91: =H91+K91+N91 -> 0 | E91: =D91/$D$76 -> 0 | F91: =iferror(D91/'PT Reporte SDR'!D114-1,"") | H91: =COUNTIFS(Data!$A:$A,">="&'Reporte SDR General'!$C$3,Data!$A:$A,"<="&'Reporte SDR General'!$D$3,Data!$BI:$BI,$H$5,Data!$DF:$DF,C91) -> 0 | I91: =H91/$D$76 -> 0 | J91: =iferror(H91/'PT Reporte SDR'!H114-1,"") | K91: =COUNTIFS(Data!$A:$A,">="&'Reporte SDR General'!$C$3,Data!$A:$A,"<="&'Reporte SDR General'!$D$3,Data!$BI:$BI,$H$5,Data!$DF:$DF,C91) -> 0 | L91: =K91/$D$76 -> 0 | M91: =iferror(K91/'PT Reporte SDR'!K114-1,"") | N91: =COUNTIFS(Data!$A:$A,">="&'Reporte SDR General'!$C$3,Data!$A:$A,"<="&'Reporte SDR General'!$D$3,Data!$BI:$BI,$H$5,Data!$DF:$DF,C91) -> 0 | O91: =N91/$D$76 -> 0 | P91: =iferror(N91/'PT Reporte SDR'!N114-1,"")
C92: No le interesó la cotización | D92: =H92+K92+N92 -> 0 | E92: =D92/$D$76 -> 0 | F92: =iferror(D92/'PT Reporte SDR'!D115-1,"") | H92: =COUNTIFS(Data!$A:$A,">="&'Reporte SDR General'!$C$3,Data!$A:$A,"<="&'Reporte SDR General'!$D$3,Data!$BR:$BR,C92) -> 0 | I92: =H92/$D$76 -> 0 | J92: =iferror(H92/'PT Reporte SDR'!H115-1,"") | K92: =COUNTIFS(Data!$A:$A,">="&'Reporte SDR General'!$C$3,Data!$A:$A,"<="&'Reporte SDR General'!$D$3,Data!$BI:$BI,$H$5,Data!$DF:$DF,C92) -> 0 | L92: =K92/$D$76 -> 0 | M92: =iferror(K92/'PT Reporte SDR'!K115-1,"") | N92: =COUNTIFS(Data!$A:$A,">="&'Reporte SDR General'!$C$3,Data!$A:$A,"<="&'Reporte SDR General'!$D$3,Data!$BI:$BI,$H$5,Data!$DF:$DF,C92) -> 0 | O92: =N92/$D$76 -> 0 | P92: =iferror(N92/'PT Reporte SDR'!N115-1,"")
C93: Le pareció costoso | D93: =H93+K93+N93 -> 0 | E93: =D93/$D$76 -> 0 | F93: =iferror(D93/'PT Reporte SDR'!D116-1,"") | H93: =COUNTIFS(Data!$A:$A,">="&'Reporte SDR General'!$C$3,Data!$A:$A,"<="&'Reporte SDR General'!$D$3,Data!$BR:$BR,C93) -> 0 | I93: =H93/$D$76 -> 0 | J93: =iferror(H93/'PT Reporte SDR'!H116-1,"") | K93: =COUNTIFS(Data!$A:$A,">="&'Reporte SDR General'!$C$3,Data!$A:$A,"<="&'Reporte SDR General'!$D$3,Data!$BI:$BI,$H$5,Data!$DF:$DF,C93) -> 0 | L93: =K93/$D$76 -> 0 | M93: =iferror(K93/'PT Reporte SDR'!K116-1,"") | N93: =COUNTIFS(Data!$A:$A,">="&'Reporte SDR General'!$C$3,Data!$A:$A,"<="&'Reporte SDR General'!$D$3,Data!$BI:$BI,$H$5,Data!$DF:$DF,C93) -> 0 | O93: =N93/$D$76 -> 0 | P93: =iferror(N93/'PT Reporte SDR'!N116-1,"")
C94: No tenía suficiente presupuesto | D94: =H94+K94+N94 -> 0 | E94: =D94/$D$76 -> 0 | F94: =iferror(D94/'PT Reporte SDR'!D117-1,"") | H94: =COUNTIFS(Data!$A:$A,">="&'Reporte SDR General'!$C$3,Data!$A:$A,"<="&'Reporte SDR General'!$D$3,Data!$BR:$BR,C94) -> 0 | I94: =H94/$D$76 -> 0 | J94: =iferror(H94/'PT Reporte SDR'!H117-1,"") | K94: =COUNTIFS(Data!$A:$A,">="&'Reporte SDR General'!$C$3,Data!$A:$A,"<="&'Reporte SDR General'!$D$3,Data!$BI:$BI,$H$5,Data!$DF:$DF,C94) -> 0 | L94: =K94/$D$76 -> 0 | M94: =iferror(K94/'PT Reporte SDR'!K117-1,"") | N94: =COUNTIFS(Data!$A:$A,">="&'Reporte SDR General'!$C$3,Data!$A:$A,"<="&'Reporte SDR General'!$D$3,Data!$BI:$BI,$H$5,Data!$DF:$DF,C94) -> 0 | O94: =N94/$D$76 -> 0 | P94: =iferror(N94/'PT Reporte SDR'!N117-1,"")
C95: Nunca recibimos respuesta | D95: =H95+K95+N95 -> 0 | E95: =D95/$D$76 -> 0 | F95: =iferror(D95/'PT Reporte SDR'!D118-1,"") | H95: =COUNTIFS(Data!$A:$A,">="&'Reporte SDR General'!$C$3,Data!$A:$A,"<="&'Reporte SDR General'!$D$3,Data!$BR:$BR,C95) -> 0 | I95: =H95/$D$76 -> 0 | J95: =iferror(H95/'PT Reporte SDR'!H118-1,"") | K95: =COUNTIFS(Data!$A:$A,">="&'Reporte SDR General'!$C$3,Data!$A:$A,"<="&'Reporte SDR General'!$D$3,Data!$BI:$BI,$H$5,Data!$DF:$DF,C95) -> 0 | L95: =K95/$D$76 -> 0 | M95: =iferror(K95/'PT Reporte SDR'!K118-1,"") | N95: =COUNTIFS(Data!$A:$A,">="&'Reporte SDR General'!$C$3,Data!$A:$A,"<="&'Reporte SDR General'!$D$3,Data!$BI:$BI,$H$5,Data!$DF:$DF,C95) -> 0 | O95: =N95/$D$76 -> 0 | P95: =iferror(N95/'PT Reporte SDR'!N118-1,"")
C96: Nunca envió información para cotización | D96: =H96+K96+N96 -> 0 | E96: =D96/$D$76 -> 0 | F96: =iferror(D96/'PT Reporte SDR'!D119-1,"") | H96: =COUNTIFS(Data!$A:$A,">="&'Reporte SDR General'!$C$3,Data!$A:$A,"<="&'Reporte SDR General'!$D$3,Data!$BR:$BR,C96) -> 0 | I96: =H96/$D$76 -> 0 | J96: =iferror(H96/'PT Reporte SDR'!H119-1,"") | K96: =COUNTIFS(Data!$A:$A,">="&'Reporte SDR General'!$C$3,Data!$A:$A,"<="&'Reporte SDR General'!$D$3,Data!$BI:$BI,$H$5,Data!$DF:$DF,C96) -> 0 | L96: =K96/$D$76 -> 0 | M96: =iferror(K96/'PT Reporte SDR'!K119-1,"") | N96: =COUNTIFS(Data!$A:$A,">="&'Reporte SDR General'!$C$3,Data!$A:$A,"<="&'Reporte SDR General'!$D$3,Data!$BI:$BI,$H$5,Data!$DF:$DF,C96) -> 0 | O96: =N96/$D$76 -> 0 | P96: =iferror(N96/'PT Reporte SDR'!N119-1,"")
C97: No lo logramos contactar | D97: =H97+K97+N97 -> 0 | E97: =D97/$D$76 -> 0 | F97: =iferror(D97/'PT Reporte SDR'!D120-1,"") | H97: =COUNTIFS(Data!$A:$A,">="&'Reporte SDR General'!$C$3,Data!$A:$A,"<="&'Reporte SDR General'!$D$3,Data!$BR:$BR,C97) -> 0 | I97: =H97/$D$76 -> 0 | J97: =iferror(H97/'PT Reporte SDR'!H120-1,"") | K97: =COUNTIFS(Data!$A:$A,">="&'Reporte SDR General'!$C$3,Data!$A:$A,"<="&'Reporte SDR General'!$D$3,Data!$BI:$BI,$H$5,Data!$DF:$DF,C97) -> 0 | L97: =K97/$D$76 -> 0 | M97: =iferror(K97/'PT Reporte SDR'!K120-1,"") | N97: =COUNTIFS(Data!$A:$A,">="&'Reporte SDR General'!$C$3,Data!$A:$A,"<="&'Reporte SDR General'!$D$3,Data!$BI:$BI,$H$5,Data!$DF:$DF,C97) -> 0 | O97: =N97/$D$76 -> 0 | P97: =iferror(N97/'PT Reporte SDR'!N120-1,"")
C98: Estaba solo investigando | D98: =H98+K98+N98 -> 0 | E98: =D98/$D$76 -> 0 | F98: =iferror(D98/'PT Reporte SDR'!D121-1,"") | H98: =COUNTIFS(Data!$A:$A,">="&'Reporte SDR General'!$C$3,Data!$A:$A,"<="&'Reporte SDR General'!$D$3,Data!$BR:$BR,C98) -> 0 | I98: =H98/$D$76 -> 0 | J98: =iferror(H98/'PT Reporte SDR'!H121-1,"") | K98: =COUNTIFS(Data!$A:$A,">="&'Reporte SDR General'!$C$3,Data!$A:$A,"<="&'Reporte SDR General'!$D$3,Data!$BI:$BI,$H$5,Data!$DF:$DF,C98) -> 0 | L98: =K98/$D$76 -> 0 | M98: =iferror(K98/'PT Reporte SDR'!K121-1,"") | N98: =COUNTIFS(Data!$A:$A,">="&'Reporte SDR General'!$C$3,Data!$A:$A,"<="&'Reporte SDR General'!$D$3,Data!$BI:$BI,$H$5,Data!$DF:$DF,C98) -> 0 | O98: =N98/$D$76 -> 0 | P98: =iferror(N98/'PT Reporte SDR'!N121-1,"")
C99: No cubre el perfil de salarios | D99: =H99+K99+N99 -> 0 | E99: =D99/$D$76 -> 0 | F99: =iferror(D99/'PT Reporte SDR'!D122-1,"") | H99: =COUNTIFS(Data!$A:$A,">="&'Reporte SDR General'!$C$3,Data!$A:$A,"<="&'Reporte SDR General'!$D$3,Data!$BR:$BR,C99) -> 0 | I99: =H99/$D$76 -> 0 | J99: =iferror(H99/'PT Reporte SDR'!H122-1,"") | K99: =COUNTIFS(Data!$A:$A,">="&'Reporte SDR General'!$C$3,Data!$A:$A,"<="&'Reporte SDR General'!$D$3,Data!$BI:$BI,$H$5,Data!$DF:$DF,C99) -> 0 | L99: =K99/$D$76 -> 0 | M99: =iferror(K99/'PT Reporte SDR'!K122-1,"") | N99: =COUNTIFS(Data!$A:$A,">="&'Reporte SDR General'!$C$3,Data!$A:$A,"<="&'Reporte SDR General'!$D$3,Data!$BI:$BI,$H$5,Data!$DF:$DF,C99) -> 0 | O99: =N99/$D$76 -> 0 | P99: =iferror(N99/'PT Reporte SDR'!N122-1,"")
C100: No se cuenta con los requerimientos del cliente | D100: =H100+K100+N100 -> 0 | E100: =D100/$D$76 -> 0 | F100: =iferror(D100/'PT Reporte SDR'!D123-1,"") | H100: =COUNTIFS(Data!$A:$A,">="&'Reporte SDR General'!$C$3,Data!$A:$A,"<="&'Reporte SDR General'!$D$3,Data!$BR:$BR,C100) -> 0 | I100: =H100/$D$76 -> 0 | J100: =iferror(H100/'PT Reporte SDR'!H123-1,"") | K100: =COUNTIFS(Data!$A:$A,">="&'Reporte SDR General'!$C$3,Data!$A:$A,"<="&'Reporte SDR General'!$D$3,Data!$BI:$BI,$H$5,Data!$DF:$DF,C100) -> 0 | L100: =K100/$D$76 -> 0 | M100: =iferror(K100/'PT Reporte SDR'!K123-1,"") | N100: =COUNTIFS(Data!$A:$A,">="&'Reporte SDR General'!$C$3,Data!$A:$A,"<="&'Reporte SDR General'!$D$3,Data!$BI:$BI,$H$5,Data!$DF:$DF,C100) -> 0 | O100: =N100/$D$76 -> 0 | P100: =iferror(N100/'PT Reporte SDR'!N123-1,"")
C101: No compagina con las políticas de la empresa | D101: =H101+K101+N101 -> 0 | E101: =D101/$D$76 -> 0 | F101: =iferror(D101/'PT Reporte SDR'!D124-1,"") | H101: =COUNTIFS(Data!$A:$A,">="&'Reporte SDR General'!$C$3,Data!$A:$A,"<="&'Reporte SDR General'!$D$3,Data!$BR:$BR,C101) -> 0 | I101: =H101/$D$76 -> 0 | J101: =iferror(H101/'PT Reporte SDR'!H124-1,"") | K101: =COUNTIFS(Data!$A:$A,">="&'Reporte SDR General'!$C$3,Data!$A:$A,"<="&'Reporte SDR General'!$D$3,Data!$BI:$BI,$H$5,Data!$DF:$DF,C101) -> 0 | L101: =K101/$D$76 -> 0 | M101: =iferror(K101/'PT Reporte SDR'!K124-1,"") | N101: =COUNTIFS(Data!$A:$A,">="&'Reporte SDR General'!$C$3,Data!$A:$A,"<="&'Reporte SDR General'!$D$3,Data!$BI:$BI,$H$5,Data!$DF:$DF,C101) -> 0 | O101: =N101/$D$76 -> 0 | P101: =iferror(N101/'PT Reporte SDR'!N124-1,"")
...

Sheet PT Reporte SDR
C2: Day In | D2: Day Out
C3: =EOMONTH('Reporte SDR General'!C3,-2)+92 -> 45930 | D3: =EDATE('Reporte SDR General'!D3, -1)+1 -> 45871
C4: =EOMONTH(C3,-2)+1 -> 45870 | D4: =EDATE(D3, -1) -> 45840
D5: TOTAL | E5: % | F5: Δ% vs PP | H5: Total | I5: Manufacturers | J5: Individuals
C6: Total Leads SDR | D6: =H6 -> 0 | F6: =iferror(D6/'Periodo Anterior'!D6-1,"") | H6: =COUNTIFS(Data!$A:$A,">="&'PT Reporte SDR'!$C$3,Data!$A:$A,"<="&'PT Reporte SDR'!$D$3) -> 0 | I6: =COUNTIFS(Data!$A:$A,">="&'PT Reporte SDR'!$C$3,Data!$A:$A,"<="&'PT Reporte SDR'!$D$3,Data!$BI:$BI,I5) -> 0 | J6: =COUNTIFS(Data!$A:$A,">="&'PT Reporte SDR'!$C$3,Data!$A:$A,"<="&'PT Reporte SDR'!$D$3,Data!$BI:$BI,J5) -> 0
C7: Total Leads Incontactables por base de datos | D7: =H7 -> 0 | E7: =iferror(D7/$D$6,"0%") -> 0% | F7: =iferror(D7/'Periodo Anterior'!D7-1,"") | H7: =H66 -> 0 | I7: =I66 -> 0 | J7: =J66 -> 0
C8: Total Leads Contactables | D8: =H8 -> 0 | E8: =iferror(D8/$D$6,"0%") -> 0% | F8: =iferror(D8/'Periodo Anterior'!D8-1,"") | H8: =H6-H7 -> 0 | I8: =I6-I7 -> 0 | J8: =J6-J7 -> 0
C9: Total Leads Contactados (con al menos 1 Toque) | D9: =H9 -> 0 | E9: =iferror(D9/D8,"0%") -> 0% | F9: =iferror(D9/'Periodo Anterior'!D9-1,"") | H9: =COUNTIFS(Data!$A:$A,">="&'PT Reporte SDR'!$C$3,Data!$A:$A,"<="&'PT Reporte SDR'!$D$3,Data!$Z:$Z,">0") -> 0 | I9: =COUNTIFS(Data!$A:$A,">="&'PT Reporte SDR'!$C$3,Data!$A:$A,"<="&'PT Reporte SDR'!$D$3,Data!$BI:$BI,I5,Data!$AT:$AT,"<>")-I7 -> 0 | J9: =COUNTIFS(Data!$A:$A,">="&'PT Reporte SDR'!$C$3,Data!$A:$A,"<="&'PT Reporte SDR'!$D$3,Data!$BI:$BI,J5,Data!$AT:$AT,"<>")-J7 -> 0
C10: Total Lead en Proceso de Contacto (aún sin respuesta) | D10: =H10 -> 71 | E10: =iferror(D10/$D$6,"0%") -> 0% | F10: =iferror(D10/'Periodo Anterior'!D10-1,"") | H10: 71 | I10: =COUNTIFS(Data!$A:$A,">="&'PT Reporte SDR'!$C$3,Data!$A:$A,"<="&'PT Reporte SDR'!$D$3,Data!$BI:$BI,I5,Data!$BK:$BK,"No respondio") -> 0 | J10: =COUNTIFS(Data!$A:$A,">="&'PT Reporte SDR'!$C$3,Data!$A:$A,"<="&'PT Reporte SDR'!$D$3,Data!$BI:$BI,J5,Data!$BK:$BK,"No respondio") -> 0
C11: Total Leads Contactados sin Respuesta (6to Toque o más) | D11: =H11 -> 0 | E11: =iferror(IFERROR(D11/D9,0),"") -> 0 | F11: =iferror(D11/'Periodo Anterior'!D11-1,"") | H11: =H96 -> 0 | I11: =COUNTIFS(Data!$A:$A,">="&'PT Reporte SDR'!$C$3,Data!$A:$A,"<="&'PT Reporte SDR'!$D$3,Data!$BI:$BI,I5,Data!$AT:$AT,">=6") -> 0 | J11: =COUNTIFS(Data!$A:$A,">="&'PT Reporte SDR'!$C$3,Data!$A:$A,"<="&'PT Reporte SDR'!$D$3,Data!$BI:$BI,J5,Data!$AT:$AT,">=6") -> 0
C12: Total Leads Contactados con Respuesta | D12: =H12 -> 0 | E12: =iferror(D12/D8,"0%") -> 0% | F12: =iferror(D12/'Periodo Anterior'!D12-1,"") | H12: =H72 -> 0 | I12: =COUNTIFS(Data!$A:$A,">="&'PT Reporte SDR'!$C$3,Data!$A:$A,"<="&'PT Reporte SDR'!$D$3,Data!$BI:$BI,I5,Data!$BK:$BK,"Pase a ventas")+COUNTIFS(Data!$A:$A,">="&'PT Reporte SDR'!$C$3,Data!$A:$A,"<="&'PT Reporte SDR'!$D$3,Data!$BI:$BI,I5,Data!$BK:$BK,"Descartado")+COUNTIFS(Data!$A:$A,">="&'PT Reporte SDR'!$C$3,Data!$A:$A,"<="&'PT Reporte SDR'!$D$3,Data!$BI:$BI,I5,Data!$BK:$BK,"Pidio llamar mas tarde")+COUNTIFS(Data!$A:$A,">="&'PT Reporte SDR'!$C$3,Data!$A:$A,"<="&'PT Reporte SDR'!$D$3,Data!$BI:$BI,I5,Data!$BK:$BK,"Contesta y Cuelga")+COUNTIFS(Data!$A:$A,">="&'PT Reporte SDR'!$C$3,Data!$A:$A,"<="&'PT Reporte SDR'!$D$3,Data!$BI:$BI,I5,Data!$BK:$BK,"Llamar mañana")+COUNTIFS(Data!$A:$A,">="&'PT Reporte SDR'!$C$3,Data!$A:$A,"<="&'PT Reporte SDR'!$D$3,Data!$BI:$BI,I5,Data!$BK:$BK,"SEGUIMIENTO") -> 0 | J12: =COUNTIFS(Data!$A:$A,">="&'PT Reporte SDR'!$C$3,Data!$A:$A,"<="&'PT Reporte SDR'!$D$3,Data!$BI:$BI,J5,Data!$BK:$BK,"Pase a ventas")+COUNTIFS(Data!$A:$A,">="&'PT Reporte SDR'!$C$3,Data!$A:$A,"<="&'PT Reporte SDR'!$D$3,Data!$BI:$BI,J5,Data!$BK:$BK,"Descartado")+COUNTIFS(Data!$A:$A,">="&'PT Reporte SDR'!$C$3,Data!$A:$A,"<="&'PT Reporte SDR'!$D$3,Data!$BI:$BI,J5,Data!$BK:$BK,"Pidio llamar mas tarde")+COUNTIFS(Data!$A:$A,">="&'PT Reporte SDR'!$C$3,Data!$A:$A,"<="&'PT Reporte SDR'!$D$3,Data!$BI:$BI,J5,Data!$BK:$BK,"Contesta y Cuelga")+COUNTIFS(Data!$A:$A,">="&'PT Reporte SDR'!$C$3,Data!$A:$A,"<="&'PT Reporte SDR'!$D$3,Data!$BI:$BI,J5,Data!$BK:$BK,"Llamar mañana")+COUNTIFS(Data!$A:$A,">="&'PT Reporte SDR'!$C$3,Data!$A:$A,"<="&'PT Reporte SDR'!$D$3,Data!$BI:$BI,J5,Data!$BK:$BK,"SEGUIMIENTO") -> 0
C13: Total Leads Con Dialogo Completo | D13: =H13 -> 0 | E13: =IFERROR(D13/$D$12,0) -> 0 | F13: =iferror(D13/'Periodo Anterior'!D13-1,"") | H13: =COUNTIFS(Data!$A:$A,">="&'PT Reporte SDR'!$C$3,Data!$A:$A,"<="&'PT Reporte SDR'!$D$3,Data!$AB:$AB,"Diálogo Completo") -> 0 | I13: =COUNTIFS(Data!$A:$A,">="&'PT Reporte SDR'!$C$3,Data!$A:$A,"<="&'PT Reporte SDR'!$D$3,Data!$BI:$BI,I5,Data!$W:$W,"Diálogo Completo") -> 0 | J13: =COUNTIFS(Data!$A:$A,">="&'PT Reporte SDR'!$C$3,Data!$A:$A,"<="&'PT Reporte SDR'!$D$3,Data!$BI:$BI,J5,Data!$W:$W,"Diálogo Completo") -> 0
C14: Total Leads Intermitentes | D14: =H14 -> 1 | E14: =IFERROR(D14/$D$12,0) -> 0 | F14: =iferror(D14/'Periodo Anterior'!D14-1,"") | H14: =COUNTIFS(Data!$A:$A,">="&'PT Reporte SDR'!$C$3,Data!$A:$A,"<="&'PT Reporte SDR'!$D$3,Data!$AB:$AB,"Intermitente")+1 -> 1 | I14: =COUNTIFS(Data!$A:$A,">="&'PT Reporte SDR'!$C$3,Data!$A:$A,"<="&'PT Reporte SDR'!$D$3,Data!$BI:$BI,I5,Data!$W:$W,"Intermitente") -> 0 | J14: =COUNTIFS(Data!$A:$A,">="&'PT Reporte SDR'!$C$3,Data!$A:$A,"<="&'PT Reporte SDR'!$D$3,Data!$BI:$BI,J5,Data!$W:$W,"Intermitente") -> 0
C15: Leads que entendieron comunicación | D15: =H15 -> 0 | E15: =IFERROR(D15/$D$12,0) -> 0 | F15: =iferror(D15/'Periodo Anterior'!D15-1,"") | H15: =COUNTIFS(Data!$A:$A,">="&'PT Reporte SDR'!$C$3,Data!$A:$A,"<="&'PT Reporte SDR'!$D$3,Data!$AF:$AF,"Si") -> 0 | I15: =COUNTIFS(Data!$A:$A,">="&'PT Reporte SDR'!$C$3,Data!$A:$A,"<="&'PT Reporte SDR'!$D$3,Data!$BI:$BI,I5,Data!$AJ:$AJ,"Si") -> 0 | J15: =COUNTIFS(Data!$A:$A,">="&'PT Reporte SDR'!$C$3,Data!$A:$A,"<="&'PT Reporte SDR'!$D$3,Data!$BI:$BI,J5,Data!$AJ:$AJ,"Si") -> 0
C16: Leads que no entendieron comunicación | D16: =H16 -> 0 | E16: =IFERROR(D16/$D$12,0) -> 0 | F16: =iferror(D16/'Periodo Anterior'!D21-1,"") | H16: =COUNTIFS(Data!$A:$A,">="&'PT Reporte SDR'!$C$3,Data!$A:$A,"<="&'PT Reporte SDR'!$D$3,Data!$AF:$AF,"No") -> 0 | I16: =COUNTIFS(Data!$A:$A,">="&'PT Reporte SDR'!$C$3,Data!$A:$A,"<="&'PT Reporte SDR'!$D$3,Data!$BI:$BI,I5,Data!$AJ:$AJ,"No") -> 0 | J16: =COUNTIFS(Data!$A:$A,">="&'PT Reporte SDR'!$C$3,Data!$A:$A,"<="&'PT Reporte SDR'!$D$3,Data!$BI:$BI,J5,Data!$AJ:$AJ,"No") -> 0
C17: Leads que mostraron interés | D17: =H17 -> 3 | E17: =IFERROR(D17/$D$12,0) -> 0 | F17: =iferror(D17/'Periodo Anterior'!D17-1,"") | H17: =COUNTIFS(Data!$A:$A,">="&'PT Reporte SDR'!$C$3,Data!$A:$A,"<="&'PT Reporte SDR'!$D$3,Data!$AG:$AG,"Si")+3 -> 3 | I17: =COUNTIFS(Data!$A:$A,">="&'PT Reporte SDR'!$C$3,Data!$A:$A,"<="&'PT Reporte SDR'!$D$3,Data!$BI:$BI,I5,Data!$BK:$BK,"Pase a ventas") -> 0 | J17: =COUNTIFS(Data!$A:$A,">="&'PT Reporte SDR'!$C$3,Data!$A:$A,"<="&'PT Reporte SDR'!$D$3,Data!$BI:$BI,J5,Data!$BK:$BK,"Pase a ventas") -> 0
C18: Total Leads Descartados | D18: =H18 -> 0 | E18: =iferror(D18/D6,"0%") -> 0% | F18: =iferror(D18/'Periodo Anterior'!D18-1,"") | H18: =H19+H20 -> 0 | I18: =I19+I20 -> 0 | J18: =J19+J20 -> 0
C19: Leads que no mostraron interés | D19: =H19 -> 0 | E19: =IFERROR(D19/$D$12,0) -> 0 | F19: =iferror(D19/'Periodo Anterior'!D19-1,"") | H19: =COUNTIFS(Data!$A:$A,">="&'PT Reporte SDR'!$C$3,Data!$A:$A,"<="&'PT Reporte SDR'!$D$3,Data!$AG:$AG,"No") -> 0 | I19: =COUNTIFS(Data!$A:$A,">="&'PT Reporte SDR'!$C$3,Data!$A:$A,"<="&'PT Reporte SDR'!$D$3,Data!$BI:$BI,I5,Data!$AJ:$AJ,"No") -> 0 | J19: =COUNTIFS(Data!$A:$A,">="&'PT Reporte SDR'!$C$3,Data!$A:$A,"<="&'PT Reporte SDR'!$D$3,Data!$BI:$BI,J5,Data!$AJ:$AJ,"No") -> 0
C20: Otras razones | D20: =H20 -> 0 | E20: =IFERROR(D20/$D$12,0) -> 0 | F20: =iferror(D20/'Periodo Anterior'!D20-1,"") | H20: =H99 -> 0 | I20: =I99 -> 0 | J20: =J99 -> 0
C21: Total Leads en seguimiento para venta | D21: =H21 -> 0 | E21: =IFERROR(D21/$D$12,0) -> 0 | F21: =iferror(D21/'Periodo Anterior'!D21-1,"") | H21: =COUNTIFS(Data!$A:$A,">="&'PT Reporte SDR'!$C$3,Data!$A:$A,"<="&'PT Reporte SDR'!$D$3,Data!$W:$W,"En Seguimiento") -> 0 | I21: =COUNTIFS(Data!$A:$A,">="&'PT Reporte SDR'!$C$3,Data!$A:$A,"<="&'PT Reporte SDR'!$D$3,Data!$BI:$BI,I5,Data!$BK:$BK,"SEGUIMIENTO") -> 0 | J21: =COUNTIFS(Data!$A:$A,">="&'PT Reporte SDR'!$C$3,Data!$A:$A,"<="&'PT Reporte SDR'!$D$3,Data!$BI:$BI,J5,Data!$BK:$BK,"SEGUIMIENTO") -> 0
C22: Total Leads Asignados a Ventas | D22: =H22 -> 0 | E22: =iferror(D22/D17,"0%") -> 0 | F22: =iferror(D22/'Periodo Anterior'!D22-1,"") | H22: =COUNTIFS(Data!$A:$A,">="&'PT Reporte SDR'!$C$3,Data!$A:$A,"<="&'PT Reporte SDR'!$D$3,Data!$W:$W,"Paso a ventas") -> 0 | I22: =COUNTIFS(Data!$A:$A,">="&'PT Reporte SDR'!$C$3,Data!$A:$A,"<="&'PT Reporte SDR'!$D$3,Data!$BI:$BI,I5,Data!$BK:$BK,"Pase a ventas") -> 0 | J22: =COUNTIFS(Data!$A:$A,">="&'PT Reporte SDR'!$C$3,Data!$A:$A,"<="&'PT Reporte SDR'!$D$3,Data!$BI:$BI,J5,Data!$BK:$BK,"Pase a ventas") -> 0
C23: Leads Asignados a Ventas Periodo Actual | D23: =H23 -> 6 | E23: =IFERROR(D23/D17,0) -> 2 | F23: =iferror(D23/'Periodo Anterior'!D23-1,"") | H23: 6
C24: Leads Asignados a Ventas Carry-Over | D24: =H24 -> 0 | E24: =IFERROR(D24/#REF!,0) -> 0 | F24: =iferror(D24/'Periodo Anterior'!D24-1,"") | H24: =COUNTIFS(Data!$A:$A,">="&'PT Reporte SDR'!$C$4,Data!$A:$A,"<="&'PT Reporte SDR'!$D$4,Data!$AR:$AR,">="&'PT Reporte SDR'!$C$3,Data!$AR:$AR,"<="&'PT Reporte SDR'!$D$3,Data!$W:$W,"Paso a ventas") -> 0
C25: Leads Contactados por Ventas | D25: =H25 | E25: =D25/D22 -> #DIV/0! | F25: =iferror(D25/'Periodo Anterior'!D25-1,"")
C26: Leads Contactados por Ventas con Respuesta | D26: =H26 | E26: =IFERROR(D26/D22,0) -> 0 | F26: =iferror(D26/'Periodo Anterior'!D26-1,"")
C27: No se envio cotizacion | D27: =H27 | E27: =iferror(D27/$D$116,0) -> 0 | F27: =iferror(D27/'Periodo Anterior'!D27-1,"")
C28: Tasa de Atención | D28: =H28 | F28: =iferror(D28/'Periodo Anterior'!D28-1,"")
C29: Número de Cotizaciones | D29: =H29 | E29: =IFERROR(D29/D26,0) -> 0 | F29: =iferror(D29/'Periodo Anterior'!D29-1,"")
C30: Monto de Cotización | D30: =H30 | F30: =iferror(D30/'Periodo Anterior'!D30-1,"")
C31: Ticket Promedio de Cotizaciones | D31: =H31 | F31: =iferror(D31/'Periodo Anterior'!D31-1,"")
C32: Leads Perdidos | D32: =H32 | E32: =IFERROR(D32/D26,0) -> 0 | F32: =iferror(D32/'Periodo Anterior'!D32-1,"")
C33: Leads en Seguimiento | D33: =H33 | E33: =IFERROR(D33/D26,0) -> 0 | F33: =iferror(D33/'Periodo Anterior'!D33-1,"")
C34: Temperatura de Lead | D34: =H34 | F34: =iferror(D34/'Periodo Anterior'!D34-1,"")
C35: Frio | D35: =H35 | F35: =iferror(D35/'Periodo Anterior'!D35-1,"")
C36: Tibio | D36: =H36 | F36: =iferror(D36/'Periodo Anterior'!D36-1,"")
C37: Caliente | D37: =H37 | F37: =iferror(D37/'Periodo Anterior'!D37-1,"")
C38: Total Número de Serv Confirmados (#) | D38: =H38 | E38: =IFERROR(D38/$D$29,0) -> 0 | F38: =iferror(D38/'Periodo Anterior'!D38-1,"")
C39: Número de Confirmados Periodo Actual (#) | D39: =H39 | E39: =IFERROR(D39/$D$29,0) -> 0 | F39: =iferror(D39/'Periodo Anterior'!D39-1,"")
C40: Número de Confirmados Carry-Over (#) | D40: =H40 | E40: =IFERROR(D40/$D$29,0) -> 0 | F40: =iferror(D40/'Periodo Anterior'!D40-1,"")
C41: Total Monto de Confirmados ($) | D41: =H41 | E41: =IFERROR(D41/$D$30,0) -> 0 | F41: =iferror(D41/'Periodo Anterior'!D41-1,"")
C42: Monto de Confirmados Periodo Actual($) | D42: =H42 | E42: =IFERROR(D42/$D$30,0) -> 0 | F42: =iferror(D42/'Periodo Anterior'!D42-1,"")
C43: Monto de Confirmados Carry-Over ($) | D43: =H43 | E43: =IFERROR(D43/$D$30,0) -> 0 | F43: =iferror(D43/'Periodo Anterior'!D43-1,"")
C44: Total Número de Ventas (#) | D44: =H44 | E44: =IFERROR(D44/$D$29,0) -> 0 | F44: =iferror(D44/'Periodo Anterior'!D44-1,"")
C45: Número de Ventas Periodo Actual (#) | D45: =H45 | E45: =IFERROR(D45/$D$29,0) -> 0 | F45: =iferror(D45/'Periodo Anterior'!D45-1,"")
C46: Número de Ventas Carry-Over (#) | D46: =H46 | E46: =IFERROR(D46/$D$29,0) -> 0 | F46: =iferror(D46/'Periodo Anterior'!D46-1,"")
C47: Número Oportunidades Perdidas | D47: =H47 | F47: =iferror(D47/'Periodo Anterior'!D47-1,"")
C48: Monto de Oportunidades Perdidas | D48: =H48 | F48: =iferror(D48/'Periodo Anterior'!D48-1,"")
C49: Total Monto de Ventas ($) | D49: =H49 | E49: =IFERROR(D49/$D$30,0) -> 0 | F49: =iferror(D49/'Periodo Anterior'!D49-1,"")
C50: Total Monto de Ventas Periodo Actual ($) | D50: =H50 | E50: =IFERROR(D50/$D$30,0) -> 0 | F50: =iferror(D50/'Periodo Anterior'!D50-1,"")
C51: Total Monto de Ventas Carry-Over ($) | D51: =H51 | E51: =IFERROR(D51/$D$30,0) -> 0 | F51: =iferror(D51/'Periodo Anterior'!D51-1,"")
C52: Ticket Promedio de Ventas | D52: =H52 | F52: =iferror(D52/'Periodo Anterior'!D52-1,"")
C53: Conversion Rate % | D53: =H53 | F53: =iferror(D53/'Periodo Anterior'!D53-1,"")
C54: Leads Efectivos | D54: =H54 | F54: =iferror(D54/'Periodo Anterior'!D54-1,"")
C55: Leads Convertidos a Oportunidad | D55: =H55 | F55: =iferror(D55/'Periodo Anterior'!D55-1,"")
C56: Monto de Inversión asignada a Ventas $ | D56: =H56 -> #N/A | E56: $ | F56: =iferror(D56/'Periodo Anterior'!D56-1,"") | H56: =SUMIFS(Data!$BQ:$BQ,Data!$A:$A,">="&'PT Reporte SDR'!$C$3,Data!$A:$A,"<="&'PT Reporte SDR'!$D$3,Data!$W:$W,"Paso a ventas") -> #N/A | I56: 0 | J56: 0
C57: Monto de Inversión Promedio por Prospecto $ | D57: =H57 -> 0 | E57: $ | F57: =iferror(D57/'Periodo Anterior'!D57-1,"") | H57: =iferror(H56/H22,"0") -> 0 | I57: =iferror(I56/I22,"0") -> 0 | J57: =iferror(J56/J22,"0") -> 0
C58: Deals Cerrados | D58: =H58 -> 0 | E58: =IFERROR(D58/$D$12,0) -> 0 | F58: =iferror(D58/'Periodo Anterior'!D58-1,"") | H58: =COUNTIFS(Data!$A:$A,">="&'PT Reporte SDR'!$C$3,Data!$A:$A,"<="&'PT Reporte SDR'!$D$3,Data!$BL:$BL,"Vendido") -> 0 | I58: 0 | J58: 0
C59: Monto de cierres $ | D59: 320 | E59: =IFERROR(D59/$D$12,0) -> 0 | F59: =iferror(D59/'Periodo Anterior'!D59-1,"") | H59: =SUMIFS(Data!$BP:$BP,Data!$A:$A,">="&'PT Reporte SDR'!$C$3,Data!$A:$A,"<="&'PT Reporte SDR'!$D$3,Data!$BL:$BL,"Vendido") -> #N/A | I59: 0 | J59: 0
C61: Total Leads Incontactables | D61: Total | E61: % | F61: %
A62: {=UNIQUE(Data!BJ:BJ)} -> #REF! | C62: Duplicado | D62: =Sum(H62+I62+J62) -> 0 | E62: =iferror(D62/$D$66,0) -> 0 | F62: =iferror(D62/'Periodo Anterior'!D60-1,"") | H62: =COUNTIFS(Data!$A:$A,">="&'PT Reporte SDR'!$C$3,Data!$A:$A,"<="&'PT Reporte SDR'!$D$3,Data!$X:$X,C62) -> 0 | I62: =COUNTIFS(Data!$A:$A,">="&'PT Reporte SDR'!$C$3,Data!$A:$A,"<="&'PT Reporte SDR'!$D$3,Data!$BI:$BI,$H$5,Data!$CM:$CM,C62) -> 0 | J62: =COUNTIFS(Data!$A:$A,">="&'PT Reporte SDR'!$C$3,Data!$A:$A,"<="&'PT Reporte SDR'!$D$3,Data!$BI:$BI,$H$5,Data!$CM:$CM,C62) -> 0
C63: Equivocado | D63: =Sum(H63+I63+J63) -> 0 | E63: =iferror(D63/$D$66,0) -> 0 | F63: =iferror(D63/'Periodo Anterior'!D61-1,"") | H63: =COUNTIFS(Data!$A:$A,">="&'PT Reporte SDR'!$C$3,Data!$A:$A,"<="&'PT Reporte SDR'!$D$3,Data!$X:$X,C63) -> 0 | I63: =COUNTIFS(Data!$A:$A,">="&'PT Reporte SDR'!$C$3,Data!$A:$A,"<="&'PT Reporte SDR'!$D$3,Data!$BI:$BI,$H$5,Data!$CM:$CM,C63) -> 0 | J63: =COUNTIFS(Data!$A:$A,">="&'PT Reporte SDR'!$C$3,Data!$A:$A,"<="&'PT Reporte SDR'!$D$3,Data!$BI:$BI,$H$5,Data!$CM:$CM,C63) -> 0
C64: SPAM | D64: =Sum(H64+I64+J64) -> 0 | E64: =iferror(D64/$D$66,0) -> 0 | F64: =iferror(D64/'Periodo Anterior'!D62-1,"") | H64: =COUNTIFS(Data!$A:$A,">="&'PT Reporte SDR'!$C$3,Data!$A:$A,"<="&'PT Reporte SDR'!$D$3,Data!$X:$X,C64) -> 0 | I64: =COUNTIFS(Data!$A:$A,">="&'PT Reporte SDR'!$C$3,Data!$A:$A,"<="&'PT Reporte SDR'!$D$3,Data!$BI:$BI,$H$5,Data!$CM:$CM,C64) -> 0 | J64: =COUNTIFS(Data!$A:$A,">="&'PT Reporte SDR'!$C$3,Data!$A:$A,"<="&'PT Reporte SDR'!$D$3,Data!$BI:$BI,$H$5,Data!$CM:$CM,C64) -> 0
C65: Prueba | D65: =Sum(H65+I65+J65) -> 0 | E65: =iferror(D65/$D$66,0) -> 0 | F65: =iferror(D65/'Periodo Anterior'!D63-1,"") | H65: =COUNTIFS(Data!$A:$A,">="&'PT Reporte SDR'!$C$3,Data!$A:$A,"<="&'PT Reporte SDR'!$D$3,Data!$X:$X,C65) -> 0 | I65: =COUNTIFS(Data!$A:$A,">="&'PT Reporte SDR'!$C$3,Data!$A:$A,"<="&'PT Reporte SDR'!$D$3,Data!$BI:$BI,$H$5,Data!$CM:$CM,C65) -> 0 | J65: =COUNTIFS(Data!$A:$A,">="&'PT Reporte SDR'!$C$3,Data!$A:$A,"<="&'PT Reporte SDR'!$D$3,Data!$BI:$BI,$H$5,Data!$CM:$CM,C65) -> 0
C66: Total | D66: =sum(D62:D65) -> 0 | E66: =iferror(D66/$D$66,0) -> 0 | F66: =iferror(D66/'Periodo Anterior'!D64-1,"") | H66: =SUM(H62:H65) -> 0 | I66: =sum(I62:I65) -> 0 | J66: =sum(J62:J65) -> 0
C69: Cross Selling | D69: =SUM(D70) -> 0 | E69: % | F69: %
C70: Cross Selling | E70: =iferror(D70/$D$69,0) -> 0 | F70: =iferror(D70/$D$69,0) -> 0
C72: Total Leads Contactados con Respuesta | D72: =SUM(D73:D82) -> 0 | E72: % | F72: % | H72: =SUM(H73:H82) -> 0 | I72: =SUM(I73:I82) -> 0 | J72: =SUM(J73:J82) -> 0
C73: Contestó Teléfono 1 | D73: =sum(H73) -> 0 | E73: =IFERROR(D73/$D$72,0) -> 0 | F73: =IFERROR(D73/$D$72,0) -> 0 | H73: =COUNTIFS(Data!$A:$A,">="&'PT Reporte SDR'!$C$3,Data!$A:$A,"<="&'PT Reporte SDR'!$D$3,Data!$Y:$Y,C73) -> 0 | I73: =COUNTIFS(Data!$A:$A,">="&'PT Reporte SDR'!$C$3,Data!$A:$A,"<="&'PT Reporte SDR'!$D$3,Data!$E:$E,D73,Data!$BG:$BG,$H$5) -> 0 | J73: =COUNTIFS(Data!$A:$A,">="&'PT Reporte SDR'!$C$3,Data!$A:$A,"<="&'PT Reporte SDR'!$D$3,Data!$E:$E,E73,Data!$BG:$BG,$H$5) -> 0
C74: Contestó Teléfono 2 | D74: =sum(H74) -> 0 | E74: =IFERROR(D74/$D$72,0) -> 0 | F74: =IFERROR(D74/$D$72,0) -> 0 | H74: =COUNTIFS(Data!$A:$A,">="&'PT Reporte SDR'!$C$3,Data!$A:$A,"<="&'PT Reporte SDR'!$D$3,Data!$Y:$Y,C74) -> 0 | I74: =COUNTIFS(Data!$A:$A,">="&'PT Reporte SDR'!$C$3,Data!$A:$A,"<="&'PT Reporte SDR'!$D$3,Data!$E:$E,D74,Data!$BG:$BG,$H$5) -> 0 | J74: =COUNTIFS(Data!$A:$A,">="&'PT Reporte SDR'!$C$3,Data!$A:$A,"<="&'PT Reporte SDR'!$D$3,Data!$E:$E,E74,Data!$BG:$BG,$H$5) -> 0
C75: Contestó Teléfono 3 | D75: =sum(H75) -> 0 | E75: =IFERROR(D75/$D$72,0) -> 0 | F75: =IFERROR(D75/$D$72,0) -> 0 | H75: =COUNTIFS(Data!$A:$A,">="&'PT Reporte SDR'!$C$3,Data!$A:$A,"<="&'PT Reporte SDR'!$D$3,Data!$Y:$Y,C75) -> 0 | I75: =COUNTIFS(Data!$A:$A,">="&'PT Reporte SDR'!$C$3,Data!$A:$A,"<="&'PT Reporte SDR'!$D$3,Data!$E:$E,D75,Data!$BG:$BG,$H$5) -> 0 | J75: =COUNTIFS(Data!$A:$A,">="&'PT Reporte SDR'!$C$3,Data!$A:$A,"<="&'PT Reporte SDR'!$D$3,Data!$E:$E,E75,Data!$BG:$BG,$H$5) -> 0
C76: Contestó Whatsapp 1 | D76: =sum(H76) -> 0 | E76: =IFERROR(D76/$D$72,0) -> 0 | F76: =IFERROR(D76/$D$72,0) -> 0 | H76: =COUNTIFS(Data!$A:$A,">="&'PT Reporte SDR'!$C$3,Data!$A:$A,"<="&'PT Reporte SDR'!$D$3,Data!$Y:$Y,C76) -> 0 | I76: =COUNTIFS(Data!$A:$A,">="&'PT Reporte SDR'!$C$3,Data!$A:$A,"<="&'PT Reporte SDR'!$D$3,Data!$E:$E,D76,Data!$BG:$BG,$H$5) -> 0 | J76: =COUNTIFS(Data!$A:$A,">="&'PT Reporte SDR'!$C$3,Data!$A:$A,"<="&'PT Reporte SDR'!$D$3,Data!$E:$E,E76,Data!$BG:$BG,$H$5) -> 0
C77: Contestó Whatsapp 2 | D77: =sum(H77) -> 0 | E77: =IFERROR(D77/$D$72,0) -> 0 | F77: =IFERROR(D77/$D$72,0) -> 0 | H77: =COUNTIFS(Data!$A:$A,">="&'PT Reporte SDR'!$C$3,Data!$A:$A,"<="&'PT Reporte SDR'!$D$3,Data!$Y:$Y,C77) -> 0 | I77: =COUNTIFS(Data!$A:$A,">="&'PT Reporte SDR'!$C$3,Data!$A:$A,"<="&'PT Reporte SDR'!$D$3,Data!$E:$E,D77,Data!$BG:$BG,$H$5) -> 0 | J77: =COUNTIFS(Data!$A:$A,">="&'PT Reporte SDR'!$C$3,Data!$A:$A,"<="&'PT Reporte SDR'!$D$3,Data!$E:$E,E77,Data!$BG:$BG,$H$5) -> 0
C78: Contestó Whatsapp 3 | D78: =sum(H78) -> 0 | E78: =IFERROR(D78/$D$72,0) -> 0 | F78: =IFERROR(D78/$D$72,0) -> 0 | H78: =COUNTIFS(Data!$A:$A,">="&'PT Reporte SDR'!$C$3,Data!$A:$A,"<="&'PT Reporte SDR'!$D$3,Data!$Y:$Y,C78) -> 0 | I78: =COUNTIFS(Data!$A:$A,">="&'PT Reporte SDR'!$C$3,Data!$A:$A,"<="&'PT Reporte SDR'!$D$3,Data!$E:$E,D78,Data!$BG:$BG,$H$5) -> 0 | J78: =COUNTIFS(Data!$A:$A,">="&'PT Reporte SDR'!$C$3,Data!$A:$A,"<="&'PT Reporte SDR'!$D$3,Data!$E:$E,E78,Data!$BG:$BG,$H$5) -> 0
C79: Contestó Correo 1 | D79: =sum(H79) -> 0 | E79: =IFERROR(D79/$D$72,0) -> 0 | F79: =IFERROR(D79/$D$72,0) -> 0 | H79: =COUNTIFS(Data!$A:$A,">="&'PT Reporte SDR'!$C$3,Data!$A:$A,"<="&'PT Reporte SDR'!$D$3,Data!$Y:$Y,C79) -> 0 | I79: =COUNTIFS(Data!$A:$A,">="&'PT Reporte SDR'!$C$3,Data!$A:$A,"<="&'PT Reporte SDR'!$D$3,Data!$E:$E,D79,Data!$BG:$BG,$H$5) -> 0 | J79: =COUNTIFS(Data!$A:$A,">="&'PT Reporte SDR'!$C$3,Data!$A:$A,"<="&'PT Reporte SDR'!$D$3,Data!$E:$E,E79,Data!$BG:$BG,$H$5) -> 0
C80: Contestó Correo 2 | D80: =sum(H80) -> 0 | E80: =IFERROR(D80/$D$72,0) -> 0 | F80: =IFERROR(D80/$D$72,0) -> 0 | H80: =COUNTIFS(Data!$A:$A,">="&'PT Reporte SDR'!$C$3,Data!$A:$A,"<="&'PT Reporte SDR'!$D$3,Data!$Y:$Y,C80) -> 0 | I80: =COUNTIFS(Data!$A:$A,">="&'PT Reporte SDR'!$C$3,Data!$A:$A,"<="&'PT Reporte SDR'!$D$3,Data!$E:$E,D80,Data!$BG:$BG,$H$5) -> 0 | J80: =COUNTIFS(Data!$A:$A,">="&'PT Reporte SDR'!$C$3,Data!$A:$A,"<="&'PT Reporte SDR'!$D$3,Data!$E:$E,E80,Data!$BG:$BG,$H$5) -> 0
C81: Contestó Correo 3 | D81: =sum(H81) -> 0 | E81: =IFERROR(D81/$D$72,0) -> 0 | F81: =IFERROR(D81/$D$72,0) -> 0 | H81: =COUNTIFS(Data!$A:$A,">="&'PT Reporte SDR'!$C$3,Data!$A:$A,"<="&'PT Reporte SDR'!$D$3,Data!$Y:$Y,C81) -> 0 | I81: =COUNTIFS(Data!$A:$A,">="&'PT Reporte SDR'!$C$3,Data!$A:$A,"<="&'PT Reporte SDR'!$D$3,Data!$E:$E,D81,Data!$BG:$BG,$H$5) -> 0 | J81: =COUNTIFS(Data!$A:$A,">="&'PT Reporte SDR'!$C$3,Data!$A:$A,"<="&'PT Reporte SDR'!$D$3,Data!$E:$E,E81,Data!$BG:$BG,$H$5) -> 0
C82: Contestó Correo 4 | D82: =sum(H82) -> 0 | E82: =IFERROR(D82/$D$72,0) -> 0 | F82: =IFERROR(D82/$D$72,0) -> 0 | H82: =COUNTIFS(Data!$A:$A,">="&'PT Reporte SDR'!$C$3,Data!$A:$A,"<="&'PT Reporte SDR'!$D$3,Data!$Y:$Y,C82) -> 0 | I82: =COUNTIFS(Data!$A:$A,">="&'PT Reporte SDR'!$C$3,Data!$A:$A,"<="&'PT Reporte SDR'!$D$3,Data!$E:$E,D82,Data!$BG:$BG,$H$5) -> 0 | J82: =COUNTIFS(Data!$A:$A,">="&'PT Reporte SDR'!$C$3,Data!$A:$A,"<="&'PT Reporte SDR'!$D$3,Data!$E:$E,E82,Data!$BG:$BG,$H$5) -> 0
C85: Total Lead en Proceso de Contacto (aún sin respuesta) | D85: =SUM(D86:D93) -> 0 | E85: % Total | F85: % Total | H85: =SUM(H86:H93) -> 0 | I85: =SUM(I86:I93) -> 0 | J85: =SUM(J86:J93) -> 0
C86: No Contestó Teléfono 1 | D86: =sum(H86) -> 0 | E86: =iferror(D86/$D$85,0) -> 0 | F86: =iferror(D86/$D$85,0) -> 0 | H86: =COUNTIFS(Data!$A:$A,">="&'PT Reporte SDR'!$C$3,Data!$A:$A,"<="&'PT Reporte SDR'!$D$3,Data!$Y:$Y,C86) -> 0 | I86: =COUNTIFS(Data!$A:$A,">="&'PT Reporte SDR'!$C$3,Data!$A:$A,"<="&'PT Reporte SDR'!$D$3,Data!$E:$E,D86,Data!$BG:$BG,$H$5) -> 0 | J86: =COUNTIFS(Data!$A:$A,">="&'PT Reporte SDR'!$C$3,Data!$A:$A,"<="&'PT Reporte SDR'!$D$3,Data!$E:$E,E86,Data!$BG:$BG,$H$5) -> 0
C87: No Contestó Teléfono 2 | D87: =sum(H87) -> 0 | E87: =iferror(D87/$D$85,0) -> 0 | F87: =iferror(D87/$D$85,0) -> 0 | H87: =COUNTIFS(Data!$A:$A,">="&'PT Reporte SDR'!$C$3,Data!$A:$A,"<="&'PT Reporte SDR'!$D$3,Data!$Y:$Y,C87) -> 0 | I87: =COUNTIFS(Data!$A:$A,">="&'PT Reporte SDR'!$C$3,Data!$A:$A,"<="&'PT Reporte SDR'!$D$3,Data!$E:$E,D87,Data!$BG:$BG,$H$5) -> 0 | J87: =COUNTIFS(Data!$A:$A,">="&'PT Reporte SDR'!$C$3,Data!$A:$A,"<="&'PT Reporte SDR'!$D$3,Data!$E:$E,E87,Data!$BG:$BG,$H$5) -> 0
C88: No Contesto Teléfono 3 | D88: =sum(H88) -> 0 | E88: =iferror(D88/$D$85,0) -> 0 | F88: =iferror(D88/$D$85,0) -> 0 | H88: =COUNTIFS(Data!$A:$A,">="&'PT Reporte SDR'!$C$3,Data!$A:$A,"<="&'PT Reporte SDR'!$D$3,Data!$Y:$Y,C88) -> 0 | I88: =COUNTIFS(Data!$A:$A,">="&'PT Reporte SDR'!$C$3,Data!$A:$A,"<="&'PT Reporte SDR'!$D$3,Data!$E:$E,D88,Data!$BG:$BG,$H$5) -> 0 | J88: =COUNTIFS(Data!$A:$A,">="&'PT Reporte SDR'!$C$3,Data!$A:$A,"<="&'PT Reporte SDR'!$D$3,Data!$E:$E,E88,Data!$BG:$BG,$H$5) -> 0
C89: No Contestó Whatsapp 1 | D89: =sum(H89) -> 0 | E89: =iferror(D89/$D$85,0) -> 0 | F89: =iferror(D89/$D$85,0) -> 0 | H89: =COUNTIFS(Data!$A:$A,">="&'PT Reporte SDR'!$C$3,Data!$A:$A,"<="&'PT Reporte SDR'!$D$3,Data!$Y:$Y,C89) -> 0 | I89: =COUNTIFS(Data!$A:$A,">="&'PT Reporte SDR'!$C$3,Data!$A:$A,"<="&'PT Reporte SDR'!$D$3,Data!$E:$E,D89,Data!$BG:$BG,$H$5) -> 0 | J89: =COUNTIFS(Data!$A:$A,">="&'PT Reporte SDR'!$C$3,Data!$A:$A,"<="&'PT Reporte SDR'!$D$3,Data!$E:$E,E89,Data!$BG:$BG,$H$5) -> 0
C90: No Contestó Whatsapp 2 | D90: =sum(H90) -> 0 | E90: =iferror(D90/$D$85,0) -> 0 | F90: =iferror(D90/$D$85,0) -> 0 | H90: =COUNTIFS(Data!$A:$A,">="&'PT Reporte SDR'!$C$3,Data!$A:$A,"<="&'PT Reporte SDR'!$D$3,Data!$Y:$Y,C90) -> 0 | I90: =COUNTIFS(Data!$A:$A,">="&'PT Reporte SDR'!$C$3,Data!$A:$A,"<="&'PT Reporte SDR'!$D$3,Data!$E:$E,D90,Data!$BG:$BG,$H$5) -> 0 | J90: =COUNTIFS(Data!$A:$A,">="&'PT Reporte SDR'!$C$3,Data!$A:$A,"<="&'PT Reporte SDR'!$D$3,Data!$E:$E,E90,Data!$BG:$BG,$H$5) -> 0
C91: No Contestó Whatsapp 3 | D91: =sum(H91) -> 0 | E91: =iferror(D91/$D$85,0) -> 0 | F91: =iferror(D91/$D$85,0) -> 0 | H91: =COUNTIFS(Data!$A:$A,">="&'PT Reporte SDR'!$C$3,Data!$A:$A,"<="&'PT Reporte SDR'!$D$3,Data!$Y:$Y,C91) -> 0 | I91: =COUNTIFS(Data!$A:$A,">="&'PT Reporte SDR'!$C$3,Data!$A:$A,"<="&'PT Reporte SDR'!$D$3,Data!$E:$E,D91,Data!$BG:$BG,$H$5) -> 0 | J91: =COUNTIFS(Data!$A:$A,">="&'PT Reporte SDR'!$C$3,Data!$A:$A,"<="&'PT Reporte SDR'!$D$3,Data!$E:$E,E91,Data!$BG:$BG,$H$5) -> 0
C95: Total Leads Contactados sin Respuesta (6to Toque) | D95: =SUM(D96:D97) -> 0 | E95: % Total | F95: % Total | H95: =SUM(H96:H97) -> 0 | I95: =SUM(I96:I97) -> 0 | J95: =SUM(J96:J97) -> 0
C96: Toque 6 | D96: =sum(H96) -> 0 | E96: =IFERROR(D96/$D$95,0) -> 0 | F96: =IFERROR(D96/$D$95,0) -> 0 | H96: =COUNTIFS(Data!$A:$A,">="&'PT Reporte SDR'!$C$3,Data!$A:$A,"<="&'PT Reporte SDR'!$D$3,Data!$AE:$AE,C96) -> 0
C99: ¿Por Qué No Pasó a Ventas? | D99: =sum(D100:D140) -> 0 | E99: % | F99: % | H99: =SUM(H100:H140) -> 0 | I99: =SUM(I100:I140) -> 0 | J99: =SUM(J100:J140) -> 0
C100: Toque 6 | D100: =H100+I100+J100 -> 0 | E100: =D100/$D$99 -> #DIV/0! | F100: =iferror(D100/'Periodo Anterior'!D98-1,"") | H100: =COUNTIFS(Data!$A:$A,">="&'PT Reporte SDR'!$C$3,Data!$A:$A,"<="&'PT Reporte SDR'!$D$3,Data!$AD:$AD,C100) -> 0 | I100: =COUNTIFS(Data!$A:$A,">="&'PT Reporte SDR'!$C$3,Data!$A:$A,"<="&'PT Reporte SDR'!$D$3,Data!$BI:$BI,$H$5,Data!$DF:$DF,C100) -> 0 | J100: =COUNTIFS(Data!$A:$A,">="&'PT Reporte SDR'!$C$3,Data!$A:$A,"<="&'PT Reporte SDR'!$D$3,Data!$BI:$BI,$H$5,Data!$DF:$DF,C100) -> 0
C101: Nunca Respondió | D101: =H101+I101+J101 -> 0 | E101: =D101/$D$99 -> #DIV/0! | F101: =iferror(D101/'Periodo Anterior'!D99-1,"") | H101: =COUNTIFS(Data!$A:$A,">="&'PT Reporte SDR'!$C$3,Data!$A:$A,"<="&'PT Reporte SDR'!$D$3,Data!$AD:$AD,C101) -> 0 | I101: =COUNTIFS(Data!$A:$A,">="&'PT Reporte SDR'!$C$3,Data!$A:$A,"<="&'PT Reporte SDR'!$D$3,Data!$BI:$BI,$H$5,Data!$DF:$DF,C101) -> 0 | J101: =COUNTIFS(Data!$A:$A,">="&'PT Reporte SDR'!$C$3,Data!$A:$A,"<="&'PT Reporte SDR'!$D$3,Data!$BI:$BI,$H$5,Data!$DF:$DF,C101) -> 0
C102: Dejó de responder | D102: =H102+I102+J102 -> 0 | E102: =D102/$D$99 -> #DIV/0! | F102: =iferror(D102/'Periodo Anterior'!D100-1,"") | H102: =COUNTIFS(Data!$A:$A,">="&'PT Reporte SDR'!$C$3,Data!$A:$A,"<="&'PT Reporte SDR'!$D$3,Data!$AD:$AD,C102) -> 0 | I102: =COUNTIFS(Data!$A:$A,">="&'PT Reporte SDR'!$C$3,Data!$A:$A,"<="&'PT Reporte SDR'!$D$3,Data!$BI:$BI,$H$5,Data!$DF:$DF,C102) -> 0 | J102: =COUNTIFS(Data!$A:$A,">="&'PT Reporte SDR'!$C$3,Data!$A:$A,"<="&'PT Reporte SDR'!$D$3,Data!$BI:$BI,$H$5,Data!$DF:$DF,C102) -> 0
C103: No tuvo más interés | D103: =H103+I103+J103 -> 0 | E103: =D103/$D$99 -> #DIV/0! | F103: =iferror(D103/'Periodo Anterior'!D101-1,"") | H103: =COUNTIFS(Data!$A:$A,">="&'PT Reporte SDR'!$C$3,Data!$A:$A,"<="&'PT Reporte SDR'!$D$3,Data!$AD:$AD,C103) -> 0 | I103: =COUNTIFS(Data!$A:$A,">="&'PT Reporte SDR'!$C$3,Data!$A:$A,"<="&'PT Reporte SDR'!$D$3,Data!$BI:$BI,$H$5,Data!$DF:$DF,C103) -> 0 | J103: =COUNTIFS(Data!$A:$A,">="&'PT Reporte SDR'!$C$3,Data!$A:$A,"<="&'PT Reporte SDR'!$D$3,Data!$BI:$BI,$H$5,Data!$DF:$DF,C103) -> 0
C104: Desconoce el registro | D104: =H104+I104+J104 -> 0 | E104: =D104/$D$99 -> #DIV/0! | F104: =iferror(D104/'Periodo Anterior'!D102-1,"") | H104: =COUNTIFS(Data!$A:$A,">="&'PT Reporte SDR'!$C$3,Data!$A:$A,"<="&'PT Reporte SDR'!$D$3,Data!$AD:$AD,C104) -> 0 | I104: =COUNTIFS(Data!$A:$A,">="&'PT Reporte SDR'!$C$3,Data!$A:$A,"<="&'PT Reporte SDR'!$D$3,Data!$BI:$BI,$H$5,Data!$DF:$DF,C104) -> 0 | J104: =COUNTIFS(Data!$A:$A,">="&'PT Reporte SDR'!$C$3,Data!$A:$A,"<="&'PT Reporte SDR'!$D$3,Data!$BI:$BI,$H$5,Data!$DF:$DF,C104) -> 0
C105: Ya resolvió su necesidad | D105: =H105+I105+J105 -> 0 | E105: =D105/$D$99 -> #DIV/0! | F105: =iferror(D105/'Periodo Anterior'!D103-1,"") | H105: =COUNTIFS(Data!$A:$A,">="&'PT Reporte SDR'!$C$3,Data!$A:$A,"<="&'PT Reporte SDR'!$D$3,Data!$AD:$AD,C105) -> 0 | I105: =COUNTIFS(Data!$A:$A,">="&'PT Reporte SDR'!$C$3,Data!$A:$A,"<="&'PT Reporte SDR'!$D$3,Data!$BI:$BI,$H$5,Data!$DF:$DF,C105) -> 0 | J105: =COUNTIFS(Data!$A:$A,">="&'PT Reporte SDR'!$C$3,Data!$A:$A,"<="&'PT Reporte SDR'!$D$3,Data!$BI:$BI,$H$5,Data!$DF:$DF,C105) -> 0
C106: No se cuenta con el servicio | D106: =H106+I106+J106 -> 0 | E106: =D106/$D$99 -> #DIV/0! | F106: =iferror(D106/'Periodo Anterior'!D104-1,"") | H106: =COUNTIFS(Data!$A:$A,">="&'PT Reporte SDR'!$C$3,Data!$A:$A,"<="&'PT Reporte SDR'!$D$3,Data!$AD:$AD,C106) -> 0 | I106: =COUNTIFS(Data!$A:$A,">="&'PT Reporte SDR'!$C$3,Data!$A:$A,"<="&'PT Reporte SDR'!$D$3,Data!$BI:$BI,$H$5,Data!$DF:$DF,C106) -> 0 | J106: =COUNTIFS(Data!$A:$A,">="&'PT Reporte SDR'!$C$3,Data!$A:$A,"<="&'PT Reporte SDR'!$D$3,Data!$BI:$BI,$H$5,Data!$DF:$DF,C106) -> 0
C107: Busca ser proveedor | D107: =H107+I107+J107 -> 0 | E107: =D107/$D$99 -> #DIV/0! | F107: =iferror(D107/'Periodo Anterior'!D105-1,"") | H107: =COUNTIFS(Data!$A:$A,">="&'PT Reporte SDR'!$C$3,Data!$A:$A,"<="&'PT Reporte SDR'!$D$3,Data!$AE:$AE,C107) -> 0 | I107: =COUNTIFS(Data!$A:$A,">="&'PT Reporte SDR'!$C$3,Data!$A:$A,"<="&'PT Reporte SDR'!$D$3,Data!$BI:$BI,$H$5,Data!$DF:$DF,C107) -> 0 | J107: =COUNTIFS(Data!$A:$A,">="&'PT Reporte SDR'!$C$3,Data!$A:$A,"<="&'PT Reporte SDR'!$D$3,Data!$BI:$BI,$H$5,Data!$DF:$DF,C107) -> 0
C108: Busca empleo | D108: =H108+I108+J108 -> 0 | E108: =D108/$D$99 -> #DIV/0! | F108: =iferror(D108/'Periodo Anterior'!D106-1,"") | H108: =COUNTIFS(Data!$A:$A,">="&'PT Reporte SDR'!$C$3,Data!$A:$A,"<="&'PT Reporte SDR'!$D$3,Data!$AD:$AD,C108) -> 0 | I108: =COUNTIFS(Data!$A:$A,">="&'PT Reporte SDR'!$C$3,Data!$A:$A,"<="&'PT Reporte SDR'!$D$3,Data!$BI:$BI,$H$5,Data!$DF:$DF,C108) -> 0 | J108: =COUNTIFS(Data!$A:$A,">="&'PT Reporte SDR'!$C$3,Data!$A:$A,"<="&'PT Reporte SDR'!$D$3,Data!$BI:$BI,$H$5,Data!$DF:$DF,C108) -> 0
C109: Pidió no volver a llamar | D109: =H109+I109+J109 -> 0 | E109: =D109/$D$99 -> #DIV/0! | F109: =iferror(D109/'Periodo Anterior'!D107-1,"") | H109: =COUNTIFS(Data!$A:$A,">="&'PT Reporte SDR'!$C$3,Data!$A:$A,"<="&'PT Reporte SDR'!$D$3,Data!$AD:$AD,C109) -> 0 | I109: =COUNTIFS(Data!$A:$A,">="&'PT Reporte SDR'!$C$3,Data!$A:$A,"<="&'PT Reporte SDR'!$D$3,Data!$BI:$BI,$H$5,Data!$DF:$DF,C109) -> 0 | J109: =COUNTIFS(Data!$A:$A,">="&'PT Reporte SDR'!$C$3,Data!$A:$A,"<="&'PT Reporte SDR'!$D$3,Data!$BI:$BI,$H$5,Data!$DF:$DF,C109) -> 0
C110: Motivos Personales | D110: =H110+I110+J110 -> 0 | E110: =D110/$D$99 -> #DIV/0! | F110: =iferror(D110/'Periodo Anterior'!D108-1,"") | H110: =COUNTIFS(Data!$A:$A,">="&'PT Reporte SDR'!$C$3,Data!$A:$A,"<="&'PT Reporte SDR'!$D$3,Data!$AD:$AD,C110) -> 0 | I110: =COUNTIFS(Data!$A:$A,">="&'PT Reporte SDR'!$C$3,Data!$A:$A,"<="&'PT Reporte SDR'!$D$3,Data!$BI:$BI,$H$5,Data!$DF:$DF,C110) -> 0 | J110: =COUNTIFS(Data!$A:$A,">="&'PT Reporte SDR'!$C$3,Data!$A:$A,"<="&'PT Reporte SDR'!$D$3,Data!$BI:$BI,$H$5,Data!$DF:$DF,C110) -> 0
C111: No me llames, yo te llamo | D111: =H111+I111+J111 -> 0 | E111: =D111/$D$99 -> #DIV/0! | F111: =iferror(D111/'Periodo Anterior'!D109-1,"") | H111: =COUNTIFS(Data!$A:$A,">="&'PT Reporte SDR'!$C$3,Data!$A:$A,"<="&'PT Reporte SDR'!$D$3,Data!$AD:$AD,C111) -> 0 | I111: =COUNTIFS(Data!$A:$A,">="&'PT Reporte SDR'!$C$3,Data!$A:$A,"<="&'PT Reporte SDR'!$D$3,Data!$BI:$BI,$H$5,Data!$DF:$DF,C111) -> 0 | J111: =COUNTIFS(Data!$A:$A,">="&'PT Reporte SDR'!$C$3,Data!$A:$A,"<="&'PT Reporte SDR'!$D$3,Data!$BI:$BI,$H$5,Data!$DF:$DF,C111) -> 0
C114: ¿Por qué se perdió la venta? | D114: =H114+I114+J114 -> 0 | E114: =D114/$D$99 -> #DIV/0! | F114: % | H114: =COUNTIFS(Data!$A:$A,">="&'PT Reporte SDR'!$C$3,Data!$A:$A,"<="&'PT Reporte SDR'!$D$3,Data!$BI:$BI,$H$5,Data!$DF:$DF,C114) -> 0 | I114: =COUNTIFS(Data!$A:$A,">="&'PT Reporte SDR'!$C$3,Data!$A:$A,"<="&'PT Reporte SDR'!$D$3,Data!$BI:$BI,$H$5,Data!$DF:$DF,C114) -> 0 | J114: =COUNTIFS(Data!$A:$A,">="&'PT Reporte SDR'!$C$3,Data!$A:$A,"<="&'PT Reporte SDR'!$D$3,Data!$BI:$BI,$H$5,Data!$DF:$DF,C114) -> 0
...

Sheet Reporte SDR 
C3: IAAPA | FUNNEL REPORT | SDR | REALTIME
C4: Day In | D4: Day Out
C5: 45778 | D5: 45997
C6: =EOMONTH(C5,-2)+1 -> 45748 | D6: =EDATE(D5, -1) -> 45967
C7: MÉTRICA | D7: TOTAL | E7: % | F7: Δ% vs PP | H7: Total | I7: % | J7: Δ% vs PP | K7: Manufacturers | L7: % | M7: Δ% vs PP | N7: Individuals | O7: % | P7: Δ% vs PP | S7: Agosto
C8: Total Leads SDR | D8: =H8 -> 0 | F8: =iferror(D8/'PT Reporte SDR'!D6-1,"") | H8: =COUNTIFS(Data!$A:$A,">="&'Reporte SDR '!$C$5,Data!$A:$A,"<="&'Reporte SDR '!$D$5) -> 0 | J8: =iferror(H8/'PT Reporte SDR'!H6-1,"") | K8: =COUNTIFS(Data!$A:$A,">="&'Reporte SDR '!$C$5,Data!$A:$A,"<="&'Reporte SDR '!$D$5,Data!$BI:$BI,K7) -> 0 | M8: =iferror(K8/'PT Reporte SDR'!K6-1,"") | N8: =COUNTIFS(Data!$A:$A,">="&'Reporte SDR '!$C$5,Data!$A:$A,"<="&'Reporte SDR '!$D$5,Data!$BI:$BI,N7) -> 0 | P8: =iferror(N8/'PT Reporte SDR'!N6-1,"") | S8: Pagados | T8: 4 | W8: Cerrados carry over
C9: Prueba | D9: =Sum(H9+K9+N9) -> 0 | E9: =iferror(D9/$D$8,"0%") -> 0% | F9: =iferror(D9/'PT Reporte SDR'!D65-1,"") | H9: =COUNTIFS(Data!$A:$A,">="&'Reporte SDR '!$C$5,Data!$A:$A,"<="&'Reporte SDR '!$D$5,Data!$X:$X,C9) -> 0 | I9: =iferror(H9/$D$50,0) -> 0 | J9: =iferror(H9/'PT Reporte SDR'!H65-1,"") | K9: =COUNTIFS(Data!$A:$A,">="&'Reporte SDR '!$C$5,Data!$A:$A,"<="&'Reporte SDR '!$D$5,Data!$BI:$BI,$H$7,Data!$CM:$CM,C9) -> 0 | L9: =iferror(K9/$D$50,0) -> 0 | M9: =iferror(K9/'PT Reporte SDR'!K65-1,"") | N9: =COUNTIFS(Data!$A:$A,">="&'Reporte SDR '!$C$5,Data!$A:$A,"<="&'Reporte SDR '!$D$5,Data!$BI:$BI,$H$7,Data!$CM:$CM,C9) -> 0 | O9: =iferror(N9/$D$50,0) -> 0 | P9: =iferror(N9/'PT Reporte SDR'!N65-1,"")
C10: Total Leads Incontactables por base de datos | D10: =H10 -> 0 | E10: =iferror(D10/$D$8,"0%") -> 0% | F10: =iferror(D10/'PT Reporte SDR'!D7-1,"") | H10: =H50 -> 0 | I10: =iferror(H10/$D$8,"0%") -> 0% | J10: =iferror(H10/'PT Reporte SDR'!H7-1,"") | K10: =K50 -> 0 | L10: =iferror(K10/$D$8,"0%") -> 0% | M10: =iferror(K10/'PT Reporte SDR'!K7-1,"") | N10: =N50 -> 0 | O10: =iferror(N10/$D$8,"0%") -> 0% | P10: =iferror(N10/'PT Reporte SDR'!N7-1,"")
C11: Total Leads Contactables | D11: =H11 -> 0 | E11: =iferror(D11/$D$8,"0%") -> 0% | F11: =iferror(D11/'PT Reporte SDR'!D8-1,"") | H11: =H8-H10-H9 -> 0 | I11: =iferror(H11/$D$8,"0%") -> 0% | J11: =iferror(H11/'PT Reporte SDR'!H8-1,"") | K11: =K8-K10 -> 0 | L11: =iferror(K11/$D$8,"0%") -> 0% | M11: =iferror(K11/'PT Reporte SDR'!K8-1,"") | N11: =N8-N10 -> 0 | O11: =iferror(N11/$D$8,"0%") -> 0% | P11: =iferror(N11/'PT Reporte SDR'!N8-1,"")
C12: Total Leads Contactados (con al menos 1 Toque) | D12: =H12 -> 3 | E12: =iferror(D12/D11,"0%") -> 0% | F12: =iferror(D12/'PT Reporte SDR'!D9-1,"") | H12: =COUNTIFS(Data!$A:$A,">="&'Reporte SDR '!$C$5,Data!$A:$A,"<="&'Reporte SDR '!$D$5,Data!$Y:$Y,"<>")+3 -> 3 | I12: =iferror(H12/H11,"0%") -> 0% | J12: =iferror(H12/'PT Reporte SDR'!H9-1,"") | K12: =COUNTIFS(Data!$A:$A,">="&'Reporte SDR '!$C$5,Data!$A:$A,"<="&'Reporte SDR '!$D$5,Data!$BI:$BI,K7,Data!$AT:$AT,"<>")-K10 -> 0 | L12: =iferror(K12/K11,"0%") -> 0% | M12: =iferror(K12/'PT Reporte SDR'!K9-1,"") | N12: =COUNTIFS(Data!$A:$A,">="&'Reporte SDR '!$C$5,Data!$A:$A,"<="&'Reporte SDR '!$D$5,Data!$BI:$BI,N7,Data!$AT:$AT,"<>")-N10 -> 0 | O12: =iferror(N12/N11,"0%") -> 0% | P12: =iferror(N12/'PT Reporte SDR'!N9-1,"")
C13: Total Lead en Proceso de Contacto (aún sin respuesta) | D13: =H13 -> -15 | E13: =iferror(D13/$D$8,"0%") -> 0% | F13: =iferror(D13/'PT Reporte SDR'!D10-1,"") -> -1.2112676 | H13: =COUNTIFS(Data!$A:$A,">="&'Reporte SDR '!$C$5,Data!$A:$A,"<="&'Reporte SDR '!$D$5,Data!$W:$W,"Contactado sin Respuesta")-15 -> -15 | I13: =iferror(H13/$D$8,"0%") -> 0% | J13: =iferror(H13/'PT Reporte SDR'!H10-1,"") -> -1.2112676 | K13: =COUNTIFS(Data!$A:$A,">="&'Reporte SDR '!$C$5,Data!$A:$A,"<="&'Reporte SDR '!$D$5,Data!$BI:$BI,K7,Data!$BK:$BK,"No respondio") -> 0 | L13: =iferror(K13/$D$8,"0%") -> 0% | M13: =iferror(K13/'PT Reporte SDR'!K10-1,"") | N13: =COUNTIFS(Data!$A:$A,">="&'Reporte SDR '!$C$5,Data!$A:$A,"<="&'Reporte SDR '!$D$5,Data!$BI:$BI,N7,Data!$BK:$BK,"No respondio") -> 0 | O13: =iferror(N13/$D$8,"0%") -> 0% | P13: =iferror(N13/'PT Reporte SDR'!N10-1,"")
C14: Total Leads Contactados sin Respuesta (6to Toque o más) | D14: =H14 -> -4 | E14: =iferror(IFERROR(D14/D12,0),"") -> -1.3333333 | F14: =iferror(D14/'PT Reporte SDR'!D11-1,"") | H14: =COUNTIFS(Data!$A:$A,">="&'Reporte SDR '!$C$5,Data!$A:$A,"<="&'Reporte SDR '!$D$5,Data!$AA:$AA,"<5")-4 -> -4 | I14: =iferror(IFERROR(H14/H12,0),"") -> -1.3333333 | J14: =iferror(H14/'PT Reporte SDR'!H11-1,"") | K14: =COUNTIFS(Data!$A:$A,">="&'Reporte SDR '!$C$5,Data!$A:$A,"<="&'Reporte SDR '!$D$5,Data!$BI:$BI,K7,Data!$AT:$AT,">=6") -> 0 | L14: =iferror(IFERROR(K14/K12,0),"") -> 0 | M14: =iferror(K14/'PT Reporte SDR'!K11-1,"") | N14: =COUNTIFS(Data!$A:$A,">="&'Reporte SDR '!$C$5,Data!$A:$A,"<="&'Reporte SDR '!$D$5,Data!$BI:$BI,N7,Data!$AT:$AT,">=6") -> 0 | O14: =iferror(IFERROR(N14/N12,0),"") -> 0 | P14: =iferror(N14/'PT Reporte SDR'!N11-1,"")
C15: Total Leads Contactados con Respuesta | D15: =H15 -> 13 | E15: =iferror(D15/D11,"0%") -> 0% | F15: =iferror(D15/'PT Reporte SDR'!D12-1,"") | H15: =H56-15 -> 13 | I15: =iferror(H15/H11,"0%") -> 0% | J15: =iferror(H15/'PT Reporte SDR'!H12-1,"") | K15: =COUNTIFS(Data!$A:$A,">="&'Reporte SDR '!$C$5,Data!$A:$A,"<="&'Reporte SDR '!$D$5,Data!$BI:$BI,K7,Data!$BK:$BK,"Pase a ventas")+COUNTIFS(Data!$A:$A,">="&'Reporte SDR '!$C$5,Data!$A:$A,"<="&'Reporte SDR '!$D$5,Data!$BI:$BI,K7,Data!$BK:$BK,"Descartado")+COUNTIFS(Data!$A:$A,">="&'Reporte SDR '!$C$5,Data!$A:$A,"<="&'Reporte SDR '!$D$5,Data!$BI:$BI,K7,Data!$BK:$BK,"Pidio llamar mas tarde")+COUNTIFS(Data!$A:$A,">="&'Reporte SDR '!$C$5,Data!$A:$A,"<="&'Reporte SDR '!$D$5,Data!$BI:$BI,K7,Data!$BK:$BK,"Contesta y Cuelga")+COUNTIFS(Data!$A:$A,">="&'Reporte SDR '!$C$5,Data!$A:$A,"<="&'Reporte SDR '!$D$5,Data!$BI:$BI,K7,Data!$BK:$BK,"Llamar mañana")+COUNTIFS(Data!$A:$A,">="&'Reporte SDR '!$C$5,Data!$A:$A,"<="&'Reporte SDR '!$D$5,Data!$BI:$BI,K7,Data!$BK:$BK,"SEGUIMIENTO") -> 0 | L15: =iferror(K15/K11,"0%") -> 0% | M15: =iferror(K15/'PT Reporte SDR'!K12-1,"") | N15: =COUNTIFS(Data!$A:$A,">="&'Reporte SDR '!$C$5,Data!$A:$A,"<="&'Reporte SDR '!$D$5,Data!$BI:$BI,N7,Data!$BK:$BK,"Pase a ventas")+COUNTIFS(Data!$A:$A,">="&'Reporte SDR '!$C$5,Data!$A:$A,"<="&'Reporte SDR '!$D$5,Data!$BI:$BI,N7,Data!$BK:$BK,"Descartado")+COUNTIFS(Data!$A:$A,">="&'Reporte SDR '!$C$5,Data!$A:$A,"<="&'Reporte SDR '!$D$5,Data!$BI:$BI,N7,Data!$BK:$BK,"Pidio llamar mas tarde")+COUNTIFS(Data!$A:$A,">="&'Reporte SDR '!$C$5,Data!$A:$A,"<="&'Reporte SDR '!$D$5,Data!$BI:$BI,N7,Data!$BK:$BK,"Contesta y Cuelga")+COUNTIFS(Data!$A:$A,">="&'Reporte SDR '!$C$5,Data!$A:$A,"<="&'Reporte SDR '!$D$5,Data!$BI:$BI,N7,Data!$BK:$BK,"Llamar mañana")+COUNTIFS(Data!$A:$A,">="&'Reporte SDR '!$C$5,Data!$A:$A,"<="&'Reporte SDR '!$D$5,Data!$BI:$BI,N7,Data!$BK:$BK,"SEGUIMIENTO") -> 0 | O15: =iferror(N15/N11,"0%") -> 0% | P15: =iferror(N15/'PT Reporte SDR'!N12-1,"")
C16: Total Leads Con Dialogo Completo | D16: =H16 -> 5 | E16: =IFERROR(D16/$D$15,0) -> 0.38461538 | F16: =iferror(D16/'PT Reporte SDR'!D13-1,"") | H16: =COUNTIFS(Data!$A:$A,">="&'Reporte SDR '!$C$5,Data!$A:$A,"<="&'Reporte SDR '!$D$5,Data!$AB:$AB,"Diálogo Completo")+5 -> 5 | I16: =IFERROR(H16/$D$15,0) -> 0.38461538 | J16: =iferror(H16/'PT Reporte SDR'!H13-1,"") | K16: =COUNTIFS(Data!$A:$A,">="&'Reporte SDR '!$C$5,Data!$A:$A,"<="&'Reporte SDR '!$D$5,Data!$BI:$BI,K7,Data!$W:$W,"Diálogo Completo") -> 0 | L16: =IFERROR(K16/$D$15,0) -> 0 | M16: =iferror(K16/'PT Reporte SDR'!K13-1,"") | N16: =COUNTIFS(Data!$A:$A,">="&'Reporte SDR '!$C$5,Data!$A:$A,"<="&'Reporte SDR '!$D$5,Data!$BI:$BI,N7,Data!$W:$W,"Diálogo Completo") -> 0 | O16: =IFERROR(N16/$D$15,0) -> 0 | P16: =iferror(N16/'PT Reporte SDR'!N13-1,"")
C17: Total Leads Intermitentes | D17: =H17 -> 37 | E17: =IFERROR(D17/$D$15,0) -> 2.8461538 | F17: =iferror(D17/'PT Reporte SDR'!D14-1,"") -> 36 | H17: =COUNTIFS(Data!$A:$A,">="&'Reporte SDR '!$C$5,Data!$A:$A,"<="&'Reporte SDR '!$D$5,Data!$AB:$AB,"Intermitente")+37 -> 37 | I17: =IFERROR(H17/$D$15,0) -> 2.8461538 | J17: =iferror(H17/'PT Reporte SDR'!H14-1,"") -> 36 | K17: =COUNTIFS(Data!$A:$A,">="&'Reporte SDR '!$C$5,Data!$A:$A,"<="&'Reporte SDR '!$D$5,Data!$BI:$BI,K7,Data!$W:$W,"Intermitente") -> 0 | L17: =IFERROR(K17/$D$15,0) -> 0 | M17: =iferror(K17/'PT Reporte SDR'!K14-1,"") | N17: =COUNTIFS(Data!$A:$A,">="&'Reporte SDR '!$C$5,Data!$A:$A,"<="&'Reporte SDR '!$D$5,Data!$BI:$BI,N7,Data!$W:$W,"Intermitente") -> 0 | O17: =IFERROR(N17/$D$15,0) -> 0 | P17: =iferror(N17/'PT Reporte SDR'!N14-1,"")
C18: Leads que entendieron comunicación | D18: =H18 -> 0 | E18: =IFERROR(D18/$D$15,0) -> 0 | F18: =iferror(D18/'PT Reporte SDR'!D15-1,"") | H18: =COUNTIFS(Data!$A:$A,">="&'Reporte SDR '!$C$5,Data!$A:$A,"<="&'Reporte SDR '!$D$5,Data!$AF:$AF,"Si") -> 0 | I18: =IFERROR(H18/$D$15,0) -> 0 | J18: =iferror(H18/'PT Reporte SDR'!H15-1,"") | K18: =COUNTIFS(Data!$A:$A,">="&'Reporte SDR '!$C$5,Data!$A:$A,"<="&'Reporte SDR '!$D$5,Data!$BI:$BI,K7,Data!$AJ:$AJ,"Si") -> 0 | L18: =IFERROR(K18/$D$15,0) -> 0 | M18: =iferror(K18/'PT Reporte SDR'!K15-1,"") | N18: =COUNTIFS(Data!$A:$A,">="&'Reporte SDR '!$C$5,Data!$A:$A,"<="&'Reporte SDR '!$D$5,Data!$BI:$BI,N7,Data!$AJ:$AJ,"Si") -> 0 | O18: =IFERROR(N18/$D$15,0) -> 0 | P18: =iferror(N18/'PT Reporte SDR'!N15-1,"")
C19: Leads que no entendieron comunicación | D19: =H19 -> 9 | E19: =IFERROR(D19/$D$15,0) -> 0.69230769 | F19: =iferror(D19/'PT Reporte SDR'!D16-1,"") | H19: =COUNTIFS(Data!$A:$A,">="&'Reporte SDR '!$C$5,Data!$A:$A,"<="&'Reporte SDR '!$D$5,Data!$AF:$AF,"No")+9 -> 9 | I19: =IFERROR(H19/$D$15,0) -> 0.69230769 | J19: =iferror(H19/'PT Reporte SDR'!H16-1,"") | K19: =COUNTIFS(Data!$A:$A,">="&'Reporte SDR '!$C$5,Data!$A:$A,"<="&'Reporte SDR '!$D$5,Data!$BI:$BI,K7,Data!$AJ:$AJ,"No") -> 0 | L19: =IFERROR(K19/$D$15,0) -> 0 | M19: =iferror(K19/'PT Reporte SDR'!K16-1,"") | N19: =COUNTIFS(Data!$A:$A,">="&'Reporte SDR '!$C$5,Data!$A:$A,"<="&'Reporte SDR '!$D$5,Data!$BI:$BI,N7,Data!$AJ:$AJ,"No") -> 0 | O19: =IFERROR(N19/$D$15,0) -> 0 | P19: =iferror(N19/'PT Reporte SDR'!N16-1,"")
C20: Leads que mostraron interés | D20: =H20 -> 39 | E20: =IFERROR(D20/$D$15,0) -> 3 | F20: =iferror(D20/'PT Reporte SDR'!D17-1,"") -> 12 | H20: =COUNTIFS(Data!$A:$A,">="&'Reporte SDR '!$C$5,Data!$A:$A,"<="&'Reporte SDR '!$D$5,Data!$AG:$AG,"Si")+39 -> 39 | I20: =IFERROR(H20/$D$15,0) -> 3 | J20: =iferror(H20/'PT Reporte SDR'!H17-1,"") -> 12 | K20: =COUNTIFS(Data!$A:$A,">="&'Reporte SDR '!$C$5,Data!$A:$A,"<="&'Reporte SDR '!$D$5,Data!$BI:$BI,K7,Data!$BK:$BK,"Pase a ventas") -> 0 | L20: =IFERROR(K20/$D$15,0) -> 0 | M20: =iferror(K20/'PT Reporte SDR'!K17-1,"") | N20: =COUNTIFS(Data!$A:$A,">="&'Reporte SDR '!$C$5,Data!$A:$A,"<="&'Reporte SDR '!$D$5,Data!$BI:$BI,N7,Data!$BK:$BK,"Pase a ventas") -> 0 | O20: =IFERROR(N20/$D$15,0) -> 0 | P20: =iferror(N20/'PT Reporte SDR'!N17-1,"")
C21: Total Leads Descartados | D21: =H21 -> 5 | E21: =iferror(D21/D8,"0%") -> 0% | F21: =iferror(D21/'PT Reporte SDR'!D18-1,"") | H21: =H22+H23 -> 5 | I21: =iferror(H21/H8,"0%") -> 0% | J21: =iferror(H21/'PT Reporte SDR'!H18-1,"") | K21: =K22+K23 -> 0 | L21: =iferror(K21/K8,"0%") -> 0% | M21: =iferror(K21/'PT Reporte SDR'!K18-1,"") | N21: =N22+N23 -> 0 | O21: =iferror(N21/N8,"0%") -> 0% | P21: =iferror(N21/'PT Reporte SDR'!N18-1,"")
C22: Leads que no mostraron interés | D22: =H22 -> 2 | E22: =IFERROR(D22/$D$15,0) -> 0.15384615 | F22: =iferror(D22/'PT Reporte SDR'!D19-1,"") | H22: =COUNTIFS(Data!$A:$A,">="&'Reporte SDR '!$C$5,Data!$A:$A,"<="&'Reporte SDR '!$D$5,Data!$AG:$AG,"No")+2 -> 2 | I22: =IFERROR(H22/$D$15,0) -> 0.15384615 | J22: =iferror(H22/'PT Reporte SDR'!H19-1,"") | K22: =COUNTIFS(Data!$A:$A,">="&'Reporte SDR '!$C$5,Data!$A:$A,"<="&'Reporte SDR '!$D$5,Data!$BI:$BI,K7,Data!$AJ:$AJ,"No") -> 0 | L22: =IFERROR(K22/$D$15,0) -> 0 | M22: =iferror(K22/'PT Reporte SDR'!K19-1,"") | N22: =COUNTIFS(Data!$A:$A,">="&'Reporte SDR '!$C$5,Data!$A:$A,"<="&'Reporte SDR '!$D$5,Data!$BI:$BI,N7,Data!$AJ:$AJ,"No") -> 0 | O22: =IFERROR(N22/$D$15,0) -> 0 | P22: =iferror(N22/'PT Reporte SDR'!N19-1,"")
C23: Otras razones | D23: =H23 -> 3 | E23: =IFERROR(D23/$D$15,0) -> 0.23076923 | F23: =iferror(D23/'PT Reporte SDR'!D20-1,"") | H23: =H83 -> 3 | I23: =IFERROR(H23/$D$15,0) -> 0.23076923 | J23: =iferror(H23/'PT Reporte SDR'!H20-1,"") | K23: =K83 -> 0 | L23: =IFERROR(K23/$D$15,0) -> 0 | M23: =iferror(K23/'PT Reporte SDR'!K20-1,"") | N23: =N83 -> 0 | O23: =IFERROR(N23/$D$15,0) -> 0 | P23: =iferror(N23/'PT Reporte SDR'!N20-1,"")
C24: Total Leads en seguimiento para venta | D24: =H24 -> 0 | E24: =IFERROR(D24/$D$15,0) -> 0 | F24: =iferror(D24/'PT Reporte SDR'!D21-1,"") | H24: =COUNTIFS(Data!$A:$A,">="&'Reporte SDR '!$C$5,Data!$A:$A,"<="&'Reporte SDR '!$D$5,Data!$W:$W,"En Seguimiento") -> 0 | I24: =IFERROR(H24/$D$15,0) -> 0 | J24: =iferror(H24/'PT Reporte SDR'!H21-1,"") | K24: =COUNTIFS(Data!$A:$A,">="&'Reporte SDR '!$C$5,Data!$A:$A,"<="&'Reporte SDR '!$D$5,Data!$BI:$BI,K7,Data!$BK:$BK,"SEGUIMIENTO") -> 0 | L24: =IFERROR(K24/$D$15,0) -> 0 | M24: =iferror(K24/'PT Reporte SDR'!K21-1,"") | N24: =COUNTIFS(Data!$A:$A,">="&'Reporte SDR '!$C$5,Data!$A:$A,"<="&'Reporte SDR '!$D$5,Data!$BI:$BI,N7,Data!$BK:$BK,"SEGUIMIENTO") -> 0 | O24: =IFERROR(N24/$D$15,0) -> 0 | P24: =iferror(N24/'PT Reporte SDR'!N21-1,"")
C25: Monto aproximado de Inversión en seguimiento a venta | D25: =H25 -> #N/A | H25: =SUMIFS(Data!$AP:$AP,Data!$A:$A,">="&'Reporte SDR '!$C$5,Data!$A:$A,"<="&'Reporte SDR '!$D$5,Data!$W:$W,"En Seguimiento")+1700 -> #N/A
C26: Total Leads Asignados a Ventas | D26: =H26 -> 0 | E26: =iferror(D26/D20,"0%") -> 0 | F26: =iferror(D26/'PT Reporte SDR'!D22-1,"") | H26: =COUNTIFS(Data!$A:$A,">="&'Reporte SDR '!$C$5,Data!$A:$A,"<="&'Reporte SDR '!$D$5,Data!$W:$W,"Paso a ventas") -> 0 | I26: =iferror(H26/H20,"0%") -> 0 | J26: =iferror(H26/'PT Reporte SDR'!H22-1,"") | K26: =COUNTIFS(Data!$A:$A,">="&'Reporte SDR '!$C$5,Data!$A:$A,"<="&'Reporte SDR '!$D$5,Data!$BI:$BI,K7,Data!$BK:$BK,"Pase a ventas") -> 0 | L26: =iferror(K26/K20,"0%") -> 0% | M26: =iferror(K26/'PT Reporte SDR'!K22-1,"") | N26: =COUNTIFS(Data!$A:$A,">="&'Reporte SDR '!$C$5,Data!$A:$A,"<="&'Reporte SDR '!$D$5,Data!$BI:$BI,N7,Data!$BK:$BK,"Pase a ventas") -> 0 | O26: =iferror(N26/N20,"0%") -> 0% | P26: =iferror(N26/'PT Reporte SDR'!N22-1,"")
C27: Monto de inversión asignada a ventas | D27: =H27 -> #N/A | E27: $ | F27: =iferror(D27/'PT Reporte SDR Brazil'!D28-1,"") | H27: =SUMIFS(Data!$AP:$AP,Data!$A:$A,">="&'Report LATAM'!$C$5,Data!$A:$A,"<="&'Report LATAM'!$D$5,Data!$W:$W,"Paso a Ventas")+2000 -> #N/A | J27: =iferror(H27/'PT Reporte SDR Brazil'!H28-1,"")
C28: Leads Asignados a Ventas Periodo Actual | D28: =H28 -> 0 | E28: =IFERROR(D28/D20,0) -> 0 | F28: =iferror(D28/'PT Reporte SDR Brazil'!D23-1,"") -> -1 | H28: =COUNTIFS(Data!$A:$A,">="&'Reporte SDR '!$C$5,Data!$A:$A,"<="&'Reporte SDR '!$D$5,Data!$W:$W,"Paso a ventas") -> 0 | I28: =IFERROR(H28/H20,0) -> 0 | J28: =iferror(H28/'PT Reporte SDR Brazil'!H23-1,"") -> -1
C29: Monto de Inversión asignada a Ventas Periodo Actual | D29: =H29 -> #N/A | E29: =IFERROR(D29/D26,0) -> 0 | F29: =iferror(D29/'PT Reporte SDR Brazil'!D26-1,"") | H29: =SUMIFS(Data!$AP:$AP,Data!$A:$A,">="&'Report LATAM'!$C$5,Data!$A:$A,"<="&'Report LATAM'!$D$5,Data!$W:$W,"Paso a Ventas")+2000 -> #N/A | I29: =IFERROR(H29/H26,0) -> 0 | J29: =iferror(H29/'PT Reporte SDR Brazil'!H26-1,"")
C30: Leads Asignados a Ventas Carry-Over | D30: =H30 -> 3 | E30: =IFERROR(D30/#REF!,0) -> 0 | F30: =iferror(D30/'PT Reporte SDR Brazil'!D24-1,"") | H30: =COUNTIFS(Data!$AR:$AR,">="&'Reporte SDR '!$C$5,Data!$AR:$AR,"<="&'Reporte SDR '!$D$5,Data!$A:$A,">="&'Reporte SDR '!$C$6,Data!$A:$A,"<="&'Reporte SDR '!$D$6,Data!$W:$W,"Paso a ventas")+3 -> 3 | I30: =IFERROR(H30/#REF!,0) -> 0 | J30: =iferror(H30/'PT Reporte SDR Brazil'!H24-1,"")
C31: Monto de Inversión asignada a Ventas Carry-Over (Leads Mes anterior) | D31: =H31 -> #N/A | E31: =iferror(D31/$D$78,0) -> 0 | F31: =iferror(D31/'PT Reporte SDR Brazil'!D27-1,"") | H31: =SUMIFS(Data!$BQ:$BQ,Data!$AR:$AR,">="&'Reporte SDR '!$C$5,Data!$AR:$AR,"<="&'Reporte SDR '!$D$5,Data!$A:$A,">="&'Reporte SDR '!$C$6,Data!$A:$A,"<="&'Reporte SDR '!$D$6,Data!$W:$W,"Paso a ventas")+1130 -> #N/A | I31: =iferror(H31/$D$78,0) -> 0 | J31: =iferror(H31/'PT Reporte SDR Brazil'!H27-1,"")
C32: Deals con Link de Pago activo | D32: =H32 -> -2 | H32: =COUNTIFS(Data!$A:$A,">="&'Reporte SDR '!$C$5,Data!$A:$A,"<="&'Reporte SDR '!$D$5,Data!$BZ:$BZ,"Si",Data!$BL:$BL,"<>Vendido")-2 -> -2
C33: Monto de Inversión con Link de Pago | D33: =H33 -> #N/A | H33: =SUMIFS(Data!$BQ:$BQ,Data!$A:$A,">="&'Reporte SDR '!$C$5,Data!$A:$A,"<="&'Reporte SDR '!$D$5,Data!$BZ:$BZ,"Si",Data!$BL:$BL,"<>Vendido")+SUMIFS(Data!$BP:$BP,Data!$A:$A,">="&'Reporte SDR '!$C$5,Data!$A:$A,"<="&'Reporte SDR '!$D$5,Data!$BZ:$BZ,"Si",Data!$BL:$BL,"<>Vendido")+1365 -> #N/A
C34: Cierres de Deals Nuevos Pagados | D34: =H34 -> -10 | F34: =iferror(D34/'PT Reporte SDR Brazil'!D35-1,"") | H34: =COUNTIFS(Data!$A:$A,">="&'Reporte SDR '!$C$5,Data!$A:$A,"<="&'Reporte SDR '!$D$5,Data!$BL:$BL,"Vendido",Data!$BY:$BY,">="&'Reporte SDR '!$C$5,Data!$BY:$BY,"<="&'Reporte SDR '!$D$5)-10 -> -10 | J34: =iferror(H34/'PT Reporte SDR Brazil'!H35-1,"")
C35: Monto de nuevos cierres | D35: =H35 -> #N/A | F35: =iferror(D35/'PT Reporte SDR Brazil'!D36-1,"") | H35: =SUMIFS(Data!$BQ:$BQ,Data!$A:$A,">="&'Reporte SDR '!$C$5,Data!$A:$A,"<="&'Reporte SDR '!$D$5,Data!$BL:$BL,"Vendido",Data!$BY:$BY,">="&'Reporte SDR '!$C$5,Data!$BY:$BY,"<="&'Reporte SDR '!$D$5)+SUMIFS(Data!$BR:$BR,Data!$A:$A,">="&'Reporte SDR '!$C$5,Data!$A:$A,"<="&'Reporte SDR '!$D$5,Data!$BL:$BL,"Vendido",Data!$BY:$BY,">="&'Reporte SDR '!$C$5,Data!$BY:$BY,"<="&'Reporte SDR '!$D$5)-4005 -> #N/A | J35: =iferror(H35/'PT Reporte SDR Brazil'!H36-1,"")
C36: Cierres de Deals Pagados por Rejoin (aquellos que fueron miembros y se vuelven a unir a IAAPA) | D36: =H36 -> 0 | H36: =COUNTIFS(Data!$A:$A,">="&'Reporte SDR '!$C$5,Data!$A:$A,"<="&'Reporte SDR '!$D$5,Data!$BL:$BL,"Vendido",Data!$CA:$CA,"Si") -> 0
C37: Monto de cierres por renovación | D37: =H37 -> #N/A | H37: =SUMIFS(Data!$BQ:$BQ,Data!$A:$A,">="&'Reporte SDR '!$C$5,Data!$A:$A,"<="&'Reporte SDR '!$D$5,Data!$BL:$BL,"Vendido",Data!$CA:$CA,"Si") -> #N/A
C38: Cierres de Deals Pagados Total | D38: =H38 -> 4 | H38: =COUNTIFS(Data!$A:$A,">="&'Reporte SDR '!$C$5,Data!$A:$A,"<="&'Reporte SDR '!$D$5,Data!$BL:$BL,"Vendido")+4 -> 4
C39: Monto de cierres Total | D39: =H39 -> #N/A | H39: =SUMIFS(Data!$BQ:$BQ,Data!$A:$A,">="&'Reporte SDR '!$C$5,Data!$A:$A,"<="&'Reporte SDR '!$D$5,Data!$BL:$BL,"Vendido")+SUMIFS(Data!$BR:$BR,Data!$A:$A,">="&'Reporte SDR '!$C$5,Data!$A:$A,"<="&'Reporte SDR '!$D$5,Data!$BL:$BL,"Vendido")+4645 -> #N/A
C40: Monto asignado a Ventas Total todos los tiempos | D40: =H40 -> #N/A | E40: =IFERROR(D40/D29,0) -> 0 | F40: =iferror(D40/'PT Reporte SDR Brazil'!D29-1,"") | H40: =SUMIFS(Data!$BQ:$BQ,Data!$A:$A,">="&'Reporte SDR '!$H$4,Data!$A:$A,"<="&'Reporte SDR '!$I$4,Data!$W:$W,"Paso a ventas")+SUMIFS(Data!$BR:$BR,Data!$A:$A,">="&'Reporte SDR '!$H$4,Data!$A:$A,"<="&'Reporte SDR '!$I$4,Data!$W:$W,"Paso a ventas")+14325 -> #N/A | I40: =IFERROR(H40/H29,0) -> 0 | J40: =iferror(H40/'PT Reporte SDR Brazil'!H29-1,"")
C41: Monto asignado a Ventas Historico aún en seguimiento | D41: =H41 -> #N/A | F41: =iferror(D41/'PT Reporte SDR Brazil'!D30-1,"") | H41: =SUMIFS(Data!$BQ:$BQ,Data!$A:$A,">="&'Reporte SDR '!$H$5,Data!$A:$A,"<="&'Reporte SDR '!$I$5,Data!$W:$W,"Paso a ventas")+SUMIFS(Data!$BR:$BR,Data!$A:$A,">="&'Reporte SDR '!$H$5,Data!$A:$A,"<="&'Reporte SDR '!$I$5,Data!$W:$W,"Paso a ventas")+13885 -> #N/A | J41: =iferror(H41/'PT Reporte SDR Brazil'!H30-1,"")
C42: Monto asignado a ventas Perdido | D42: =H42 -> #N/A | E42: =IFERROR(D42/D29,0) -> 0 | F42: =iferror(D42/'PT Reporte SDR Brazil'!D32-1,"") | H42: =SUMIFS(Data!$BQ:$BQ,Data!$A:$A,">="&'Reporte SDR '!$H$5,Data!$A:$A,"<="&'Reporte SDR '!$I$5,Data!$W:$W,"Paso a ventas",Data!$BL:$BL,"Perdido")+SUMIFS(Data!$BR:$BR,Data!$A:$A,">="&'Reporte SDR '!$H$5,Data!$A:$A,"<="&'Reporte SDR '!$I$5,Data!$W:$W,"Paso a ventas",Data!$BL:$BL,"Perdido") -> #N/A | I42: =IFERROR(H42/H29,0) -> 0 | J42: =iferror(H42/'PT Reporte SDR Brazil'!H32-1,"")
C43: Monto asignado a ventas Promedio por Prospecto | D43: =H43 -> #N/A | E43: =IFERROR(D43/D29,0) -> 0 | F43: =iferror(D43/'PT Reporte SDR Brazil'!D33-1,"") | H43: =H29/H28 -> #N/A | I43: =IFERROR(H43/H29,0) -> 0 | J43: =iferror(H43/'PT Reporte SDR Brazil'!H33-1,"")
C44: Monto asignado a ventas Promedio por Prospecto Periodo Anterior | D44: =H44 -> #N/A | F44: =iferror(D44/'PT Reporte SDR Brazil'!D34-1,"") | H44: =H40/H34 -> #N/A | J44: =iferror(H44/'PT Reporte SDR Brazil'!H34-1,"")
F45: =iferror(D45/'PT Reporte SDR'!D60-1,"") | J45: =iferror(H45/'PT Reporte SDR'!H60-1,"") | M45: =iferror(K45/'PT Reporte SDR'!K60-1,"") | P45: =iferror(N45/'PT Reporte SDR'!N60-1,"")
C46: Total Leads Incontactables | D46: Total | E46: % | F46: =iferror(D46/'PT Reporte SDR'!D61-1,"") | I46: % | J46: =iferror(H46/'PT Reporte SDR'!H61-1,"") | L46: % | M46: =iferror(K46/'PT Reporte SDR'!K61-1,"") | O46: % | P46: =iferror(N46/'PT Reporte SDR'!N61-1,"")
A47: {=UNIQUE(Data!BJ:BJ)} -> #REF! | C47: Duplicado | D47: =Sum(H47+K47+N47) -> 0 | E47: =iferror(D47/$D$50,0) -> 0 | F47: =iferror(D47/'PT Reporte SDR'!D62-1,"") | H47: =COUNTIFS(Data!$A:$A,">="&'Reporte SDR '!$C$5,Data!$A:$A,"<="&'Reporte SDR '!$D$5,Data!$X:$X,C47) -> 0 | I47: =iferror(H47/$D$50,0) -> 0 | J47: =iferror(H47/'PT Reporte SDR'!H62-1,"") | K47: =COUNTIFS(Data!$A:$A,">="&'Reporte SDR '!$C$5,Data!$A:$A,"<="&'Reporte SDR '!$D$5,Data!$BI:$BI,$H$7,Data!$CM:$CM,C47) -> 0 | L47: =iferror(K47/$D$50,0) -> 0 | M47: =iferror(K47/'PT Reporte SDR'!K62-1,"") | N47: =COUNTIFS(Data!$A:$A,">="&'Reporte SDR '!$C$5,Data!$A:$A,"<="&'Reporte SDR '!$D$5,Data!$BI:$BI,$H$7,Data!$CM:$CM,C47) -> 0 | O47: =iferror(N47/$D$50,0) -> 0 | P47: =iferror(N47/'PT Reporte SDR'!N62-1,"")
C48: Equivocado | D48: =Sum(H48+K48+N48) -> 0 | E48: =iferror(D48/$D$50,0) -> 0 | F48: =iferror(D48/'PT Reporte SDR'!D63-1,"") | H48: =COUNTIFS(Data!$A:$A,">="&'Reporte SDR '!$C$5,Data!$A:$A,"<="&'Reporte SDR '!$D$5,Data!$X:$X,C48) -> 0 | I48: =iferror(H48/$D$50,0) -> 0 | J48: =iferror(H48/'PT Reporte SDR'!H63-1,"") | K48: =COUNTIFS(Data!$A:$A,">="&'Reporte SDR '!$C$5,Data!$A:$A,"<="&'Reporte SDR '!$D$5,Data!$BI:$BI,$H$7,Data!$CM:$CM,C48) -> 0 | L48: =iferror(K48/$D$50,0) -> 0 | M48: =iferror(K48/'PT Reporte SDR'!K63-1,"") | N48: =COUNTIFS(Data!$A:$A,">="&'Reporte SDR '!$C$5,Data!$A:$A,"<="&'Reporte SDR '!$D$5,Data!$BI:$BI,$H$7,Data!$CM:$CM,C48) -> 0 | O48: =iferror(N48/$D$50,0) -> 0 | P48: =iferror(N48/'PT Reporte SDR'!N63-1,"")
C49: SPAM | D49: =Sum(H49+K49+N49) -> 0 | E49: =iferror(D49/$D$50,0) -> 0 | F49: =iferror(D49/'PT Reporte SDR'!D64-1,"") | H49: =COUNTIFS(Data!$A:$A,">="&'Reporte SDR '!$C$5,Data!$A:$A,"<="&'Reporte SDR '!$D$5,Data!$X:$X,C49) -> 0 | I49: =iferror(H49/$D$50,0) -> 0 | J49: =iferror(H49/'PT Reporte SDR'!H64-1,"") | K49: =COUNTIFS(Data!$A:$A,">="&'Reporte SDR '!$C$5,Data!$A:$A,"<="&'Reporte SDR '!$D$5,Data!$BI:$BI,$H$7,Data!$CM:$CM,C49) -> 0 | L49: =iferror(K49/$D$50,0) -> 0 | M49: =iferror(K49/'PT Reporte SDR'!K64-1,"") | N49: =COUNTIFS(Data!$A:$A,">="&'Reporte SDR '!$C$5,Data!$A:$A,"<="&'Reporte SDR '!$D$5,Data!$BI:$BI,$H$7,Data!$CM:$CM,C49) -> 0 | O49: =iferror(N49/$D$50,0) -> 0 | P49: =iferror(N49/'PT Reporte SDR'!N64-1,"")
C50: Total | D50: =sum(D47:D49) -> 0 | E50: =iferror(D50/$D$50,0) -> 0 | F50: =iferror(D50/'PT Reporte SDR'!D66-1,"") | H50: =SUM(H47:H49) -> 0 | I50: =iferror(H50/$D$50,0) -> 0 | J50: =iferror(H50/'PT Reporte SDR'!H66-1,"") | K50: =sum(K47:K49) -> 0 | L50: =iferror(K50/$D$50,0) -> 0 | M50: =iferror(K50/'PT Reporte SDR'!K66-1,"") | N50: =sum(N47:N49) -> 0 | O50: =iferror(N50/$D$50,0) -> 0 | P50: =iferror(N50/'PT Reporte SDR'!N66-1,"")
F51: =iferror(D51/'PT Reporte SDR'!D67-1,"") | J51: =iferror(H51/'PT Reporte SDR'!H67-1,"") | M51: =iferror(K51/'PT Reporte SDR'!K67-1,"") | P51: =iferror(N51/'PT Reporte SDR'!N67-1,"")
F52: =iferror(D52/'PT Reporte SDR'!D68-1,"") | J52: =iferror(H52/'PT Reporte SDR'!H68-1,"") | M52: =iferror(K52/'PT Reporte SDR'!K68-1,"") | P52: =iferror(N52/'PT Reporte SDR'!N68-1,"")
C53: Cross Selling | D53: =SUM(D54) -> 0 | E53: % | F53: =iferror(D53/'PT Reporte SDR'!D69-1,"") | I53: % | J53: =iferror(H53/'PT Reporte SDR'!H69-1,"") | L53: % | M53: =iferror(K53/'PT Reporte SDR'!K69-1,"") | O53: % | P53: =iferror(N53/'PT Reporte SDR'!N69-1,"")
C54: Cross Selling | E54: =iferror(D54/$D$53,0) -> 0 | F54: =iferror(D54/'PT Reporte SDR'!D70-1,"") | I54: =iferror(H54/$D$53,0) -> 0 | J54: =iferror(H54/'PT Reporte SDR'!H70-1,"") | L54: =iferror(K54/$D$53,0) -> 0 | M54: =iferror(K54/'PT Reporte SDR'!K70-1,"") | O54: =iferror(N54/$D$53,0) -> 0 | P54: =iferror(N54/'PT Reporte SDR'!N70-1,"")
F55: =iferror(D55/'PT Reporte SDR'!D71-1,"") | J55: =iferror(H55/'PT Reporte SDR'!H71-1,"") | M55: =iferror(K55/'PT Reporte SDR'!K71-1,"") | P55: =iferror(N55/'PT Reporte SDR'!N71-1,"")
C56: Total Leads Contactados con Respuesta | D56: =SUM(D57:D66) -> 28 | E56: % | F56: =iferror(D56/'PT Reporte SDR'!D72-1,"") | H56: =SUM(H57:H66) -> 28 | I56: % | J56: =iferror(H56/'PT Reporte SDR'!H72-1,"") | K56: =SUM(K57:K66) -> 0 | L56: % | M56: =iferror(K56/'PT Reporte SDR'!K72-1,"") | N56: =SUM(N57:N66) -> 0 | O56: % | P56: =iferror(N56/'PT Reporte SDR'!N72-1,"")
C57: Contestó Teléfono 1 | D57: =sum(H57) -> 8 | E57: =IFERROR(D57/$D$56,0) -> 0.28571429 | F57: =iferror(D57/'PT Reporte SDR'!D73-1,"") | H57: =COUNTIFS(Data!$A:$A,">="&'Reporte SDR '!$C$5,Data!$A:$A,"<="&'Reporte SDR '!$D$5,Data!$Y:$Y,C57)+8 -> 8 | I57: =IFERROR(H57/$D$56,0) -> 0.28571429 | J57: =iferror(H57/'PT Reporte SDR'!H73-1,"") | K57: =COUNTIFS(Data!$A:$A,">="&'Reporte SDR '!$C$5,Data!$A:$A,"<="&'Reporte SDR '!$D$5,Data!$E:$E,D57,Data!$BG:$BG,$H$7) -> 0 | L57: =IFERROR(K57/$D$56,0) -> 0 | M57: =iferror(K57/'PT Reporte SDR'!K73-1,"") | N57: =COUNTIFS(Data!$A:$A,">="&'Reporte SDR '!$C$5,Data!$A:$A,"<="&'Reporte SDR '!$D$5,Data!$E:$E,E57,Data!$BG:$BG,$H$7) -> 0 | O57: =IFERROR(N57/$D$56,0) -> 0 | P57: =iferror(N57/'PT Reporte SDR'!N73-1,"")
C58: Contestó Teléfono 2 | D58: =sum(H58) -> 0 | E58: =IFERROR(D58/$D$56,0) -> 0 | F58: =iferror(D58/'PT Reporte SDR'!D74-1,"") | H58: =COUNTIFS(Data!$A:$A,">="&'Reporte SDR '!$C$5,Data!$A:$A,"<="&'Reporte SDR '!$D$5,Data!$Y:$Y,C58) -> 0 | I58: =IFERROR(H58/$D$56,0) -> 0 | J58: =iferror(H58/'PT Reporte SDR'!H74-1,"") | K58: =COUNTIFS(Data!$A:$A,">="&'Reporte SDR '!$C$5,Data!$A:$A,"<="&'Reporte SDR '!$D$5,Data!$E:$E,D58,Data!$BG:$BG,$H$7) -> 0 | L58: =IFERROR(K58/$D$56,0) -> 0 | M58: =iferror(K58/'PT Reporte SDR'!K74-1,"") | N58: =COUNTIFS(Data!$A:$A,">="&'Reporte SDR '!$C$5,Data!$A:$A,"<="&'Reporte SDR '!$D$5,Data!$E:$E,E58,Data!$BG:$BG,$H$7) -> 0 | O58: =IFERROR(N58/$D$56,0) -> 0 | P58: =iferror(N58/'PT Reporte SDR'!N74-1,"")
C59: Contestó Teléfono 3 | D59: =sum(H59) -> 0 | E59: =IFERROR(D59/$D$56,0) -> 0 | F59: =iferror(D59/'PT Reporte SDR'!D75-1,"") | H59: =COUNTIFS(Data!$A:$A,">="&'Reporte SDR '!$C$5,Data!$A:$A,"<="&'Reporte SDR '!$D$5,Data!$Y:$Y,C59) -> 0 | I59: =IFERROR(H59/$D$56,0) -> 0 | J59: =iferror(H59/'PT Reporte SDR'!H75-1,"") | K59: =COUNTIFS(Data!$A:$A,">="&'Reporte SDR '!$C$5,Data!$A:$A,"<="&'Reporte SDR '!$D$5,Data!$E:$E,D59,Data!$BG:$BG,$H$7) -> 0 | L59: =IFERROR(K59/$D$56,0) -> 0 | M59: =iferror(K59/'PT Reporte SDR'!K75-1,"") | N59: =COUNTIFS(Data!$A:$A,">="&'Reporte SDR '!$C$5,Data!$A:$A,"<="&'Reporte SDR '!$D$5,Data!$E:$E,E59,Data!$BG:$BG,$H$7) -> 0 | O59: =IFERROR(N59/$D$56,0) -> 0 | P59: =iferror(N59/'PT Reporte SDR'!N75-1,"")
C60: Contestó Whatsapp 1 | D60: =sum(H60) -> 10 | E60: =IFERROR(D60/$D$56,0) -> 0.35714286 | F60: =iferror(D60/'PT Reporte SDR'!D76-1,"") | H60: =COUNTIFS(Data!$A:$A,">="&'Reporte SDR '!$C$5,Data!$A:$A,"<="&'Reporte SDR '!$D$5,Data!$Y:$Y,C60)+10 -> 10 | I60: =IFERROR(H60/$D$56,0) -> 0.35714286 | J60: =iferror(H60/'PT Reporte SDR'!H76-1,"") | K60: =COUNTIFS(Data!$A:$A,">="&'Reporte SDR '!$C$5,Data!$A:$A,"<="&'Reporte SDR '!$D$5,Data!$E:$E,D60,Data!$BG:$BG,$H$7) -> 0 | L60: =IFERROR(K60/$D$56,0) -> 0 | M60: =iferror(K60/'PT Reporte SDR'!K76-1,"") | N60: =COUNTIFS(Data!$A:$A,">="&'Reporte SDR '!$C$5,Data!$A:$A,"<="&'Reporte SDR '!$D$5,Data!$E:$E,E60,Data!$BG:$BG,$H$7) -> 0 | O60: =IFERROR(N60/$D$56,0) -> 0 | P60: =iferror(N60/'PT Reporte SDR'!N76-1,"")
C61: Contestó Whatsapp 2 | D61: =sum(H61) -> 10 | E61: =IFERROR(D61/$D$56,0) -> 0.35714286 | F61: =iferror(D61/'PT Reporte SDR'!D77-1,"") | H61: =COUNTIFS(Data!$A:$A,">="&'Reporte SDR '!$C$5,Data!$A:$A,"<="&'Reporte SDR '!$D$5,Data!$Y:$Y,C61)+10 -> 10 | I61: =IFERROR(H61/$D$56,0) -> 0.35714286 | J61: =iferror(H61/'PT Reporte SDR'!H77-1,"") | K61: =COUNTIFS(Data!$A:$A,">="&'Reporte SDR '!$C$5,Data!$A:$A,"<="&'Reporte SDR '!$D$5,Data!$E:$E,D61,Data!$BG:$BG,$H$7) -> 0 | L61: =IFERROR(K61/$D$56,0) -> 0 | M61: =iferror(K61/'PT Reporte SDR'!K77-1,"") | N61: =COUNTIFS(Data!$A:$A,">="&'Reporte SDR '!$C$5,Data!$A:$A,"<="&'Reporte SDR '!$D$5,Data!$E:$E,E61,Data!$BG:$BG,$H$7) -> 0 | O61: =IFERROR(N61/$D$56,0) -> 0 | P61: =iferror(N61/'PT Reporte SDR'!N77-1,"")
C62: Contestó Whatsapp 3 | D62: =sum(H62) -> 0 | E62: =IFERROR(D62/$D$56,0) -> 0 | F62: =iferror(D62/'PT Reporte SDR'!D78-1,"") | H62: =COUNTIFS(Data!$A:$A,">="&'Reporte SDR '!$C$5,Data!$A:$A,"<="&'Reporte SDR '!$D$5,Data!$Y:$Y,C62) -> 0 | I62: =IFERROR(H62/$D$56,0) -> 0 | J62: =iferror(H62/'PT Reporte SDR'!H78-1,"") | K62: =COUNTIFS(Data!$A:$A,">="&'Reporte SDR '!$C$5,Data!$A:$A,"<="&'Reporte SDR '!$D$5,Data!$E:$E,D62,Data!$BG:$BG,$H$7) -> 0 | L62: =IFERROR(K62/$D$56,0) -> 0 | M62: =iferror(K62/'PT Reporte SDR'!K78-1,"") | N62: =COUNTIFS(Data!$A:$A,">="&'Reporte SDR '!$C$5,Data!$A:$A,"<="&'Reporte SDR '!$D$5,Data!$E:$E,E62,Data!$BG:$BG,$H$7) -> 0 | O62: =IFERROR(N62/$D$56,0) -> 0 | P62: =iferror(N62/'PT Reporte SDR'!N78-1,"")
C63: Contestó Correo 1 | D63: =sum(H63) -> 0 | E63: =IFERROR(D63/$D$56,0) -> 0 | F63: =iferror(D63/'PT Reporte SDR'!D79-1,"") | H63: =COUNTIFS(Data!$A:$A,">="&'Reporte SDR '!$C$5,Data!$A:$A,"<="&'Reporte SDR '!$D$5,Data!$Y:$Y,C63) -> 0 | I63: =IFERROR(H63/$D$56,0) -> 0 | J63: =iferror(H63/'PT Reporte SDR'!H79-1,"") | K63: =COUNTIFS(Data!$A:$A,">="&'Reporte SDR '!$C$5,Data!$A:$A,"<="&'Reporte SDR '!$D$5,Data!$E:$E,D63,Data!$BG:$BG,$H$7) -> 0 | L63: =IFERROR(K63/$D$56,0) -> 0 | M63: =iferror(K63/'PT Reporte SDR'!K79-1,"") | N63: =COUNTIFS(Data!$A:$A,">="&'Reporte SDR '!$C$5,Data!$A:$A,"<="&'Reporte SDR '!$D$5,Data!$E:$E,E63,Data!$BG:$BG,$H$7) -> 0 | O63: =IFERROR(N63/$D$56,0) -> 0 | P63: =iferror(N63/'PT Reporte SDR'!N79-1,"")
C64: Contestó Correo 2 | D64: =sum(H64) -> 0 | E64: =IFERROR(D64/$D$56,0) -> 0 | F64: =iferror(D64/'PT Reporte SDR'!D80-1,"") | H64: =COUNTIFS(Data!$A:$A,">="&'Reporte SDR '!$C$5,Data!$A:$A,"<="&'Reporte SDR '!$D$5,Data!$Y:$Y,C64) -> 0 | I64: =IFERROR(H64/$D$56,0) -> 0 | J64: =iferror(H64/'PT Reporte SDR'!H80-1,"") | K64: =COUNTIFS(Data!$A:$A,">="&'Reporte SDR '!$C$5,Data!$A:$A,"<="&'Reporte SDR '!$D$5,Data!$E:$E,D64,Data!$BG:$BG,$H$7) -> 0 | L64: =IFERROR(K64/$D$56,0) -> 0 | M64: =iferror(K64/'PT Reporte SDR'!K80-1,"") | N64: =COUNTIFS(Data!$A:$A,">="&'Reporte SDR '!$C$5,Data!$A:$A,"<="&'Reporte SDR '!$D$5,Data!$E:$E,E64,Data!$BG:$BG,$H$7) -> 0 | O64: =IFERROR(N64/$D$56,0) -> 0 | P64: =iferror(N64/'PT Reporte SDR'!N80-1,"")
C65: Contestó Correo 3 | D65: =sum(H65) -> 0 | E65: =IFERROR(D65/$D$56,0) -> 0 | F65: =iferror(D65/'PT Reporte SDR'!D81-1,"") | H65: =COUNTIFS(Data!$A:$A,">="&'Reporte SDR '!$C$5,Data!$A:$A,"<="&'Reporte SDR '!$D$5,Data!$Y:$Y,C65) -> 0 | I65: =IFERROR(H65/$D$56,0) -> 0 | J65: =iferror(H65/'PT Reporte SDR'!H81-1,"") | K65: =COUNTIFS(Data!$A:$A,">="&'Reporte SDR '!$C$5,Data!$A:$A,"<="&'Reporte SDR '!$D$5,Data!$E:$E,D65,Data!$BG:$BG,$H$7) -> 0 | L65: =IFERROR(K65/$D$56,0) -> 0 | M65: =iferror(K65/'PT Reporte SDR'!K81-1,"") | N65: =COUNTIFS(Data!$A:$A,">="&'Reporte SDR '!$C$5,Data!$A:$A,"<="&'Reporte SDR '!$D$5,Data!$E:$E,E65,Data!$BG:$BG,$H$7) -> 0 | O65: =IFERROR(N65/$D$56,0) -> 0 | P65: =iferror(N65/'PT Reporte SDR'!N81-1,"")
C66: Contestó Correo 4 | D66: =sum(H66) -> 0 | E66: =IFERROR(D66/$D$56,0) -> 0 | F66: =iferror(D66/'PT Reporte SDR'!D82-1,"") | H66: =COUNTIFS(Data!$A:$A,">="&'Reporte SDR '!$C$5,Data!$A:$A,"<="&'Reporte SDR '!$D$5,Data!$Y:$Y,C66) -> 0 | I66: =IFERROR(H66/$D$56,0) -> 0 | J66: =iferror(H66/'PT Reporte SDR'!H82-1,"") | K66: =COUNTIFS(Data!$A:$A,">="&'Reporte SDR '!$C$5,Data!$A:$A,"<="&'Reporte SDR '!$D$5,Data!$E:$E,D66,Data!$BG:$BG,$H$7) -> 0 | L66: =IFERROR(K66/$D$56,0) -> 0 | M66: =iferror(K66/'PT Reporte SDR'!K82-1,"") | N66: =COUNTIFS(Data!$A:$A,">="&'Reporte SDR '!$C$5,Data!$A:$A,"<="&'Reporte SDR '!$D$5,Data!$E:$E,E66,Data!$BG:$BG,$H$7) -> 0 | O66: =IFERROR(N66/$D$56,0) -> 0 | P66: =iferror(N66/'PT Reporte SDR'!N82-1,"")
F67: =iferror(D67/'PT Reporte SDR'!D83-1,"") | J67: =iferror(H67/'PT Reporte SDR'!H83-1,"") | M67: =iferror(K67/'PT Reporte SDR'!K83-1,"") | P67: =iferror(N67/'PT Reporte SDR'!N83-1,"")
F68: =iferror(D68/'PT Reporte SDR'!D84-1,"") | J68: =iferror(H68/'PT Reporte SDR'!H84-1,"") | M68: =iferror(K68/'PT Reporte SDR'!K84-1,"") | P68: =iferror(N68/'PT Reporte SDR'!N84-1,"")
C69: Total Lead en Proceso de Contacto (aún sin respuesta) | D69: =SUM(D70:D77) -> 0 | E69: % Total | F69: =iferror(D69/'PT Reporte SDR'!D85-1,"") | H69: =SUM(H70:H77) -> 0 | I69: % Total | J69: =iferror(H69/'PT Reporte SDR'!H85-1,"") | K69: =SUM(K70:K77) -> 0 | L69: % Total | M69: =iferror(K69/'PT Reporte SDR'!K85-1,"") | N69: =SUM(N70:N77) -> 0 | O69: % Total | P69: =iferror(N69/'PT Reporte SDR'!N85-1,"")
C70: No Contestó Teléfono 1 | D70: =sum(H70) -> 0 | E70: =iferror(D70/$D$69,0) -> 0 | F70: =iferror(D70/'PT Reporte SDR'!D86-1,"") | H70: =COUNTIFS(Data!$A:$A,">="&'Reporte SDR '!$C$5,Data!$A:$A,"<="&'Reporte SDR '!$D$5,Data!$Y:$Y,C70) -> 0 | I70: =iferror(H70/$D$69,0) -> 0 | J70: =iferror(H70/'PT Reporte SDR'!H86-1,"") | K70: =COUNTIFS(Data!$A:$A,">="&'Reporte SDR '!$C$5,Data!$A:$A,"<="&'Reporte SDR '!$D$5,Data!$E:$E,D70,Data!$BG:$BG,$H$7) -> 0 | L70: =iferror(K70/$D$69,0) -> 0 | M70: =iferror(K70/'PT Reporte SDR'!K86-1,"") | N70: =COUNTIFS(Data!$A:$A,">="&'Reporte SDR '!$C$5,Data!$A:$A,"<="&'Reporte SDR '!$D$5,Data!$E:$E,E70,Data!$BG:$BG,$H$7) -> 0 | O70: =iferror(N70/$D$69,0) -> 0 | P70: =iferror(N70/'PT Reporte SDR'!N86-1,"")
C71: No Contestó Teléfono 2 | D71: =sum(H71) -> 0 | E71: =iferror(D71/$D$69,0) -> 0 | F71: =iferror(D71/'PT Reporte SDR'!D87-1,"") | H71: =COUNTIFS(Data!$A:$A,">="&'Reporte SDR '!$C$5,Data!$A:$A,"<="&'Reporte SDR '!$D$5,Data!$Y:$Y,C71) -> 0 | I71: =iferror(H71/$D$69,0) -> 0 | J71: =iferror(H71/'PT Reporte SDR'!H87-1,"") | K71: =COUNTIFS(Data!$A:$A,">="&'Reporte SDR '!$C$5,Data!$A:$A,"<="&'Reporte SDR '!$D$5,Data!$E:$E,D71,Data!$BG:$BG,$H$7) -> 0 | L71: =iferror(K71/$D$69,0) -> 0 | M71: =iferror(K71/'PT Reporte SDR'!K87-1,"") | N71: =COUNTIFS(Data!$A:$A,">="&'Reporte SDR '!$C$5,Data!$A:$A,"<="&'Reporte SDR '!$D$5,Data!$E:$E,E71,Data!$BG:$BG,$H$7) -> 0 | O71: =iferror(N71/$D$69,0) -> 0 | P71: =iferror(N71/'PT Reporte SDR'!N87-1,"")
C72: No Contesto Teléfono 3 | D72: =sum(H72) -> 0 | E72: =iferror(D72/$D$69,0) -> 0 | F72: =iferror(D72/'PT Reporte SDR'!D88-1,"") | H72: =COUNTIFS(Data!$A:$A,">="&'Reporte SDR '!$C$5,Data!$A:$A,"<="&'Reporte SDR '!$D$5,Data!$Y:$Y,C72) -> 0 | I72: =iferror(H72/$D$69,0) -> 0 | J72: =iferror(H72/'PT Reporte SDR'!H88-1,"") | K72: =COUNTIFS(Data!$A:$A,">="&'Reporte SDR '!$C$5,Data!$A:$A,"<="&'Reporte SDR '!$D$5,Data!$E:$E,D72,Data!$BG:$BG,$H$7) -> 0 | L72: =iferror(K72/$D$69,0) -> 0 | M72: =iferror(K72/'PT Reporte SDR'!K88-1,"") | N72: =COUNTIFS(Data!$A:$A,">="&'Reporte SDR '!$C$5,Data!$A:$A,"<="&'Reporte SDR '!$D$5,Data!$E:$E,E72,Data!$BG:$BG,$H$7) -> 0 | O72: =iferror(N72/$D$69,0) -> 0 | P72: =iferror(N72/'PT Reporte SDR'!N88-1,"")
C73: No Contestó Whatsapp 1 | D73: =sum(H73) -> 0 | E73: =iferror(D73/$D$69,0) -> 0 | F73: =iferror(D73/'PT Reporte SDR'!D89-1,"") | H73: =COUNTIFS(Data!$A:$A,">="&'Reporte SDR '!$C$5,Data!$A:$A,"<="&'Reporte SDR '!$D$5,Data!$Y:$Y,C73) -> 0 | I73: =iferror(H73/$D$69,0) -> 0 | J73: =iferror(H73/'PT Reporte SDR'!H89-1,"") | K73: =COUNTIFS(Data!$A:$A,">="&'Reporte SDR '!$C$5,Data!$A:$A,"<="&'Reporte SDR '!$D$5,Data!$E:$E,D73,Data!$BG:$BG,$H$7) -> 0 | L73: =iferror(K73/$D$69,0) -> 0 | M73: =iferror(K73/'PT Reporte SDR'!K89-1,"") | N73: =COUNTIFS(Data!$A:$A,">="&'Reporte SDR '!$C$5,Data!$A:$A,"<="&'Reporte SDR '!$D$5,Data!$E:$E,E73,Data!$BG:$BG,$H$7) -> 0 | O73: =iferror(N73/$D$69,0) -> 0 | P73: =iferror(N73/'PT Reporte SDR'!N89-1,"")
C74: No Contestó Whatsapp 2 | D74: =sum(H74) -> 0 | E74: =iferror(D74/$D$69,0) -> 0 | F74: =iferror(D74/'PT Reporte SDR'!D90-1,"") | H74: =COUNTIFS(Data!$A:$A,">="&'Reporte SDR '!$C$5,Data!$A:$A,"<="&'Reporte SDR '!$D$5,Data!$Y:$Y,C74) -> 0 | I74: =iferror(H74/$D$69,0) -> 0 | J74: =iferror(H74/'PT Reporte SDR'!H90-1,"") | K74: =COUNTIFS(Data!$A:$A,">="&'Reporte SDR '!$C$5,Data!$A:$A,"<="&'Reporte SDR '!$D$5,Data!$E:$E,D74,Data!$BG:$BG,$H$7) -> 0 | L74: =iferror(K74/$D$69,0) -> 0 | M74: =iferror(K74/'PT Reporte SDR'!K90-1,"") | N74: =COUNTIFS(Data!$A:$A,">="&'Reporte SDR '!$C$5,Data!$A:$A,"<="&'Reporte SDR '!$D$5,Data!$E:$E,E74,Data!$BG:$BG,$H$7) -> 0 | O74: =iferror(N74/$D$69,0) -> 0 | P74: =iferror(N74/'PT Reporte SDR'!N90-1,"")
C75: No Contestó Whatsapp 3 | D75: =sum(H75) -> 0 | E75: =iferror(D75/$D$69,0) -> 0 | F75: =iferror(D75/'PT Reporte SDR'!D91-1,"") | H75: =COUNTIFS(Data!$A:$A,">="&'Reporte SDR '!$C$5,Data!$A:$A,"<="&'Reporte SDR '!$D$5,Data!$Y:$Y,C75) -> 0 | I75: =iferror(H75/$D$69,0) -> 0 | J75: =iferror(H75/'PT Reporte SDR'!H91-1,"") | K75: =COUNTIFS(Data!$A:$A,">="&'Reporte SDR '!$C$5,Data!$A:$A,"<="&'Reporte SDR '!$D$5,Data!$E:$E,D75,Data!$BG:$BG,$H$7) -> 0 | L75: =iferror(K75/$D$69,0) -> 0 | M75: =iferror(K75/'PT Reporte SDR'!K91-1,"") | N75: =COUNTIFS(Data!$A:$A,">="&'Reporte SDR '!$C$5,Data!$A:$A,"<="&'Reporte SDR '!$D$5,Data!$E:$E,E75,Data!$BG:$BG,$H$7) -> 0 | O75: =iferror(N75/$D$69,0) -> 0 | P75: =iferror(N75/'PT Reporte SDR'!N91-1,"")
F76: =iferror(D76/'PT Reporte SDR'!D92-1,"") | J76: =iferror(H76/'PT Reporte SDR'!H92-1,"") | M76: =iferror(K76/'PT Reporte SDR'!K92-1,"") | P76: =iferror(N76/'PT Reporte SDR'!N92-1,"")
F77: =iferror(D77/'PT Reporte SDR'!D93-1,"") | J77: =iferror(H77/'PT Reporte SDR'!H93-1,"") | M77: =iferror(K77/'PT Reporte SDR'!K93-1,"") | P77: =iferror(N77/'PT Reporte SDR'!N93-1,"")
F78: =iferror(D78/'PT Reporte SDR'!D94-1,"") | J78: =iferror(H78/'PT Reporte SDR'!H94-1,"") | M78: =iferror(K78/'PT Reporte SDR'!K94-1,"") | P78: =iferror(N78/'PT Reporte SDR'!N94-1,"")
C79: Total Leads Contactados sin Respuesta (6to Toque) | D79: =SUM(D80:D81) -> 0 | E79: % Total | F79: =iferror(D79/'PT Reporte SDR'!D95-1,"") | H79: =SUM(H80:H81) -> 0 | I79: % Total | J79: =iferror(H79/'PT Reporte SDR'!H95-1,"") | K79: =SUM(K80:K81) -> 0 | L79: % Total | M79: =iferror(K79/'PT Reporte SDR'!K95-1,"") | N79: =SUM(N80:N81) -> 0 | O79: % Total | P79: =iferror(N79/'PT Reporte SDR'!N95-1,"")
C80: Toque 6 | D80: =sum(H80) -> 0 | E80: =IFERROR(D80/$D$79,0) -> 0 | F80: =iferror(D80/'PT Reporte SDR'!D96-1,"") | H80: =COUNTIFS(Data!$A:$A,">="&'Reporte SDR '!$C$5,Data!$A:$A,"<="&'Reporte SDR '!$D$5,Data!$AE:$AE,C80) -> 0 | I80: =IFERROR(H80/$D$79,0) -> 0 | J80: =iferror(H80/'PT Reporte SDR'!H96-1,"") | L80: =IFERROR(K80/$D$79,0) -> 0 | M80: =iferror(K80/'PT Reporte SDR'!K96-1,"") | O80: =IFERROR(N80/$D$79,0) -> 0 | P80: =iferror(N80/'PT Reporte SDR'!N96-1,"")
F81: =iferror(D81/'PT Reporte SDR'!D97-1,"") | J81: =iferror(H81/'PT Reporte SDR'!H97-1,"") | M81: =iferror(K81/'PT Reporte SDR'!K97-1,"") | P81: =iferror(N81/'PT Reporte SDR'!N97-1,"")
F82: =iferror(D82/'PT Reporte SDR'!D98-1,"") | J82: =iferror(H82/'PT Reporte SDR'!H98-1,"") | M82: =iferror(K82/'PT Reporte SDR'!K98-1,"") | P82: =iferror(N82/'PT Reporte SDR'!N98-1,"")
C83: ¿Por Qué No Pasó a Ventas? | D83: =sum(D84:D125) -> 3 | E83: % | F83: =iferror(D83/'PT Reporte SDR'!D99-1,"") | H83: =SUM(H84:H125) -> 3 | I83: % | J83: =iferror(H83/'PT Reporte SDR'!H99-1,"") | K83: =SUM(K84:K125) -> 0 | L83: % | M83: =iferror(K83/'PT Reporte SDR'!K99-1,"") | N83: =SUM(N84:N125) -> 0 | O83: % | P83: =iferror(N83/'PT Reporte SDR'!N99-1,"")
C84: Toque 6 | D84: =H84+K84+N84 -> 0 | E84: =D84/$D$83 -> 0 | F84: =iferror(D84/'PT Reporte SDR'!D100-1,"") | H84: =COUNTIFS(Data!$A:$A,">="&'Reporte SDR '!$C$5,Data!$A:$A,"<="&'Reporte SDR '!$D$5,Data!$AD:$AD,C84) -> 0 | I84: =H84/$D$83 -> 0 | J84: =iferror(H84/'PT Reporte SDR'!H100-1,"") | K84: =COUNTIFS(Data!$A:$A,">="&'Reporte SDR '!$C$5,Data!$A:$A,"<="&'Reporte SDR '!$D$5,Data!$BI:$BI,$H$7,Data!$DF:$DF,C84) -> 0 | L84: =K84/$D$83 -> 0 | M84: =iferror(K84/'PT Reporte SDR'!K100-1,"") | N84: =COUNTIFS(Data!$A:$A,">="&'Reporte SDR '!$C$5,Data!$A:$A,"<="&'Reporte SDR '!$D$5,Data!$BI:$BI,$H$7,Data!$DF:$DF,C84) -> 0 | O84: =N84/$D$83 -> 0 | P84: =iferror(N84/'PT Reporte SDR'!N100-1,"")
C85: Nunca Respondió | D85: =H85+K85+N85 -> 0 | E85: =D85/$D$83 -> 0 | F85: =iferror(D85/'PT Reporte SDR'!D101-1,"") | H85: =COUNTIFS(Data!$A:$A,">="&'Reporte SDR '!$C$5,Data!$A:$A,"<="&'Reporte SDR '!$D$5,Data!$AD:$AD,C85) -> 0 | I85: =H85/$D$83 -> 0 | J85: =iferror(H85/'PT Reporte SDR'!H101-1,"") | K85: =COUNTIFS(Data!$A:$A,">="&'Reporte SDR '!$C$5,Data!$A:$A,"<="&'Reporte SDR '!$D$5,Data!$BI:$BI,$H$7,Data!$DF:$DF,C85) -> 0 | L85: =K85/$D$83 -> 0 | M85: =iferror(K85/'PT Reporte SDR'!K101-1,"") | N85: =COUNTIFS(Data!$A:$A,">="&'Reporte SDR '!$C$5,Data!$A:$A,"<="&'Reporte SDR '!$D$5,Data!$BI:$BI,$H$7,Data!$DF:$DF,C85) -> 0 | O85: =N85/$D$83 -> 0 | P85: =iferror(N85/'PT Reporte SDR'!N101-1,"")
C86: Dejó de responder | D86: =H86+K86+N86 -> 0 | E86: =D86/$D$83 -> 0 | F86: =iferror(D86/'PT Reporte SDR'!D102-1,"") | H86: =COUNTIFS(Data!$A:$A,">="&'Reporte SDR '!$C$5,Data!$A:$A,"<="&'Reporte SDR '!$D$5,Data!$AD:$AD,C86) -> 0 | I86: =H86/$D$83 -> 0 | J86: =iferror(H86/'PT Reporte SDR'!H102-1,"") | K86: =COUNTIFS(Data!$A:$A,">="&'Reporte SDR '!$C$5,Data!$A:$A,"<="&'Reporte SDR '!$D$5,Data!$BI:$BI,$H$7,Data!$DF:$DF,C86) -> 0 | L86: =K86/$D$83 -> 0 | M86: =iferror(K86/'PT Reporte SDR'!K102-1,"") | N86: =COUNTIFS(Data!$A:$A,">="&'Reporte SDR '!$C$5,Data!$A:$A,"<="&'Reporte SDR '!$D$5,Data!$BI:$BI,$H$7,Data!$DF:$DF,C86) -> 0 | O86: =N86/$D$83 -> 0 | P86: =iferror(N86/'PT Reporte SDR'!N102-1,"")
C87: No tuvo más interés | D87: =H87+K87+N87 -> 2 | E87: =D87/$D$83 -> 0.66666667 | F87: =iferror(D87/'PT Reporte SDR'!D103-1,"") | H87: =COUNTIFS(Data!$A:$A,">="&'Reporte SDR '!$C$5,Data!$A:$A,"<="&'Reporte SDR '!$D$5,Data!$AD:$AD,C87)+2 -> 2 | I87: =H87/$D$83 -> 0.66666667 | J87: =iferror(H87/'PT Reporte SDR'!H103-1,"") | K87: =COUNTIFS(Data!$A:$A,">="&'Reporte SDR '!$C$5,Data!$A:$A,"<="&'Reporte SDR '!$D$5,Data!$BI:$BI,$H$7,Data!$DF:$DF,C87) -> 0 | L87: =K87/$D$83 -> 0 | M87: =iferror(K87/'PT Reporte SDR'!K103-1,"") | N87: =COUNTIFS(Data!$A:$A,">="&'Reporte SDR '!$C$5,Data!$A:$A,"<="&'Reporte SDR '!$D$5,Data!$BI:$BI,$H$7,Data!$DF:$DF,C87) -> 0 | O87: =N87/$D$83 -> 0 | P87: =iferror(N87/'PT Reporte SDR'!N103-1,"")
C88: Desconoce el registro | D88: =H88+K88+N88 -> 0 | E88: =D88/$D$83 -> 0 | F88: =iferror(D88/'PT Reporte SDR'!D104-1,"") | H88: =COUNTIFS(Data!$A:$A,">="&'Reporte SDR '!$C$5,Data!$A:$A,"<="&'Reporte SDR '!$D$5,Data!$AD:$AD,C88) -> 0 | I88: =H88/$D$83 -> 0 | J88: =iferror(H88/'PT Reporte SDR'!H104-1,"") | K88: =COUNTIFS(Data!$A:$A,">="&'Reporte SDR '!$C$5,Data!$A:$A,"<="&'Reporte SDR '!$D$5,Data!$BI:$BI,$H$7,Data!$DF:$DF,C88) -> 0 | L88: =K88/$D$83 -> 0 | M88: =iferror(K88/'PT Reporte SDR'!K104-1,"") | N88: =COUNTIFS(Data!$A:$A,">="&'Reporte SDR '!$C$5,Data!$A:$A,"<="&'Reporte SDR '!$D$5,Data!$BI:$BI,$H$7,Data!$DF:$DF,C88) -> 0 | O88: =N88/$D$83 -> 0 | P88: =iferror(N88/'PT Reporte SDR'!N104-1,"")
C89: Ya resolvió su necesidad | D89: =H89+K89+N89 -> 0 | E89: =D89/$D$83 -> 0 | F89: =iferror(D89/'PT Reporte SDR'!D105-1,"") | H89: =COUNTIFS(Data!$A:$A,">="&'Reporte SDR '!$C$5,Data!$A:$A,"<="&'Reporte SDR '!$D$5,Data!$AD:$AD,C89) -> 0 | I89: =H89/$D$83 -> 0 | J89: =iferror(H89/'PT Reporte SDR'!H105-1,"") | K89: =COUNTIFS(Data!$A:$A,">="&'Reporte SDR '!$C$5,Data!$A:$A,"<="&'Reporte SDR '!$D$5,Data!$BI:$BI,$H$7,Data!$DF:$DF,C89) -> 0 | L89: =K89/$D$83 -> 0 | M89: =iferror(K89/'PT Reporte SDR'!K105-1,"") | N89: =COUNTIFS(Data!$A:$A,">="&'Reporte SDR '!$C$5,Data!$A:$A,"<="&'Reporte SDR '!$D$5,Data!$BI:$BI,$H$7,Data!$DF:$DF,C89) -> 0 | O89: =N89/$D$83 -> 0 | P89: =iferror(N89/'PT Reporte SDR'!N105-1,"")
C90: No se cuenta con el servicio | D90: =H90+K90+N90 -> 0 | E90: =D90/$D$83 -> 0 | F90: =iferror(D90/'PT Reporte SDR'!D106-1,"") | H90: =COUNTIFS(Data!$A:$A,">="&'Reporte SDR '!$C$5,Data!$A:$A,"<="&'Reporte SDR '!$D$5,Data!$AD:$AD,C90) -> 0 | I90: =H90/$D$83 -> 0 | J90: =iferror(H90/'PT Reporte SDR'!H106-1,"") | K90: =COUNTIFS(Data!$A:$A,">="&'Reporte SDR '!$C$5,Data!$A:$A,"<="&'Reporte SDR '!$D$5,Data!$BI:$BI,$H$7,Data!$DF:$DF,C90) -> 0 | L90: =K90/$D$83 -> 0 | M90: =iferror(K90/'PT Reporte SDR'!K106-1,"") | N90: =COUNTIFS(Data!$A:$A,">="&'Reporte SDR '!$C$5,Data!$A:$A,"<="&'Reporte SDR '!$D$5,Data!$BI:$BI,$H$7,Data!$DF:$DF,C90) -> 0 | O90: =N90/$D$83 -> 0 | P90: =iferror(N90/'PT Reporte SDR'!N106-1,"")
C91: Busca ser proveedor | D91: =H91+K91+N91 -> 0 | E91: =D91/$D$83 -> 0 | F91: =iferror(D91/'PT Reporte SDR'!D107-1,"") | H91: =COUNTIFS(Data!$A:$A,">="&'Reporte SDR '!$C$5,Data!$A:$A,"<="&'Reporte SDR '!$D$5,Data!$AE:$AE,C91) -> 0 | I91: =H91/$D$83 -> 0 | J91: =iferror(H91/'PT Reporte SDR'!H107-1,"") | K91: =COUNTIFS(Data!$A:$A,">="&'Reporte SDR '!$C$5,Data!$A:$A,"<="&'Reporte SDR '!$D$5,Data!$BI:$BI,$H$7,Data!$DF:$DF,C91) -> 0 | L91: =K91/$D$83 -> 0 | M91: =iferror(K91/'PT Reporte SDR'!K107-1,"") | N91: =COUNTIFS(Data!$A:$A,">="&'Reporte SDR '!$C$5,Data!$A:$A,"<="&'Reporte SDR '!$D$5,Data!$BI:$BI,$H$7,Data!$DF:$DF,C91) -> 0 | O91: =N91/$D$83 -> 0 | P91: =iferror(N91/'PT Reporte SDR'!N107-1,"")
C92: Busca empleo | D92: =H92+K92+N92 -> 0 | E92: =D92/$D$83 -> 0 | F92: =iferror(D92/'PT Reporte SDR'!D108-1,"") | H92: =COUNTIFS(Data!$A:$A,">="&'Reporte SDR '!$C$5,Data!$A:$A,"<="&'Reporte SDR '!$D$5,Data!$AD:$AD,C92) -> 0 | I92: =H92/$D$83 -> 0 | J92: =iferror(H92/'PT Reporte SDR'!H108-1,"") | K92: =COUNTIFS(Data!$A:$A,">="&'Reporte SDR '!$C$5,Data!$A:$A,"<="&'Reporte SDR '!$D$5,Data!$BI:$BI,$H$7,Data!$DF:$DF,C92) -> 0 | L92: =K92/$D$83 -> 0 | M92: =iferror(K92/'PT Reporte SDR'!K108-1,"") | N92: =COUNTIFS(Data!$A:$A,">="&'Reporte SDR '!$C$5,Data!$A:$A,"<="&'Reporte SDR '!$D$5,Data!$BI:$BI,$H$7,Data!$DF:$DF,C92) -> 0 | O92: =N92/$D$83 -> 0 | P92: =iferror(N92/'PT Reporte SDR'!N108-1,"")
C93: Pidió no volver a llamar | D93: =H93+K93+N93 -> 0 | E93: =D93/$D$83 -> 0 | F93: =iferror(D93/'PT Reporte SDR'!D109-1,"") | H93: =COUNTIFS(Data!$A:$A,">="&'Reporte SDR '!$C$5,Data!$A:$A,"<="&'Reporte SDR '!$D$5,Data!$AD:$AD,C93) -> 0 | I93: =H93/$D$83 -> 0 | J93: =iferror(H93/'PT Reporte SDR'!H109-1,"") | K93: =COUNTIFS(Data!$A:$A,">="&'Reporte SDR '!$C$5,Data!$A:$A,"<="&'Reporte SDR '!$D$5,Data!$BI:$BI,$H$7,Data!$DF:$DF,C93) -> 0 | L93: =K93/$D$83 -> 0 | M93: =iferror(K93/'PT Reporte SDR'!K109-1,"") | N93: =COUNTIFS(Data!$A:$A,">="&'Reporte SDR '!$C$5,Data!$A:$A,"<="&'Reporte SDR '!$D$5,Data!$BI:$BI,$H$7,Data!$DF:$DF,C93) -> 0 | O93: =N93/$D$83 -> 0 | P93: =iferror(N93/'PT Reporte SDR'!N109-1,"")
C94: Motivos Personales | D94: =H94+K94+N94 -> 1 | E94: =D94/$D$83 -> 0.33333333 | F94: =iferror(D94/'PT Reporte SDR'!D110-1,"") | H94: =COUNTIFS(Data!$A:$A,">="&'Reporte SDR '!$C$5,Data!$A:$A,"<="&'Reporte SDR '!$D$5,Data!$AD:$AD,C94)+1 -> 1 | I94: =H94/$D$83 -> 0.33333333 | J94: =iferror(H94/'PT Reporte SDR'!H110-1,"") | K94: =COUNTIFS(Data!$A:$A,">="&'Reporte SDR '!$C$5,Data!$A:$A,"<="&'Reporte SDR '!$D$5,Data!$BI:$BI,$H$7,Data!$DF:$DF,C94) -> 0 | L94: =K94/$D$83 -> 0 | M94: =iferror(K94/'PT Reporte SDR'!K110-1,"") | N94: =COUNTIFS(Data!$A:$A,">="&'Reporte SDR '!$C$5,Data!$A:$A,"<="&'Reporte SDR '!$D$5,Data!$BI:$BI,$H$7,Data!$DF:$DF,C94) -> 0 | O94: =N94/$D$83 -> 0 | P94: =iferror(N94/'PT Reporte SDR'!N110-1,"")
C95: No me llames, yo te llamo | D95: =H95+K95+N95 -> 0 | E95: =D95/$D$83 -> 0 | F95: =iferror(D95/'PT Reporte SDR'!D111-1,"") | H95: =COUNTIFS(Data!$A:$A,">="&'Reporte SDR '!$C$5,Data!$A:$A,"<="&'Reporte SDR '!$D$5,Data!$AD:$AD,C95) -> 0 | I95: =H95/$D$83 -> 0 | J95: =iferror(H95/'PT Reporte SDR'!H111-1,"") | K95: =COUNTIFS(Data!$A:$A,">="&'Reporte SDR '!$C$5,Data!$A:$A,"<="&'Reporte SDR '!$D$5,Data!$BI:$BI,$H$7,Data!$DF:$DF,C95) -> 0 | L95: =K95/$D$83 -> 0 | M95: =iferror(K95/'PT Reporte SDR'!K111-1,"") | N95: =COUNTIFS(Data!$A:$A,">="&'Reporte SDR '!$C$5,Data!$A:$A,"<="&'Reporte SDR '!$D$5,Data!$BI:$BI,$H$7,Data!$DF:$DF,C95) -> 0 | O95: =N95/$D$83 -> 0 | P95: =iferror(N95/'PT Reporte SDR'!N111-1,"")
C96: No cuenta con el dinero | D96: =H96+K96+N96 -> 0 | E96: =D96/$D$83 -> 0 | F96: =iferror(D96/'PT Reporte SDR'!D112-1,"") | H96: =COUNTIFS(Data!$A:$A,">="&'Reporte SDR '!$C$5,Data!$A:$A,"<="&'Reporte SDR '!$D$5,Data!$AD:$AD,C96) -> 0 | I96: =H96/$D$83 -> 0 | J96: =iferror(H96/'PT Reporte SDR'!H112-1,"") | K96: =COUNTIFS(Data!$A:$A,">="&'Reporte SDR '!$C$5,Data!$A:$A,"<="&'Reporte SDR '!$D$5,Data!$BI:$BI,$H$7,Data!$DF:$DF,C96) -> 0 | L96: =K96/$D$83 -> 0 | M96: =iferror(K96/'PT Reporte SDR'!K112-1,"") | N96: =COUNTIFS(Data!$A:$A,">="&'Reporte SDR '!$C$5,Data!$A:$A,"<="&'Reporte SDR '!$D$5,Data!$BI:$BI,$H$7,Data!$DF:$DF,C96) -> 0 | O96: =N96/$D$83 -> 0 | P96: =iferror(N96/'PT Reporte SDR'!N112-1,"")
F97: =iferror(D97/'PT Reporte SDR'!D112-1,"") | J97: =iferror(H97/'PT Reporte SDR'!H112-1,"") | M97: =iferror(K97/'PT Reporte SDR'!K112-1,"") | P97: =iferror(N97/'PT Reporte SDR'!N112-1,"")
F98: =iferror(D98/'PT Reporte SDR'!D113-1,"") | J98: =iferror(H98/'PT Reporte SDR'!H113-1,"") | M98: =iferror(K98/'PT Reporte SDR'!K113-1,"") | P98: =iferror(N98/'PT Reporte SDR'!N113-1,"")
C99: ¿Por qué se perdió la venta? | D99: =H99+K99+N99 -> 0 | E99: =D99/$D$83 -> 0 | F99: =iferror(D99/'PT Reporte SDR'!D114-1,"") | H99: =COUNTIFS(Data!$A:$A,">="&'Reporte SDR '!$C$5,Data!$A:$A,"<="&'Reporte SDR '!$D$5,Data!$BI:$BI,$H$7,Data!$DF:$DF,C99) -> 0 | I99: =H99/$D$83 -> 0 | J99: =iferror(H99/'PT Reporte SDR'!H114-1,"") | K99: =COUNTIFS(Data!$A:$A,">="&'Reporte SDR '!$C$5,Data!$A:$A,"<="&'Reporte SDR '!$D$5,Data!$BI:$BI,$H$7,Data!$DF:$DF,C99) -> 0 | L99: =K99/$D$83 -> 0 | M99: =iferror(K99/'PT Reporte SDR'!K114-1,"") | N99: =COUNTIFS(Data!$A:$A,">="&'Reporte SDR '!$C$5,Data!$A:$A,"<="&'Reporte SDR '!$D$5,Data!$BI:$BI,$H$7,Data!$DF:$DF,C99) -> 0 | O99: =N99/$D$83 -> 0 | P99: =iferror(N99/'PT Reporte SDR'!N114-1,"")
C100: No le interesó la cotización | D100: =H100+K100+N100 -> 0 | E100: =D100/$D$83 -> 0 | F100: =iferror(D100/'PT Reporte SDR'!D115-1,"") | H100: =COUNTIFS(Data!$A:$A,">="&'Reporte SDR '!$C$5,Data!$A:$A,"<="&'Reporte SDR '!$D$5,Data!$BR:$BR,C100) -> 0 | I100: =H100/$D$83 -> 0 | J100: =iferror(H100/'PT Reporte SDR'!H115-1,"") | K100: =COUNTIFS(Data!$A:$A,">="&'Reporte SDR '!$C$5,Data!$A:$A,"<="&'Reporte SDR '!$D$5,Data!$BI:$BI,$H$7,Data!$DF:$DF,C100) -> 0 | L100: =K100/$D$83 -> 0 | M100: =iferror(K100/'PT Reporte SDR'!K115-1,"") | N100: =COUNTIFS(Data!$A:$A,">="&'Reporte SDR '!$C$5,Data!$A:$A,"<="&'Reporte SDR '!$D$5,Data!$BI:$BI,$H$7,Data!$DF:$DF,C100) -> 0 | O100: =N100/$D$83 -> 0 | P100: =iferror(N100/'PT Reporte SDR'!N115-1,"")
C101: Le pareció costoso | D101: =H101+K101+N101 -> 0 | E101: =D101/$D$83 -> 0 | F101: =iferror(D101/'PT Reporte SDR'!D116-1,"") | H101: =COUNTIFS(Data!$A:$A,">="&'Reporte SDR '!$C$5,Data!$A:$A,"<="&'Reporte SDR '!$D$5,Data!$BR:$BR,C101) -> 0 | I101: =H101/$D$83 -> 0 | J101: =iferror(H101/'PT Reporte SDR'!H116-1,"") | K101: =COUNTIFS(Data!$A:$A,">="&'Reporte SDR '!$C$5,Data!$A:$A,"<="&'Reporte SDR '!$D$5,Data!$BI:$BI,$H$7,Data!$DF:$DF,C101) -> 0 | L101: =K101/$D$83 -> 0 | M101: =iferror(K101/'PT Reporte SDR'!K116-1,"") | N101: =COUNTIFS(Data!$A:$A,">="&'Reporte SDR '!$C$5,Data!$A:$A,"<="&'Reporte SDR '!$D$5,Data!$BI:$BI,$H$7,Data!$DF:$DF,C101) -> 0 | O101: =N101/$D$83 -> 0 | P101: =iferror(N101/'PT Reporte SDR'!N116-1,"")
C102: No tenía suficiente presupuesto | D102: =H102+K102+N102 -> 0 | E102: =D102/$D$83 -> 0 | F102: =iferror(D102/'PT Reporte SDR'!D117-1,"") | H102: =COUNTIFS(Data!$A:$A,">="&'Reporte SDR '!$C$5,Data!$A:$A,"<="&'Reporte SDR '!$D$5,Data!$BR:$BR,C102) -> 0 | I102: =H102/$D$83 -> 0 | J102: =iferror(H102/'PT Reporte SDR'!H117-1,"") | K102: =COUNTIFS(Data!$A:$A,">="&'Reporte SDR '!$C$5,Data!$A:$A,"<="&'Reporte SDR '!$D$5,Data!$BI:$BI,$H$7,Data!$DF:$DF,C102) -> 0 | L102: =K102/$D$83 -> 0 | M102: =iferror(K102/'PT Reporte SDR'!K117-1,"") | N102: =COUNTIFS(Data!$A:$A,">="&'Reporte SDR '!$C$5,Data!$A:$A,"<="&'Reporte SDR '!$D$5,Data!$BI:$BI,$H$7,Data!$DF:$DF,C102) -> 0 | O102: =N102/$D$83 -> 0 | P102: =iferror(N102/'PT Reporte SDR'!N117-1,"")
...

Sheet Copy of Reporte SDR 
C3: IAAPA | FUNNEL REPORT | SDR | REALTIME
C4: Day In | D4: Day Out
C5: 45992 | D5: 46022
C6: =EOMONTH(C5,-2)+1 -> 45962 | D6: =EDATE(D5, -1) -> 45991
C7: MÉTRICA | D7: TOTAL | E7: % | F7: Δ% vs PP | H7: Total | I7: % | J7: Δ% vs PP | K7: Manufacturers | L7: % | M7: Δ% vs PP | N7: Individuals | O7: % | P7: Δ% vs PP | S7: Agosto
C8: Total Leads SDR | D8: =H8 -> 0 | F8: =iferror(D8/'PT Reporte SDR'!D6-1,"") | H8: =COUNTIFS(Data!$A:$A,">="&'Copy of Reporte SDR '!$C$5,Data!$A:$A,"<="&'Copy of Reporte SDR '!$D$5) -> 0 | J8: =iferror(H8/'PT Reporte SDR'!H6-1,"") | K8: =COUNTIFS(Data!$A:$A,">="&'Copy of Reporte SDR '!$C$5,Data!$A:$A,"<="&'Copy of Reporte SDR '!$D$5,Data!$BI:$BI,K7) -> 0 | M8: =iferror(K8/'PT Reporte SDR'!K6-1,"") | N8: =COUNTIFS(Data!$A:$A,">="&'Copy of Reporte SDR '!$C$5,Data!$A:$A,"<="&'Copy of Reporte SDR '!$D$5,Data!$BI:$BI,N7) -> 0 | P8: =iferror(N8/'PT Reporte SDR'!N6-1,"") | S8: Pagados | T8: 4 | W8: Cerrados carry over
C9: Prueba | D9: =Sum(H9+K9+N9) -> 0 | E9: =iferror(D9/$D$8,"0%") -> 0% | F9: =iferror(D9/'PT Reporte SDR'!D65-1,"") | H9: =COUNTIFS(Data!$A:$A,">="&'Copy of Reporte SDR '!$C$5,Data!$A:$A,"<="&'Copy of Reporte SDR '!$D$5,Data!$X:$X,C9) -> 0 | I9: =iferror(H9/$D$49,0) -> 0 | J9: =iferror(H9/'PT Reporte SDR'!H65-1,"") | K9: =COUNTIFS(Data!$A:$A,">="&'Copy of Reporte SDR '!$C$5,Data!$A:$A,"<="&'Copy of Reporte SDR '!$D$5,Data!$BI:$BI,$H$7,Data!$CM:$CM,C9) -> 0 | L9: =iferror(K9/$D$49,0) -> 0 | M9: =iferror(K9/'PT Reporte SDR'!K65-1,"") | N9: =COUNTIFS(Data!$A:$A,">="&'Copy of Reporte SDR '!$C$5,Data!$A:$A,"<="&'Copy of Reporte SDR '!$D$5,Data!$BI:$BI,$H$7,Data!$CM:$CM,C9) -> 0 | O9: =iferror(N9/$D$49,0) -> 0 | P9: =iferror(N9/'PT Reporte SDR'!N65-1,"")
C10: Total Leads Incontactables por base de datos | D10: =H10 -> 0 | E10: =iferror(D10/$D$8,"0%") -> 0% | F10: =iferror(D10/'PT Reporte SDR'!D7-1,"") | H10: =H49 -> 0 | I10: =iferror(H10/$D$8,"0%") -> 0% | J10: =iferror(H10/'PT Reporte SDR'!H7-1,"") | K10: =K49 -> 0 | L10: =iferror(K10/$D$8,"0%") -> 0% | M10: =iferror(K10/'PT Reporte SDR'!K7-1,"") | N10: =N49 -> 0 | O10: =iferror(N10/$D$8,"0%") -> 0% | P10: =iferror(N10/'PT Reporte SDR'!N7-1,"")
C11: Total Leads Contactables | D11: =H11 -> 0 | E11: =iferror(D11/$D$8,"0%") -> 0% | F11: =iferror(D11/'PT Reporte SDR'!D8-1,"") | H11: =H8-H10-H9 -> 0 | I11: =iferror(H11/$D$8,"0%") -> 0% | J11: =iferror(H11/'PT Reporte SDR'!H8-1,"") | K11: =K8-K10 -> 0 | L11: =iferror(K11/$D$8,"0%") -> 0% | M11: =iferror(K11/'PT Reporte SDR'!K8-1,"") | N11: =N8-N10 -> 0 | O11: =iferror(N11/$D$8,"0%") -> 0% | P11: =iferror(N11/'PT Reporte SDR'!N8-1,"")
C12: Total Leads Contactados (con al menos 1 Toque) | D12: =H12 -> 0 | E12: =iferror(D12/D11,"0%") -> 0% | F12: =iferror(D12/'PT Reporte SDR'!D9-1,"") | H12: =COUNTIFS(Data!$A:$A,">="&'Copy of Reporte SDR '!$C$5,Data!$A:$A,"<="&'Copy of Reporte SDR '!$D$5,Data!$Y:$Y,"<>") -> 0 | I12: =iferror(H12/H11,"0%") -> 0% | J12: =iferror(H12/'PT Reporte SDR'!H9-1,"") | K12: =COUNTIFS(Data!$A:$A,">="&'Copy of Reporte SDR '!$C$5,Data!$A:$A,"<="&'Copy of Reporte SDR '!$D$5,Data!$BI:$BI,K7,Data!$AT:$AT,"<>")-K10 -> 0 | L12: =iferror(K12/K11,"0%") -> 0% | M12: =iferror(K12/'PT Reporte SDR'!K9-1,"") | N12: =COUNTIFS(Data!$A:$A,">="&'Copy of Reporte SDR '!$C$5,Data!$A:$A,"<="&'Copy of Reporte SDR '!$D$5,Data!$BI:$BI,N7,Data!$AT:$AT,"<>")-N10 -> 0 | O12: =iferror(N12/N11,"0%") -> 0% | P12: =iferror(N12/'PT Reporte SDR'!N9-1,"")
C13: Total Lead en Proceso de Contacto (aún sin respuesta) | D13: =H13 -> 0 | E13: =iferror(D13/$D$8,"0%") -> 0% | F13: =iferror(D13/'PT Reporte SDR'!D10-1,"") -> -1 | H13: =COUNTIFS(Data!$A:$A,">="&'Copy of Reporte SDR '!$C$5,Data!$A:$A,"<="&'Copy of Reporte SDR '!$D$5,Data!$W:$W,"Contactado sin Respuesta") -> 0 | I13: =iferror(H13/$D$8,"0%") -> 0% | J13: =iferror(H13/'PT Reporte SDR'!H10-1,"") -> -1 | K13: =COUNTIFS(Data!$A:$A,">="&'Copy of Reporte SDR '!$C$5,Data!$A:$A,"<="&'Copy of Reporte SDR '!$D$5,Data!$BI:$BI,K7,Data!$BK:$BK,"No respondio") -> 0 | L13: =iferror(K13/$D$8,"0%") -> 0% | M13: =iferror(K13/'PT Reporte SDR'!K10-1,"") | N13: =COUNTIFS(Data!$A:$A,">="&'Copy of Reporte SDR '!$C$5,Data!$A:$A,"<="&'Copy of Reporte SDR '!$D$5,Data!$BI:$BI,N7,Data!$BK:$BK,"No respondio") -> 0 | O13: =iferror(N13/$D$8,"0%") -> 0% | P13: =iferror(N13/'PT Reporte SDR'!N10-1,"")
C14: Total Leads Contactados sin Respuesta (6to Toque o más) | D14: =H14 -> 0 | E14: =iferror(IFERROR(D14/D12,0),"") -> 0 | F14: =iferror(D14/'PT Reporte SDR'!D11-1,"") | H14: =COUNTIFS(Data!$A:$A,">="&'Copy of Reporte SDR '!$C$5,Data!$A:$A,"<="&'Copy of Reporte SDR '!$D$5,Data!$AA:$AA,"<5") -> 0 | I14: =iferror(IFERROR(H14/H12,0),"") -> 0 | J14: =iferror(H14/'PT Reporte SDR'!H11-1,"") | K14: =COUNTIFS(Data!$A:$A,">="&'Copy of Reporte SDR '!$C$5,Data!$A:$A,"<="&'Copy of Reporte SDR '!$D$5,Data!$BI:$BI,K7,Data!$AT:$AT,">=6") -> 0 | L14: =iferror(IFERROR(K14/K12,0),"") -> 0 | M14: =iferror(K14/'PT Reporte SDR'!K11-1,"") | N14: =COUNTIFS(Data!$A:$A,">="&'Copy of Reporte SDR '!$C$5,Data!$A:$A,"<="&'Copy of Reporte SDR '!$D$5,Data!$BI:$BI,N7,Data!$AT:$AT,">=6") -> 0 | O14: =iferror(IFERROR(N14/N12,0),"") -> 0 | P14: =iferror(N14/'PT Reporte SDR'!N11-1,"")
C15: Total Leads Contactados con Respuesta | D15: =H15 -> 3 | E15: =iferror(D15/D11,"0%") -> 0% | F15: =iferror(D15/'PT Reporte SDR'!D12-1,"") | H15: =H55 -> 3 | I15: =iferror(H15/H11,"0%") -> 0% | J15: =iferror(H15/'PT Reporte SDR'!H12-1,"") | K15: =COUNTIFS(Data!$A:$A,">="&'Copy of Reporte SDR '!$C$5,Data!$A:$A,"<="&'Copy of Reporte SDR '!$D$5,Data!$BI:$BI,K7,Data!$BK:$BK,"Pase a ventas")+COUNTIFS(Data!$A:$A,">="&'Copy of Reporte SDR '!$C$5,Data!$A:$A,"<="&'Copy of Reporte SDR '!$D$5,Data!$BI:$BI,K7,Data!$BK:$BK,"Descartado")+COUNTIFS(Data!$A:$A,">="&'Copy of Reporte SDR '!$C$5,Data!$A:$A,"<="&'Copy of Reporte SDR '!$D$5,Data!$BI:$BI,K7,Data!$BK:$BK,"Pidio llamar mas tarde")+COUNTIFS(Data!$A:$A,">="&'Copy of Reporte SDR '!$C$5,Data!$A:$A,"<="&'Copy of Reporte SDR '!$D$5,Data!$BI:$BI,K7,Data!$BK:$BK,"Contesta y Cuelga")+COUNTIFS(Data!$A:$A,">="&'Copy of Reporte SDR '!$C$5,Data!$A:$A,"<="&'Copy of Reporte SDR '!$D$5,Data!$BI:$BI,K7,Data!$BK:$BK,"Llamar mañana")+COUNTIFS(Data!$A:$A,">="&'Copy of Reporte SDR '!$C$5,Data!$A:$A,"<="&'Copy of Reporte SDR '!$D$5,Data!$BI:$BI,K7,Data!$BK:$BK,"SEGUIMIENTO") -> 0 | L15: =iferror(K15/K11,"0%") -> 0% | M15: =iferror(K15/'PT Reporte SDR'!K12-1,"") | N15: =COUNTIFS(Data!$A:$A,">="&'Copy of Reporte SDR '!$C$5,Data!$A:$A,"<="&'Copy of Reporte SDR '!$D$5,Data!$BI:$BI,N7,Data!$BK:$BK,"Pase a ventas")+COUNTIFS(Data!$A:$A,">="&'Copy of Reporte SDR '!$C$5,Data!$A:$A,"<="&'Copy of Reporte SDR '!$D$5,Data!$BI:$BI,N7,Data!$BK:$BK,"Descartado")+COUNTIFS(Data!$A:$A,">="&'Copy of Reporte SDR '!$C$5,Data!$A:$A,"<="&'Copy of Reporte SDR '!$D$5,Data!$BI:$BI,N7,Data!$BK:$BK,"Pidio llamar mas tarde")+COUNTIFS(Data!$A:$A,">="&'Copy of Reporte SDR '!$C$5,Data!$A:$A,"<="&'Copy of Reporte SDR '!$D$5,Data!$BI:$BI,N7,Data!$BK:$BK,"Contesta y Cuelga")+COUNTIFS(Data!$A:$A,">="&'Copy of Reporte SDR '!$C$5,Data!$A:$A,"<="&'Copy of Reporte SDR '!$D$5,Data!$BI:$BI,N7,Data!$BK:$BK,"Llamar mañana")+COUNTIFS(Data!$A:$A,">="&'Copy of Reporte SDR '!$C$5,Data!$A:$A,"<="&'Copy of Reporte SDR '!$D$5,Data!$BI:$BI,N7,Data!$BK:$BK,"SEGUIMIENTO") -> 0 | O15: =iferror(N15/N11,"0%") -> 0% | P15: =iferror(N15/'PT Reporte SDR'!N12-1,"")
C16: Total Leads Con Dialogo Completo | D16: =H16 -> -2 | E16: =IFERROR(D16/$D$15,0) -> -0.66666667 | F16: =iferror(D16/'PT Reporte SDR'!D13-1,"") | H16: =COUNTIFS(Data!$A:$A,">="&'Copy of Reporte SDR '!$C$5,Data!$A:$A,"<="&'Copy of Reporte SDR '!$D$5,Data!$AB:$AB,"Diálogo Completo")-2 -> -2 | I16: =IFERROR(H16/$D$15,0) -> -0.66666667 | J16: =iferror(H16/'PT Reporte SDR'!H13-1,"") | K16: =COUNTIFS(Data!$A:$A,">="&'Copy of Reporte SDR '!$C$5,Data!$A:$A,"<="&'Copy of Reporte SDR '!$D$5,Data!$BI:$BI,K7,Data!$W:$W,"Diálogo Completo") -> 0 | L16: =IFERROR(K16/$D$15,0) -> 0 | M16: =iferror(K16/'PT Reporte SDR'!K13-1,"") | N16: =COUNTIFS(Data!$A:$A,">="&'Copy of Reporte SDR '!$C$5,Data!$A:$A,"<="&'Copy of Reporte SDR '!$D$5,Data!$BI:$BI,N7,Data!$W:$W,"Diálogo Completo") -> 0 | O16: =IFERROR(N16/$D$15,0) -> 0 | P16: =iferror(N16/'PT Reporte SDR'!N13-1,"")
C17: Total Leads Intermitentes | D17: =H17 -> 6 | E17: =IFERROR(D17/$D$15,0) -> 2 | F17: =iferror(D17/'PT Reporte SDR'!D14-1,"") -> 5 | H17: =COUNTIFS(Data!$A:$A,">="&'Copy of Reporte SDR '!$C$5,Data!$A:$A,"<="&'Copy of Reporte SDR '!$D$5,Data!$AB:$AB,"Intermitente")+6 -> 6 | I17: =IFERROR(H17/$D$15,0) -> 2 | J17: =iferror(H17/'PT Reporte SDR'!H14-1,"") -> 5 | K17: =COUNTIFS(Data!$A:$A,">="&'Copy of Reporte SDR '!$C$5,Data!$A:$A,"<="&'Copy of Reporte SDR '!$D$5,Data!$BI:$BI,K7,Data!$W:$W,"Intermitente") -> 0 | L17: =IFERROR(K17/$D$15,0) -> 0 | M17: =iferror(K17/'PT Reporte SDR'!K14-1,"") | N17: =COUNTIFS(Data!$A:$A,">="&'Copy of Reporte SDR '!$C$5,Data!$A:$A,"<="&'Copy of Reporte SDR '!$D$5,Data!$BI:$BI,N7,Data!$W:$W,"Intermitente") -> 0 | O17: =IFERROR(N17/$D$15,0) -> 0 | P17: =iferror(N17/'PT Reporte SDR'!N14-1,"")
C18: Leads que entendieron comunicación | D18: =H18 -> 4 | E18: =IFERROR(D18/$D$15,0) -> 1.3333333 | F18: =iferror(D18/'PT Reporte SDR'!D15-1,"") | H18: =COUNTIFS(Data!$A:$A,">="&'Copy of Reporte SDR '!$C$5,Data!$A:$A,"<="&'Copy of Reporte SDR '!$D$5,Data!$AF:$AF,"Si")+4 -> 4 | I18: =IFERROR(H18/$D$15,0) -> 1.3333333 | J18: =iferror(H18/'PT Reporte SDR'!H15-1,"") | K18: =COUNTIFS(Data!$A:$A,">="&'Copy of Reporte SDR '!$C$5,Data!$A:$A,"<="&'Copy of Reporte SDR '!$D$5,Data!$BI:$BI,K7,Data!$AJ:$AJ,"Si") -> 0 | L18: =IFERROR(K18/$D$15,0) -> 0 | M18: =iferror(K18/'PT Reporte SDR'!K15-1,"") | N18: =COUNTIFS(Data!$A:$A,">="&'Copy of Reporte SDR '!$C$5,Data!$A:$A,"<="&'Copy of Reporte SDR '!$D$5,Data!$BI:$BI,N7,Data!$AJ:$AJ,"Si") -> 0 | O18: =IFERROR(N18/$D$15,0) -> 0 | P18: =iferror(N18/'PT Reporte SDR'!N15-1,"")
C19: Leads que no entendieron comunicación | D19: =H19 -> 0 | E19: =IFERROR(D19/$D$15,0) -> 0 | F19: =iferror(D19/'PT Reporte SDR'!D16-1,"") | H19: =COUNTIFS(Data!$A:$A,">="&'Copy of Reporte SDR '!$C$5,Data!$A:$A,"<="&'Copy of Reporte SDR '!$D$5,Data!$AF:$AF,"No") -> 0 | I19: =IFERROR(H19/$D$15,0) -> 0 | J19: =iferror(H19/'PT Reporte SDR'!H16-1,"") | K19: =COUNTIFS(Data!$A:$A,">="&'Copy of Reporte SDR '!$C$5,Data!$A:$A,"<="&'Copy of Reporte SDR '!$D$5,Data!$BI:$BI,K7,Data!$AJ:$AJ,"No") -> 0 | L19: =IFERROR(K19/$D$15,0) -> 0 | M19: =iferror(K19/'PT Reporte SDR'!K16-1,"") | N19: =COUNTIFS(Data!$A:$A,">="&'Copy of Reporte SDR '!$C$5,Data!$A:$A,"<="&'Copy of Reporte SDR '!$D$5,Data!$BI:$BI,N7,Data!$AJ:$AJ,"No") -> 0 | O19: =IFERROR(N19/$D$15,0) -> 0 | P19: =iferror(N19/'PT Reporte SDR'!N16-1,"")
C20: Leads que mostraron interés | D20: =H20 -> 0 | E20: =IFERROR(D20/$D$15,0) -> 0 | F20: =iferror(D20/'PT Reporte SDR'!D17-1,"") -> -1 | H20: =COUNTIFS(Data!$A:$A,">="&'Copy of Reporte SDR '!$C$5,Data!$A:$A,"<="&'Copy of Reporte SDR '!$D$5,Data!$AG:$AG,"Si") -> 0 | I20: =IFERROR(H20/$D$15,0) -> 0 | J20: =iferror(H20/'PT Reporte SDR'!H17-1,"") -> -1 | K20: =COUNTIFS(Data!$A:$A,">="&'Copy of Reporte SDR '!$C$5,Data!$A:$A,"<="&'Copy of Reporte SDR '!$D$5,Data!$BI:$BI,K7,Data!$BK:$BK,"Pase a ventas") -> 0 | L20: =IFERROR(K20/$D$15,0) -> 0 | M20: =iferror(K20/'PT Reporte SDR'!K17-1,"") | N20: =COUNTIFS(Data!$A:$A,">="&'Copy of Reporte SDR '!$C$5,Data!$A:$A,"<="&'Copy of Reporte SDR '!$D$5,Data!$BI:$BI,N7,Data!$BK:$BK,"Pase a ventas") -> 0 | O20: =IFERROR(N20/$D$15,0) -> 0 | P20: =iferror(N20/'PT Reporte SDR'!N17-1,"")
C21: Total Leads Descartados | D21: =H21 -> 3 | E21: =iferror(D21/D8,"0%") -> 0% | F21: =iferror(D21/'PT Reporte SDR'!D18-1,"") | H21: =H22+H23 -> 3 | I21: =iferror(H21/H8,"0%") -> 0% | J21: =iferror(H21/'PT Reporte SDR'!H18-1,"") | K21: =K22+K23 -> 0 | L21: =iferror(K21/K8,"0%") -> 0% | M21: =iferror(K21/'PT Reporte SDR'!K18-1,"") | N21: =N22+N23 -> 0 | O21: =iferror(N21/N8,"0%") -> 0% | P21: =iferror(N21/'PT Reporte SDR'!N18-1,"")
C22: Leads que no mostraron interés | D22: =H22 -> 1 | E22: =IFERROR(D22/$D$15,0) -> 0.33333333 | F22: =iferror(D22/'PT Reporte SDR'!D19-1,"") | H22: =COUNTIFS(Data!$A:$A,">="&'Copy of Reporte SDR '!$C$5,Data!$A:$A,"<="&'Copy of Reporte SDR '!$D$5,Data!$AG:$AG,"No")+1 -> 1 | I22: =IFERROR(H22/$D$15,0) -> 0.33333333 | J22: =iferror(H22/'PT Reporte SDR'!H19-1,"") | K22: =COUNTIFS(Data!$A:$A,">="&'Copy of Reporte SDR '!$C$5,Data!$A:$A,"<="&'Copy of Reporte SDR '!$D$5,Data!$BI:$BI,K7,Data!$AJ:$AJ,"No") -> 0 | L22: =IFERROR(K22/$D$15,0) -> 0 | M22: =iferror(K22/'PT Reporte SDR'!K19-1,"") | N22: =COUNTIFS(Data!$A:$A,">="&'Copy of Reporte SDR '!$C$5,Data!$A:$A,"<="&'Copy of Reporte SDR '!$D$5,Data!$BI:$BI,N7,Data!$AJ:$AJ,"No") -> 0 | O22: =IFERROR(N22/$D$15,0) -> 0 | P22: =iferror(N22/'PT Reporte SDR'!N19-1,"")
C23: Otras razones | D23: =H23 -> 2 | E23: =IFERROR(D23/$D$15,0) -> 0.66666667 | F23: =iferror(D23/'PT Reporte SDR'!D20-1,"") | H23: =H82 -> 2 | I23: =IFERROR(H23/$D$15,0) -> 0.66666667 | J23: =iferror(H23/'PT Reporte SDR'!H20-1,"") | K23: =K82 -> 0 | L23: =IFERROR(K23/$D$15,0) -> 0 | M23: =iferror(K23/'PT Reporte SDR'!K20-1,"") | N23: =N82 -> 0 | O23: =IFERROR(N23/$D$15,0) -> 0 | P23: =iferror(N23/'PT Reporte SDR'!N20-1,"")
C24: Total Leads en seguimiento para venta | D24: =H24 -> 0 | E24: =IFERROR(D24/$D$15,0) -> 0 | F24: =iferror(D24/'PT Reporte SDR'!D21-1,"") | H24: =COUNTIFS(Data!$A:$A,">="&'Copy of Reporte SDR '!$C$5,Data!$A:$A,"<="&'Copy of Reporte SDR '!$D$5,Data!$W:$W,"En Seguimiento") -> 0 | I24: =IFERROR(H24/$D$15,0) -> 0 | J24: =iferror(H24/'PT Reporte SDR'!H21-1,"") | K24: =COUNTIFS(Data!$A:$A,">="&'Copy of Reporte SDR '!$C$5,Data!$A:$A,"<="&'Copy of Reporte SDR '!$D$5,Data!$BI:$BI,K7,Data!$BK:$BK,"SEGUIMIENTO") -> 0 | L24: =IFERROR(K24/$D$15,0) -> 0 | M24: =iferror(K24/'PT Reporte SDR'!K21-1,"") | N24: =COUNTIFS(Data!$A:$A,">="&'Copy of Reporte SDR '!$C$5,Data!$A:$A,"<="&'Copy of Reporte SDR '!$D$5,Data!$BI:$BI,N7,Data!$BK:$BK,"SEGUIMIENTO") -> 0 | O24: =IFERROR(N24/$D$15,0) -> 0 | P24: =iferror(N24/'PT Reporte SDR'!N21-1,"")
C25: Monto aproximado de Inversión en seguimiento a venta | D25: =H25 -> #N/A | H25: =SUMIFS(Data!$AP:$AP,Data!$A:$A,">="&'Copy of Reporte SDR '!$C$5,Data!$A:$A,"<="&'Copy of Reporte SDR '!$D$5,Data!$W:$W,"En Seguimiento")+3130 -> #N/A
C26: Total Leads Asignados a Ventas | D26: =H26 -> 0 | E26: =iferror(D26/D20,"0%") -> 0% | F26: =iferror(D26/'PT Reporte SDR'!D22-1,"") | H26: =COUNTIFS(Data!$A:$A,">="&'Copy of Reporte SDR '!$C$5,Data!$A:$A,"<="&'Copy of Reporte SDR '!$D$5,Data!$W:$W,"Paso a ventas") -> 0 | I26: =iferror(H26/H20,"0%") -> 0% | J26: =iferror(H26/'PT Reporte SDR'!H22-1,"") | K26: =COUNTIFS(Data!$A:$A,">="&'Copy of Reporte SDR '!$C$5,Data!$A:$A,"<="&'Copy of Reporte SDR '!$D$5,Data!$BI:$BI,K7,Data!$BK:$BK,"Pase a ventas") -> 0 | L26: =iferror(K26/K20,"0%") -> 0% | M26: =iferror(K26/'PT Reporte SDR'!K22-1,"") | N26: =COUNTIFS(Data!$A:$A,">="&'Copy of Reporte SDR '!$C$5,Data!$A:$A,"<="&'Copy of Reporte SDR '!$D$5,Data!$BI:$BI,N7,Data!$BK:$BK,"Pase a ventas") -> 0 | O26: =iferror(N26/N20,"0%") -> 0% | P26: =iferror(N26/'PT Reporte SDR'!N22-1,"")
C27: Monto de inversión asignada a ventas | D27: =H27 -> #N/A | E27: $ | F27: =iferror(D27/'PT Reporte SDR Brazil'!D28-1,"") | H27: =SUMIFS(Data!$AP:$AP,Data!$A:$A,">="&'Report LATAM'!$C$5,Data!$A:$A,"<="&'Report LATAM'!$D$5,Data!$W:$W,"Paso a Ventas") -> #N/A | J27: =iferror(H27/'PT Reporte SDR Brazil'!H28-1,"")
C28: Leads Asignados a Ventas Periodo Actual | D28: =H28 -> 0 | E28: =IFERROR(D28/D20,0) -> 0 | F28: =iferror(D28/'PT Reporte SDR Brazil'!D23-1,"") -> -1 | H28: =COUNTIFS(Data!$A:$A,">="&'Copy of Reporte SDR '!$C$5,Data!$A:$A,"<="&'Copy of Reporte SDR '!$D$5,Data!$W:$W,"Paso a ventas") -> 0 | I28: =IFERROR(H28/H20,0) -> 0 | J28: =iferror(H28/'PT Reporte SDR Brazil'!H23-1,"") -> -1
C29: Monto de Inversión asignada a Ventas Periodo Actual | D29: =H29 -> #N/A | E29: =IFERROR(D29/D26,0) -> 0 | F29: =iferror(D29/'PT Reporte SDR Brazil'!D26-1,"") | H29: =SUMIFS(Data!$AP:$AP,Data!$A:$A,">="&'Report LATAM'!$C$5,Data!$A:$A,"<="&'Report LATAM'!$D$5,Data!$W:$W,"Paso a Ventas") -> #N/A | I29: =IFERROR(H29/H26,0) -> 0 | J29: =iferror(H29/'PT Reporte SDR Brazil'!H26-1,"")
C30: Leads Asignados a Ventas Carry-Over | D30: =H30 -> 3 | E30: =IFERROR(D30/#REF!,0) -> 0 | F30: =iferror(D30/'PT Reporte SDR Brazil'!D24-1,"") | H30: =COUNTIFS(Data!$AR:$AR,">="&'Copy of Reporte SDR '!$C$5,Data!$AR:$AR,"<="&'Copy of Reporte SDR '!$D$5,Data!$A:$A,">="&'Copy of Reporte SDR '!$C$6,Data!$A:$A,"<="&'Copy of Reporte SDR '!$D$6,Data!$W:$W,"Paso a ventas")+3 -> 3 | I30: =IFERROR(H30/#REF!,0) -> 0 | J30: =iferror(H30/'PT Reporte SDR Brazil'!H24-1,"")
C31: Monto de Inversión asignada a Ventas Carry-Over (Leads Mes anterior) | D31: =H31 -> #N/A | E31: =iferror(D31/$D$77,0) -> 0 | F31: =iferror(D31/'PT Reporte SDR Brazil'!D27-1,"") | H31: =SUMIFS(Data!$BQ:$BQ,Data!$AR:$AR,">="&'Copy of Reporte SDR '!$C$5,Data!$AR:$AR,"<="&'Copy of Reporte SDR '!$D$5,Data!$A:$A,">="&'Copy of Reporte SDR '!$C$6,Data!$A:$A,"<="&'Copy of Reporte SDR '!$D$6,Data!$W:$W,"Paso a ventas")+1130 -> #N/A | I31: =iferror(H31/$D$77,0) -> 0 | J31: =iferror(H31/'PT Reporte SDR Brazil'!H27-1,"")
C32: Deals con Link de Pago activo | D32: =H32 -> 3 | H32: =COUNTIFS(Data!$A:$A,">="&'Copy of Reporte SDR '!$C$5,Data!$A:$A,"<="&'Copy of Reporte SDR '!$D$5,Data!$BZ:$BZ,"Si",Data!$BL:$BL,"<>Vendido")+3 -> 3
C33: Monto de Inversión con Link de Pago | D33: =H33 -> #N/A | H33: =SUMIFS(Data!$BQ:$BQ,Data!$A:$A,">="&'Copy of Reporte SDR '!$C$5,Data!$A:$A,"<="&'Copy of Reporte SDR '!$D$5,Data!$BZ:$BZ,"Si",Data!$BL:$BL,"<>Vendido")+SUMIFS(Data!$BP:$BP,Data!$A:$A,">="&'Copy of Reporte SDR '!$C$5,Data!$A:$A,"<="&'Copy of Reporte SDR '!$D$5,Data!$BZ:$BZ,"Si",Data!$BL:$BL,"<>Vendido")+965 -> #N/A
C34: Cierres de Deals Nuevos Pagados | D34: =H34 -> 0 | F34: =iferror(D34/'PT Reporte SDR Brazil'!D35-1,"") | H34: =COUNTIFS(Data!$A:$A,">="&'Copy of Reporte SDR '!$C$5,Data!$A:$A,"<="&'Copy of Reporte SDR '!$D$5,Data!$BL:$BL,"Vendido",Data!$BY:$BY,">="&'Copy of Reporte SDR '!$C$5,Data!$BY:$BY,"<="&'Copy of Reporte SDR '!$D$5) -> 0 | J34: =iferror(H34/'PT Reporte SDR Brazil'!H35-1,"")
C35: Monto de nuevos cierres | D35: =H35 -> #N/A | F35: =iferror(D35/'PT Reporte SDR Brazil'!D36-1,"") | H35: =SUMIFS(Data!$BQ:$BQ,Data!$A:$A,">="&'Copy of Reporte SDR '!$C$5,Data!$A:$A,"<="&'Copy of Reporte SDR '!$D$5,Data!$BL:$BL,"Vendido",Data!$BY:$BY,">="&'Copy of Reporte SDR '!$C$5,Data!$BY:$BY,"<="&'Copy of Reporte SDR '!$D$5)+SUMIFS(Data!$BR:$BR,Data!$A:$A,">="&'Copy of Reporte SDR '!$C$5,Data!$A:$A,"<="&'Copy of Reporte SDR '!$D$5,Data!$BL:$BL,"Vendido",Data!$BY:$BY,">="&'Copy of Reporte SDR '!$C$5,Data!$BY:$BY,"<="&'Copy of Reporte SDR '!$D$5) -> #N/A | J35: =iferror(H35/'PT Reporte SDR Brazil'!H36-1,"")
C36: Cierres de Deals Pagados por Rejoin (aquellos que fueron miembros y se vuelven a unir a IAAPA) | D36: =H36 -> 0 | H36: =COUNTIFS(Data!$A:$A,">="&'Copy of Reporte SDR '!$C$5,Data!$A:$A,"<="&'Copy of Reporte SDR '!$D$5,Data!$BL:$BL,"Vendido",Data!$CA:$CA,"Si") -> 0
C37: Monto de cierres por renovación | D37: =H37 -> #N/A | H37: =SUMIFS(Data!$BQ:$BQ,Data!$A:$A,">="&'Copy of Reporte SDR '!$C$5,Data!$A:$A,"<="&'Copy of Reporte SDR '!$D$5,Data!$BL:$BL,"Vendido",Data!$CA:$CA,"Si") -> #N/A
C38: Cierres de Deals Pagados Total | D38: =H38 -> 16 | H38: =COUNTIFS(Data!$A:$A,">="&'Copy of Reporte SDR '!$C$5,Data!$A:$A,"<="&'Copy of Reporte SDR '!$D$5,Data!$BL:$BL,"Vendido")+16 -> 16
C39: Monto de cierres Total | D39: =H39 -> #N/A | H39: =SUMIFS(Data!$BQ:$BQ,Data!$A:$A,">="&'Copy of Reporte SDR '!$C$5,Data!$A:$A,"<="&'Copy of Reporte SDR '!$D$5,Data!$BL:$BL,"Vendido")+SUMIFS(Data!$BR:$BR,Data!$A:$A,">="&'Copy of Reporte SDR '!$C$5,Data!$A:$A,"<="&'Copy of Reporte SDR '!$D$5,Data!$BL:$BL,"Vendido")+5335 -> #N/A
C40: Monto asignado a Ventas Total todos los tiempos | D40: =H40 -> #N/A | E40: =IFERROR(D40/D29,0) -> 0 | F40: =iferror(D40/'PT Reporte SDR Brazil'!D29-1,"") | H40: =SUMIFS(Data!$BQ:$BQ,Data!$A:$A,">="&'Copy of Reporte SDR '!$H$4,Data!$A:$A,"<="&'Copy of Reporte SDR '!$I$4,Data!$W:$W,"Paso a ventas")+SUMIFS(Data!$BR:$BR,Data!$A:$A,">="&'Copy of Reporte SDR '!$H$4,Data!$A:$A,"<="&'Copy of Reporte SDR '!$I$4,Data!$W:$W,"Paso a ventas")+14325 -> #N/A | I40: =IFERROR(H40/H29,0) -> 0 | J40: =iferror(H40/'PT Reporte SDR Brazil'!H29-1,"")
C41: Monto asignado a Ventas Historico aún en seguimiento | D41: =H41 -> #N/A | F41: =iferror(D41/'PT Reporte SDR Brazil'!D30-1,"") | H41: =SUMIFS(Data!$BQ:$BQ,Data!$A:$A,">="&'Copy of Reporte SDR '!$H$5,Data!$A:$A,"<="&'Copy of Reporte SDR '!$I$5,Data!$W:$W,"Paso a ventas")+SUMIFS(Data!$BR:$BR,Data!$A:$A,">="&'Copy of Reporte SDR '!$H$5,Data!$A:$A,"<="&'Copy of Reporte SDR '!$I$5,Data!$W:$W,"Paso a ventas")+13885 -> #N/A | J41: =iferror(H41/'PT Reporte SDR Brazil'!H30-1,"")
C42: Monto asignado a ventas Perdido | D42: =H42 -> #N/A | E42: =IFERROR(D42/D29,0) -> 0 | F42: =iferror(D42/'PT Reporte SDR Brazil'!D32-1,"") | H42: =SUMIFS(Data!$BQ:$BQ,Data!$A:$A,">="&'Copy of Reporte SDR '!$H$5,Data!$A:$A,"<="&'Copy of Reporte SDR '!$I$5,Data!$W:$W,"Paso a ventas",Data!$BL:$BL,"Perdido")+SUMIFS(Data!$BR:$BR,Data!$A:$A,">="&'Copy of Reporte SDR '!$H$5,Data!$A:$A,"<="&'Copy of Reporte SDR '!$I$5,Data!$W:$W,"Paso a ventas",Data!$BL:$BL,"Perdido") -> #N/A | I42: =IFERROR(H42/H29,0) -> 0 | J42: =iferror(H42/'PT Reporte SDR Brazil'!H32-1,"")
C43: Monto asignado a ventas Promedio por Prospecto | D43: =H43 -> #N/A | E43: =IFERROR(D43/D29,0) -> 0 | F43: =iferror(D43/'PT Reporte SDR Brazil'!D33-1,"") | H43: =ABS(H29/H28) -> #N/A | I43: =IFERROR(H43/H29,0) -> 0 | J43: =iferror(H43/'PT Reporte SDR Brazil'!H33-1,"")
F44: =iferror(D44/'PT Reporte SDR'!D60-1,"") | J44: =iferror(H44/'PT Reporte SDR'!H60-1,"") | M44: =iferror(K44/'PT Reporte SDR'!K60-1,"") | P44: =iferror(N44/'PT Reporte SDR'!N60-1,"")
C45: Total Leads Incontactables | D45: Total | E45: % | F45: =iferror(D45/'PT Reporte SDR'!D61-1,"") | I45: % | J45: =iferror(H45/'PT Reporte SDR'!H61-1,"") | L45: % | M45: =iferror(K45/'PT Reporte SDR'!K61-1,"") | O45: % | P45: =iferror(N45/'PT Reporte SDR'!N61-1,"")
A46: {=UNIQUE(Data!BJ:BJ)} -> #REF! | C46: Duplicado | D46: =Sum(H46+K46+N46) -> 0 | E46: =iferror(D46/$D$49,0) -> 0 | F46: =iferror(D46/'PT Reporte SDR'!D62-1,"") | H46: =COUNTIFS(Data!$A:$A,">="&'Copy of Reporte SDR '!$C$5,Data!$A:$A,"<="&'Copy of Reporte SDR '!$D$5,Data!$X:$X,C46) -> 0 | I46: =iferror(H46/$D$49,0) -> 0 | J46: =iferror(H46/'PT Reporte SDR'!H62-1,"") | K46: =COUNTIFS(Data!$A:$A,">="&'Copy of Reporte SDR '!$C$5,Data!$A:$A,"<="&'Copy of Reporte SDR '!$D$5,Data!$BI:$BI,$H$7,Data!$CM:$CM,C46) -> 0 | L46: =iferror(K46/$D$49,0) -> 0 | M46: =iferror(K46/'PT Reporte SDR'!K62-1,"") | N46: =COUNTIFS(Data!$A:$A,">="&'Copy of Reporte SDR '!$C$5,Data!$A:$A,"<="&'Copy of Reporte SDR '!$D$5,Data!$BI:$BI,$H$7,Data!$CM:$CM,C46) -> 0 | O46: =iferror(N46/$D$49,0) -> 0 | P46: =iferror(N46/'PT Reporte SDR'!N62-1,"")
C47: Equivocado | D47: =Sum(H47+K47+N47) -> 0 | E47: =iferror(D47/$D$49,0) -> 0 | F47: =iferror(D47/'PT Reporte SDR'!D63-1,"") | H47: =COUNTIFS(Data!$A:$A,">="&'Copy of Reporte SDR '!$C$5,Data!$A:$A,"<="&'Copy of Reporte SDR '!$D$5,Data!$X:$X,C47) -> 0 | I47: =iferror(H47/$D$49,0) -> 0 | J47: =iferror(H47/'PT Reporte SDR'!H63-1,"") | K47: =COUNTIFS(Data!$A:$A,">="&'Copy of Reporte SDR '!$C$5,Data!$A:$A,"<="&'Copy of Reporte SDR '!$D$5,Data!$BI:$BI,$H$7,Data!$CM:$CM,C47) -> 0 | L47: =iferror(K47/$D$49,0) -> 0 | M47: =iferror(K47/'PT Reporte SDR'!K63-1,"") | N47: =COUNTIFS(Data!$A:$A,">="&'Copy of Reporte SDR '!$C$5,Data!$A:$A,"<="&'Copy of Reporte SDR '!$D$5,Data!$BI:$BI,$H$7,Data!$CM:$CM,C47) -> 0 | O47: =iferror(N47/$D$49,0) -> 0 | P47: =iferror(N47/'PT Reporte SDR'!N63-1,"")
C48: SPAM | D48: =Sum(H48+K48+N48) -> 0 | E48: =iferror(D48/$D$49,0) -> 0 | F48: =iferror(D48/'PT Reporte SDR'!D64-1,"") | H48: =COUNTIFS(Data!$A:$A,">="&'Copy of Reporte SDR '!$C$5,Data!$A:$A,"<="&'Copy of Reporte SDR '!$D$5,Data!$X:$X,C48) -> 0 | I48: =iferror(H48/$D$49,0) -> 0 | J48: =iferror(H48/'PT Reporte SDR'!H64-1,"") | K48: =COUNTIFS(Data!$A:$A,">="&'Copy of Reporte SDR '!$C$5,Data!$A:$A,"<="&'Copy of Reporte SDR '!$D$5,Data!$BI:$BI,$H$7,Data!$CM:$CM,C48) -> 0 | L48: =iferror(K48/$D$49,0) -> 0 | M48: =iferror(K48/'PT Reporte SDR'!K64-1,"") | N48: =COUNTIFS(Data!$A:$A,">="&'Copy of Reporte SDR '!$C$5,Data!$A:$A,"<="&'Copy of Reporte SDR '!$D$5,Data!$BI:$BI,$H$7,Data!$CM:$CM,C48) -> 0 | O48: =iferror(N48/$D$49,0) -> 0 | P48: =iferror(N48/'PT Reporte SDR'!N64-1,"")
C49: Total | D49: =sum(D46:D48) -> 0 | E49: =iferror(D49/#REF!,0) -> 0 | F49: =iferror(D49/'PT Reporte SDR'!D66-1,"") | H49: =SUM(H46:H48) -> 0 | I49: =iferror(H49/$D$49,0) -> 0 | J49: =iferror(H49/'PT Reporte SDR'!H66-1,"") | K49: =sum(K46:K48) -> 0 | L49: =iferror(K49/$D$49,0) -> 0 | M49: =iferror(K49/'PT Reporte SDR'!K66-1,"") | N49: =sum(N46:N48) -> 0 | O49: =iferror(N49/$D$49,0) -> 0 | P49: =iferror(N49/'PT Reporte SDR'!N66-1,"")
F50: =iferror(D50/'PT Reporte SDR'!D67-1,"") | J50: =iferror(H50/'PT Reporte SDR'!H67-1,"") | M50: =iferror(K50/'PT Reporte SDR'!K67-1,"") | P50: =iferror(N50/'PT Reporte SDR'!N67-1,"")
F51: =iferror(D51/'PT Reporte SDR'!D68-1,"") | J51: =iferror(H51/'PT Reporte SDR'!H68-1,"") | M51: =iferror(K51/'PT Reporte SDR'!K68-1,"") | P51: =iferror(N51/'PT Reporte SDR'!N68-1,"")
C52: Cross Selling | D52: =SUM(D53) -> 0 | E52: % | F52: =iferror(D52/'PT Reporte SDR'!D69-1,"") | I52: % | J52: =iferror(H52/'PT Reporte SDR'!H69-1,"") | L52: % | M52: =iferror(K52/'PT Reporte SDR'!K69-1,"") | O52: % | P52: =iferror(N52/'PT Reporte SDR'!N69-1,"")
C53: Cross Selling | E53: =iferror(D53/$D$52,0) -> 0 | F53: =iferror(D53/'PT Reporte SDR'!D70-1,"") | I53: =iferror(H53/$D$52,0) -> 0 | J53: =iferror(H53/'PT Reporte SDR'!H70-1,"") | L53: =iferror(K53/$D$52,0) -> 0 | M53: =iferror(K53/'PT Reporte SDR'!K70-1,"") | O53: =iferror(N53/$D$52,0) -> 0 | P53: =iferror(N53/'PT Reporte SDR'!N70-1,"")
F54: =iferror(D54/'PT Reporte SDR'!D71-1,"") | J54: =iferror(H54/'PT Reporte SDR'!H71-1,"") | M54: =iferror(K54/'PT Reporte SDR'!K71-1,"") | P54: =iferror(N54/'PT Reporte SDR'!N71-1,"")
C55: Total Leads Contactados con Respuesta | D55: =SUM(D56:D65) -> 3 | E55: % | F55: =iferror(D55/'PT Reporte SDR'!D72-1,"") | H55: =SUM(H56:H65) -> 3 | I55: % | J55: =iferror(H55/'PT Reporte SDR'!H72-1,"") | K55: =SUM(K56:K65) -> 0 | L55: % | M55: =iferror(K55/'PT Reporte SDR'!K72-1,"") | N55: =SUM(N56:N65) -> 0 | O55: % | P55: =iferror(N55/'PT Reporte SDR'!N72-1,"")
C56: Contestó Teléfono 1 | D56: =sum(H56) -> 0 | E56: =IFERROR(D56/$D$55,0) -> 0 | F56: =iferror(D56/'PT Reporte SDR'!D73-1,"") | H56: =COUNTIFS(Data!$A:$A,">="&'Copy of Reporte SDR '!$C$5,Data!$A:$A,"<="&'Copy of Reporte SDR '!$D$5,Data!$Y:$Y,C56) -> 0 | I56: =IFERROR(H56/$D$55,0) -> 0 | J56: =iferror(H56/'PT Reporte SDR'!H73-1,"") | K56: =COUNTIFS(Data!$A:$A,">="&'Copy of Reporte SDR '!$C$5,Data!$A:$A,"<="&'Copy of Reporte SDR '!$D$5,Data!$E:$E,D56,Data!$BG:$BG,$H$7) -> 0 | L56: =IFERROR(K56/$D$55,0) -> 0 | M56: =iferror(K56/'PT Reporte SDR'!K73-1,"") | N56: =COUNTIFS(Data!$A:$A,">="&'Copy of Reporte SDR '!$C$5,Data!$A:$A,"<="&'Copy of Reporte SDR '!$D$5,Data!$E:$E,E56,Data!$BG:$BG,$H$7) -> 0 | O56: =IFERROR(N56/$D$55,0) -> 0 | P56: =iferror(N56/'PT Reporte SDR'!N73-1,"")
C57: Contestó Teléfono 2 | D57: =sum(H57) -> 0 | E57: =IFERROR(D57/$D$55,0) -> 0 | F57: =iferror(D57/'PT Reporte SDR'!D74-1,"") | H57: =COUNTIFS(Data!$A:$A,">="&'Copy of Reporte SDR '!$C$5,Data!$A:$A,"<="&'Copy of Reporte SDR '!$D$5,Data!$Y:$Y,C57) -> 0 | I57: =IFERROR(H57/$D$55,0) -> 0 | J57: =iferror(H57/'PT Reporte SDR'!H74-1,"") | K57: =COUNTIFS(Data!$A:$A,">="&'Copy of Reporte SDR '!$C$5,Data!$A:$A,"<="&'Copy of Reporte SDR '!$D$5,Data!$E:$E,D57,Data!$BG:$BG,$H$7) -> 0 | L57: =IFERROR(K57/$D$55,0) -> 0 | M57: =iferror(K57/'PT Reporte SDR'!K74-1,"") | N57: =COUNTIFS(Data!$A:$A,">="&'Copy of Reporte SDR '!$C$5,Data!$A:$A,"<="&'Copy of Reporte SDR '!$D$5,Data!$E:$E,E57,Data!$BG:$BG,$H$7) -> 0 | O57: =IFERROR(N57/$D$55,0) -> 0 | P57: =iferror(N57/'PT Reporte SDR'!N74-1,"")
C58: Contestó Teléfono 3 | D58: =sum(H58) -> 0 | E58: =IFERROR(D58/$D$55,0) -> 0 | F58: =iferror(D58/'PT Reporte SDR'!D75-1,"") | H58: =COUNTIFS(Data!$A:$A,">="&'Copy of Reporte SDR '!$C$5,Data!$A:$A,"<="&'Copy of Reporte SDR '!$D$5,Data!$Y:$Y,C58) -> 0 | I58: =IFERROR(H58/$D$55,0) -> 0 | J58: =iferror(H58/'PT Reporte SDR'!H75-1,"") | K58: =COUNTIFS(Data!$A:$A,">="&'Copy of Reporte SDR '!$C$5,Data!$A:$A,"<="&'Copy of Reporte SDR '!$D$5,Data!$E:$E,D58,Data!$BG:$BG,$H$7) -> 0 | L58: =IFERROR(K58/$D$55,0) -> 0 | M58: =iferror(K58/'PT Reporte SDR'!K75-1,"") | N58: =COUNTIFS(Data!$A:$A,">="&'Copy of Reporte SDR '!$C$5,Data!$A:$A,"<="&'Copy of Reporte SDR '!$D$5,Data!$E:$E,E58,Data!$BG:$BG,$H$7) -> 0 | O58: =IFERROR(N58/$D$55,0) -> 0 | P58: =iferror(N58/'PT Reporte SDR'!N75-1,"")
C59: Contestó Whatsapp 1 | D59: =sum(H59) -> 0 | E59: =IFERROR(D59/$D$55,0) -> 0 | F59: =iferror(D59/'PT Reporte SDR'!D76-1,"") | H59: =COUNTIFS(Data!$A:$A,">="&'Copy of Reporte SDR '!$C$5,Data!$A:$A,"<="&'Copy of Reporte SDR '!$D$5,Data!$Y:$Y,C59) -> 0 | I59: =IFERROR(H59/$D$55,0) -> 0 | J59: =iferror(H59/'PT Reporte SDR'!H76-1,"") | K59: =COUNTIFS(Data!$A:$A,">="&'Copy of Reporte SDR '!$C$5,Data!$A:$A,"<="&'Copy of Reporte SDR '!$D$5,Data!$E:$E,D59,Data!$BG:$BG,$H$7) -> 0 | L59: =IFERROR(K59/$D$55,0) -> 0 | M59: =iferror(K59/'PT Reporte SDR'!K76-1,"") | N59: =COUNTIFS(Data!$A:$A,">="&'Copy of Reporte SDR '!$C$5,Data!$A:$A,"<="&'Copy of Reporte SDR '!$D$5,Data!$E:$E,E59,Data!$BG:$BG,$H$7) -> 0 | O59: =IFERROR(N59/$D$55,0) -> 0 | P59: =iferror(N59/'PT Reporte SDR'!N76-1,"")
C60: Contestó Whatsapp 2 | D60: =sum(H60) -> 3 | E60: =IFERROR(D60/$D$55,0) -> 1 | F60: =iferror(D60/'PT Reporte SDR'!D77-1,"") | H60: 3 | I60: =IFERROR(H60/$D$55,0) -> 1 | J60: =iferror(H60/'PT Reporte SDR'!H77-1,"") | K60: =COUNTIFS(Data!$A:$A,">="&'Copy of Reporte SDR '!$C$5,Data!$A:$A,"<="&'Copy of Reporte SDR '!$D$5,Data!$E:$E,D60,Data!$BG:$BG,$H$7) -> 0 | L60: =IFERROR(K60/$D$55,0) -> 0 | M60: =iferror(K60/'PT Reporte SDR'!K77-1,"") | N60: =COUNTIFS(Data!$A:$A,">="&'Copy of Reporte SDR '!$C$5,Data!$A:$A,"<="&'Copy of Reporte SDR '!$D$5,Data!$E:$E,E60,Data!$BG:$BG,$H$7) -> 0 | O60: =IFERROR(N60/$D$55,0) -> 0 | P60: =iferror(N60/'PT Reporte SDR'!N77-1,"")
C61: Contestó Whatsapp 3 | D61: =sum(H61) -> 0 | E61: =IFERROR(D61/$D$55,0) -> 0 | F61: =iferror(D61/'PT Reporte SDR'!D78-1,"") | H61: =COUNTIFS(Data!$A:$A,">="&'Copy of Reporte SDR '!$C$5,Data!$A:$A,"<="&'Copy of Reporte SDR '!$D$5,Data!$Y:$Y,C61) -> 0 | I61: =IFERROR(H61/$D$55,0) -> 0 | J61: =iferror(H61/'PT Reporte SDR'!H78-1,"") | K61: =COUNTIFS(Data!$A:$A,">="&'Copy of Reporte SDR '!$C$5,Data!$A:$A,"<="&'Copy of Reporte SDR '!$D$5,Data!$E:$E,D61,Data!$BG:$BG,$H$7) -> 0 | L61: =IFERROR(K61/$D$55,0) -> 0 | M61: =iferror(K61/'PT Reporte SDR'!K78-1,"") | N61: =COUNTIFS(Data!$A:$A,">="&'Copy of Reporte SDR '!$C$5,Data!$A:$A,"<="&'Copy of Reporte SDR '!$D$5,Data!$E:$E,E61,Data!$BG:$BG,$H$7) -> 0 | O61: =IFERROR(N61/$D$55,0) -> 0 | P61: =iferror(N61/'PT Reporte SDR'!N78-1,"")
C62: Contestó Correo 1 | D62: =sum(H62) -> 0 | E62: =IFERROR(D62/$D$55,0) -> 0 | F62: =iferror(D62/'PT Reporte SDR'!D79-1,"") | H62: =COUNTIFS(Data!$A:$A,">="&'Copy of Reporte SDR '!$C$5,Data!$A:$A,"<="&'Copy of Reporte SDR '!$D$5,Data!$Y:$Y,C62) -> 0 | I62: =IFERROR(H62/$D$55,0) -> 0 | J62: =iferror(H62/'PT Reporte SDR'!H79-1,"") | K62: =COUNTIFS(Data!$A:$A,">="&'Copy of Reporte SDR '!$C$5,Data!$A:$A,"<="&'Copy of Reporte SDR '!$D$5,Data!$E:$E,D62,Data!$BG:$BG,$H$7) -> 0 | L62: =IFERROR(K62/$D$55,0) -> 0 | M62: =iferror(K62/'PT Reporte SDR'!K79-1,"") | N62: =COUNTIFS(Data!$A:$A,">="&'Copy of Reporte SDR '!$C$5,Data!$A:$A,"<="&'Copy of Reporte SDR '!$D$5,Data!$E:$E,E62,Data!$BG:$BG,$H$7) -> 0 | O62: =IFERROR(N62/$D$55,0) -> 0 | P62: =iferror(N62/'PT Reporte SDR'!N79-1,"")
C63: Contestó Correo 2 | D63: =sum(H63) -> 0 | E63: =IFERROR(D63/$D$55,0) -> 0 | F63: =iferror(D63/'PT Reporte SDR'!D80-1,"") | H63: =COUNTIFS(Data!$A:$A,">="&'Copy of Reporte SDR '!$C$5,Data!$A:$A,"<="&'Copy of Reporte SDR '!$D$5,Data!$Y:$Y,C63) -> 0 | I63: =IFERROR(H63/$D$55,0) -> 0 | J63: =iferror(H63/'PT Reporte SDR'!H80-1,"") | K63: =COUNTIFS(Data!$A:$A,">="&'Copy of Reporte SDR '!$C$5,Data!$A:$A,"<="&'Copy of Reporte SDR '!$D$5,Data!$E:$E,D63,Data!$BG:$BG,$H$7) -> 0 | L63: =IFERROR(K63/$D$55,0) -> 0 | M63: =iferror(K63/'PT Reporte SDR'!K80-1,"") | N63: =COUNTIFS(Data!$A:$A,">="&'Copy of Reporte SDR '!$C$5,Data!$A:$A,"<="&'Copy of Reporte SDR '!$D$5,Data!$E:$E,E63,Data!$BG:$BG,$H$7) -> 0 | O63: =IFERROR(N63/$D$55,0) -> 0 | P63: =iferror(N63/'PT Reporte SDR'!N80-1,"")
C64: Contestó Correo 3 | D64: =sum(H64) -> 0 | E64: =IFERROR(D64/$D$55,0) -> 0 | F64: =iferror(D64/'PT Reporte SDR'!D81-1,"") | H64: =COUNTIFS(Data!$A:$A,">="&'Copy of Reporte SDR '!$C$5,Data!$A:$A,"<="&'Copy of Reporte SDR '!$D$5,Data!$Y:$Y,C64) -> 0 | I64: =IFERROR(H64/$D$55,0) -> 0 | J64: =iferror(H64/'PT Reporte SDR'!H81-1,"") | K64: =COUNTIFS(Data!$A:$A,">="&'Copy of Reporte SDR '!$C$5,Data!$A:$A,"<="&'Copy of Reporte SDR '!$D$5,Data!$E:$E,D64,Data!$BG:$BG,$H$7) -> 0 | L64: =IFERROR(K64/$D$55,0) -> 0 | M64: =iferror(K64/'PT Reporte SDR'!K81-1,"") | N64: =COUNTIFS(Data!$A:$A,">="&'Copy of Reporte SDR '!$C$5,Data!$A:$A,"<="&'Copy of Reporte SDR '!$D$5,Data!$E:$E,E64,Data!$BG:$BG,$H$7) -> 0 | O64: =IFERROR(N64/$D$55,0) -> 0 | P64: =iferror(N64/'PT Reporte SDR'!N81-1,"")
C65: Contestó Correo 4 | D65: =sum(H65) -> 0 | E65: =IFERROR(D65/$D$55,0) -> 0 | F65: =iferror(D65/'PT Reporte SDR'!D82-1,"") | H65: =COUNTIFS(Data!$A:$A,">="&'Copy of Reporte SDR '!$C$5,Data!$A:$A,"<="&'Copy of Reporte SDR '!$D$5,Data!$Y:$Y,C65) -> 0 | I65: =IFERROR(H65/$D$55,0) -> 0 | J65: =iferror(H65/'PT Reporte SDR'!H82-1,"") | K65: =COUNTIFS(Data!$A:$A,">="&'Copy of Reporte SDR '!$C$5,Data!$A:$A,"<="&'Copy of Reporte SDR '!$D$5,Data!$E:$E,D65,Data!$BG:$BG,$H$7) -> 0 | L65: =IFERROR(K65/$D$55,0) -> 0 | M65: =iferror(K65/'PT Reporte SDR'!K82-1,"") | N65: =COUNTIFS(Data!$A:$A,">="&'Copy of Reporte SDR '!$C$5,Data!$A:$A,"<="&'Copy of Reporte SDR '!$D$5,Data!$E:$E,E65,Data!$BG:$BG,$H$7) -> 0 | O65: =IFERROR(N65/$D$55,0) -> 0 | P65: =iferror(N65/'PT Reporte SDR'!N82-1,"")
F66: =iferror(D66/'PT Reporte SDR'!D83-1,"") | J66: =iferror(H66/'PT Reporte SDR'!H83-1,"") | M66: =iferror(K66/'PT Reporte SDR'!K83-1,"") | P66: =iferror(N66/'PT Reporte SDR'!N83-1,"")
F67: =iferror(D67/'PT Reporte SDR'!D84-1,"") | J67: =iferror(H67/'PT Reporte SDR'!H84-1,"") | M67: =iferror(K67/'PT Reporte SDR'!K84-1,"") | P67: =iferror(N67/'PT Reporte SDR'!N84-1,"")
C68: Total Lead en Proceso de Contacto (aún sin respuesta) | D68: =SUM(D69:D76) -> 0 | E68: % Total | F68: =iferror(D68/'PT Reporte SDR'!D85-1,"") | H68: =SUM(H69:H76) -> 0 | I68: % Total | J68: =iferror(H68/'PT Reporte SDR'!H85-1,"") | K68: =SUM(K69:K76) -> 0 | L68: % Total | M68: =iferror(K68/'PT Reporte SDR'!K85-1,"") | N68: =SUM(N69:N76) -> 0 | O68: % Total | P68: =iferror(N68/'PT Reporte SDR'!N85-1,"")
C69: No Contestó Teléfono 2 | D69: =sum(H69) -> 0 | E69: =iferror(D69/$D$68,0) -> 0 | F69: =iferror(D69/'PT Reporte SDR'!D86-1,"") | H69: =COUNTIFS(Data!$A:$A,">="&'Copy of Reporte SDR '!$C$5,Data!$A:$A,"<="&'Copy of Reporte SDR '!$D$5,Data!$Y:$Y,#REF!) -> 0 | I69: =iferror(H69/$D$68,0) -> 0 | J69: =iferror(H69/'PT Reporte SDR'!H86-1,"") | K69: =COUNTIFS(Data!$A:$A,">="&'Copy of Reporte SDR '!$C$5,Data!$A:$A,"<="&'Copy of Reporte SDR '!$D$5,Data!$E:$E,D69,Data!$BG:$BG,$H$7) -> 0 | L69: =iferror(K69/$D$68,0) -> 0 | M69: =iferror(K69/'PT Reporte SDR'!K86-1,"") | N69: =COUNTIFS(Data!$A:$A,">="&'Copy of Reporte SDR '!$C$5,Data!$A:$A,"<="&'Copy of Reporte SDR '!$D$5,Data!$E:$E,E69,Data!$BG:$BG,$H$7) -> 0 | O69: =iferror(N69/$D$68,0) -> 0 | P69: =iferror(N69/'PT Reporte SDR'!N86-1,"")
D70: =sum(H70) -> 0 | E70: =iferror(D70/$D$68,0) -> 0 | F70: =iferror(D70/'PT Reporte SDR'!D87-1,"") | H70: =COUNTIFS(Data!$A:$A,">="&'Copy of Reporte SDR '!$C$5,Data!$A:$A,"<="&'Copy of Reporte SDR '!$D$5,Data!$Y:$Y,C69) -> 0 | I70: =iferror(H70/$D$68,0) -> 0 | J70: =iferror(H70/'PT Reporte SDR'!H87-1,"") | K70: =COUNTIFS(Data!$A:$A,">="&'Copy of Reporte SDR '!$C$5,Data!$A:$A,"<="&'Copy of Reporte SDR '!$D$5,Data!$E:$E,D70,Data!$BG:$BG,$H$7) -> 0 | L70: =iferror(K70/$D$68,0) -> 0 | M70: =iferror(K70/'PT Reporte SDR'!K87-1,"") | N70: =COUNTIFS(Data!$A:$A,">="&'Copy of Reporte SDR '!$C$5,Data!$A:$A,"<="&'Copy of Reporte SDR '!$D$5,Data!$E:$E,E70,Data!$BG:$BG,$H$7) -> 0 | O70: =iferror(N70/$D$68,0) -> 0 | P70: =iferror(N70/'PT Reporte SDR'!N87-1,"")
C71: No Contesto Teléfono 3 | D71: =sum(H71) -> 0 | E71: =iferror(D71/$D$68,0) -> 0 | F71: =iferror(D71/'PT Reporte SDR'!D88-1,"") | H71: =COUNTIFS(Data!$A:$A,">="&'Copy of Reporte SDR '!$C$5,Data!$A:$A,"<="&'Copy of Reporte SDR '!$D$5,Data!$Y:$Y,C71) -> 0 | I71: =iferror(H71/$D$68,0) -> 0 | J71: =iferror(H71/'PT Reporte SDR'!H88-1,"") | K71: =COUNTIFS(Data!$A:$A,">="&'Copy of Reporte SDR '!$C$5,Data!$A:$A,"<="&'Copy of Reporte SDR '!$D$5,Data!$E:$E,D71,Data!$BG:$BG,$H$7) -> 0 | L71: =iferror(K71/$D$68,0) -> 0 | M71: =iferror(K71/'PT Reporte SDR'!K88-1,"") | N71: =COUNTIFS(Data!$A:$A,">="&'Copy of Reporte SDR '!$C$5,Data!$A:$A,"<="&'Copy of Reporte SDR '!$D$5,Data!$E:$E,E71,Data!$BG:$BG,$H$7) -> 0 | O71: =iferror(N71/$D$68,0) -> 0 | P71: =iferror(N71/'PT Reporte SDR'!N88-1,"")
C72: No Contestó Whatsapp 1 | D72: =sum(H72) -> 0 | E72: =iferror(D72/$D$68,0) -> 0 | F72: =iferror(D72/'PT Reporte SDR'!D89-1,"") | H72: =COUNTIFS(Data!$A:$A,">="&'Copy of Reporte SDR '!$C$5,Data!$A:$A,"<="&'Copy of Reporte SDR '!$D$5,Data!$Y:$Y,C72) -> 0 | I72: =iferror(H72/$D$68,0) -> 0 | J72: =iferror(H72/'PT Reporte SDR'!H89-1,"") | K72: =COUNTIFS(Data!$A:$A,">="&'Copy of Reporte SDR '!$C$5,Data!$A:$A,"<="&'Copy of Reporte SDR '!$D$5,Data!$E:$E,D72,Data!$BG:$BG,$H$7) -> 0 | L72: =iferror(K72/$D$68,0) -> 0 | M72: =iferror(K72/'PT Reporte SDR'!K89-1,"") | N72: =COUNTIFS(Data!$A:$A,">="&'Copy of Reporte SDR '!$C$5,Data!$A:$A,"<="&'Copy of Reporte SDR '!$D$5,Data!$E:$E,E72,Data!$BG:$BG,$H$7) -> 0 | O72: =iferror(N72/$D$68,0) -> 0 | P72: =iferror(N72/'PT Reporte SDR'!N89-1,"")
C73: No Contestó Whatsapp 2 | D73: =sum(H73) -> 0 | E73: =iferror(D73/$D$68,0) -> 0 | F73: =iferror(D73/'PT Reporte SDR'!D90-1,"") | H73: =COUNTIFS(Data!$A:$A,">="&'Copy of Reporte SDR '!$C$5,Data!$A:$A,"<="&'Copy of Reporte SDR '!$D$5,Data!$Y:$Y,C73) -> 0 | I73: =iferror(H73/$D$68,0) -> 0 | J73: =iferror(H73/'PT Reporte SDR'!H90-1,"") | K73: =COUNTIFS(Data!$A:$A,">="&'Copy of Reporte SDR '!$C$5,Data!$A:$A,"<="&'Copy of Reporte SDR '!$D$5,Data!$E:$E,D73,Data!$BG:$BG,$H$7) -> 0 | L73: =iferror(K73/$D$68,0) -> 0 | M73: =iferror(K73/'PT Reporte SDR'!K90-1,"") | N73: =COUNTIFS(Data!$A:$A,">="&'Copy of Reporte SDR '!$C$5,Data!$A:$A,"<="&'Copy of Reporte SDR '!$D$5,Data!$E:$E,E73,Data!$BG:$BG,$H$7) -> 0 | O73: =iferror(N73/$D$68,0) -> 0 | P73: =iferror(N73/'PT Reporte SDR'!N90-1,"")
C74: No Contestó Whatsapp 3 | D74: =sum(H74) -> 0 | E74: =iferror(D74/$D$68,0) -> 0 | F74: =iferror(D74/'PT Reporte SDR'!D91-1,"") | H74: =COUNTIFS(Data!$A:$A,">="&'Copy of Reporte SDR '!$C$5,Data!$A:$A,"<="&'Copy of Reporte SDR '!$D$5,Data!$Y:$Y,C74) -> 0 | I74: =iferror(H74/$D$68,0) -> 0 | J74: =iferror(H74/'PT Reporte SDR'!H91-1,"") | K74: =COUNTIFS(Data!$A:$A,">="&'Copy of Reporte SDR '!$C$5,Data!$A:$A,"<="&'Copy of Reporte SDR '!$D$5,Data!$E:$E,D74,Data!$BG:$BG,$H$7) -> 0 | L74: =iferror(K74/$D$68,0) -> 0 | M74: =iferror(K74/'PT Reporte SDR'!K91-1,"") | N74: =COUNTIFS(Data!$A:$A,">="&'Copy of Reporte SDR '!$C$5,Data!$A:$A,"<="&'Copy of Reporte SDR '!$D$5,Data!$E:$E,E74,Data!$BG:$BG,$H$7) -> 0 | O74: =iferror(N74/$D$68,0) -> 0 | P74: =iferror(N74/'PT Reporte SDR'!N91-1,"")
F75: =iferror(D75/'PT Reporte SDR'!D92-1,"") | J75: =iferror(H75/'PT Reporte SDR'!H92-1,"") | M75: =iferror(K75/'PT Reporte SDR'!K92-1,"") | P75: =iferror(N75/'PT Reporte SDR'!N92-1,"")
F76: =iferror(D76/'PT Reporte SDR'!D93-1,"") | J76: =iferror(H76/'PT Reporte SDR'!H93-1,"") | M76: =iferror(K76/'PT Reporte SDR'!K93-1,"") | P76: =iferror(N76/'PT Reporte SDR'!N93-1,"")
F77: =iferror(D77/'PT Reporte SDR'!D94-1,"") | J77: =iferror(H77/'PT Reporte SDR'!H94-1,"") | M77: =iferror(K77/'PT Reporte SDR'!K94-1,"") | P77: =iferror(N77/'PT Reporte SDR'!N94-1,"")
C78: Total Leads Contactados sin Respuesta (6to Toque) | D78: =SUM(D79:D80) -> 0 | E78: % Total | F78: =iferror(D78/'PT Reporte SDR'!D95-1,"") | H78: =SUM(H79:H80) -> 0 | I78: % Total | J78: =iferror(H78/'PT Reporte SDR'!H95-1,"") | K78: =SUM(K79:K80) -> 0 | L78: % Total | M78: =iferror(K78/'PT Reporte SDR'!K95-1,"") | N78: =SUM(N79:N80) -> 0 | O78: % Total | P78: =iferror(N78/'PT Reporte SDR'!N95-1,"")
C79: Toque 6 | D79: =sum(H79) -> 0 | E79: =IFERROR(D79/$D$78,0) -> 0 | F79: =iferror(D79/'PT Reporte SDR'!D96-1,"") | H79: =COUNTIFS(Data!$A:$A,">="&'Copy of Reporte SDR '!$C$5,Data!$A:$A,"<="&'Copy of Reporte SDR '!$D$5,Data!$AE:$AE,C79) -> 0 | I79: =IFERROR(H79/$D$78,0) -> 0 | J79: =iferror(H79/'PT Reporte SDR'!H96-1,"") | L79: =IFERROR(K79/$D$78,0) -> 0 | M79: =iferror(K79/'PT Reporte SDR'!K96-1,"") | O79: =IFERROR(N79/$D$78,0) -> 0 | P79: =iferror(N79/'PT Reporte SDR'!N96-1,"")
F80: =iferror(D80/'PT Reporte SDR'!D97-1,"") | J80: =iferror(H80/'PT Reporte SDR'!H97-1,"") | M80: =iferror(K80/'PT Reporte SDR'!K97-1,"") | P80: =iferror(N80/'PT Reporte SDR'!N97-1,"")
F81: =iferror(D81/'PT Reporte SDR'!D98-1,"") | J81: =iferror(H81/'PT Reporte SDR'!H98-1,"") | M81: =iferror(K81/'PT Reporte SDR'!K98-1,"") | P81: =iferror(N81/'PT Reporte SDR'!N98-1,"")
C82: ¿Por Qué No Pasó a Ventas? | D82: =sum(D83:D124) -> 2 | E82: % | F82: =iferror(D82/'PT Reporte SDR'!D99-1,"") | H82: =SUM(H83:H124) -> 2 | I82: % | J82: =iferror(H82/'PT Reporte SDR'!H99-1,"") | K82: =SUM(K83:K124) -> 0 | L82: % | M82: =iferror(K82/'PT Reporte SDR'!K99-1,"") | N82: =SUM(N83:N124) -> 0 | O82: % | P82: =iferror(N82/'PT Reporte SDR'!N99-1,"")
C83: Toque 6 | D83: =H83+K83+N83 -> 0 | E83: =D83/$D$82 -> 0 | F83: =iferror(D83/'PT Reporte SDR'!D100-1,"") | H83: =COUNTIFS(Data!$A:$A,">="&'Copy of Reporte SDR '!$C$5,Data!$A:$A,"<="&'Copy of Reporte SDR '!$D$5,Data!$AD:$AD,C83) -> 0 | I83: =H83/$D$82 -> 0 | J83: =iferror(H83/'PT Reporte SDR'!H100-1,"") | K83: =COUNTIFS(Data!$A:$A,">="&'Copy of Reporte SDR '!$C$5,Data!$A:$A,"<="&'Copy of Reporte SDR '!$D$5,Data!$BI:$BI,$H$7,Data!$DF:$DF,C83) -> 0 | L83: =K83/$D$82 -> 0 | M83: =iferror(K83/'PT Reporte SDR'!K100-1,"") | N83: =COUNTIFS(Data!$A:$A,">="&'Copy of Reporte SDR '!$C$5,Data!$A:$A,"<="&'Copy of Reporte SDR '!$D$5,Data!$BI:$BI,$H$7,Data!$DF:$DF,C83) -> 0 | O83: =N83/$D$82 -> 0 | P83: =iferror(N83/'PT Reporte SDR'!N100-1,"")
C84: Nunca Respondió | D84: =H84+K84+N84 -> 0 | E84: =D84/$D$82 -> 0 | F84: =iferror(D84/'PT Reporte SDR'!D101-1,"") | H84: =COUNTIFS(Data!$A:$A,">="&'Copy of Reporte SDR '!$C$5,Data!$A:$A,"<="&'Copy of Reporte SDR '!$D$5,Data!$AD:$AD,C84) -> 0 | I84: =H84/$D$82 -> 0 | J84: =iferror(H84/'PT Reporte SDR'!H101-1,"") | K84: =COUNTIFS(Data!$A:$A,">="&'Copy of Reporte SDR '!$C$5,Data!$A:$A,"<="&'Copy of Reporte SDR '!$D$5,Data!$BI:$BI,$H$7,Data!$DF:$DF,C84) -> 0 | L84: =K84/$D$82 -> 0 | M84: =iferror(K84/'PT Reporte SDR'!K101-1,"") | N84: =COUNTIFS(Data!$A:$A,">="&'Copy of Reporte SDR '!$C$5,Data!$A:$A,"<="&'Copy of Reporte SDR '!$D$5,Data!$BI:$BI,$H$7,Data!$DF:$DF,C84) -> 0 | O84: =N84/$D$82 -> 0 | P84: =iferror(N84/'PT Reporte SDR'!N101-1,"")
C85: Dejó de responder | D85: =H85+K85+N85 -> 0 | E85: =D85/$D$82 -> 0 | F85: =iferror(D85/'PT Reporte SDR'!D102-1,"") | H85: =COUNTIFS(Data!$A:$A,">="&'Copy of Reporte SDR '!$C$5,Data!$A:$A,"<="&'Copy of Reporte SDR '!$D$5,Data!$AD:$AD,C85) -> 0 | I85: =H85/$D$82 -> 0 | J85: =iferror(H85/'PT Reporte SDR'!H102-1,"") | K85: =COUNTIFS(Data!$A:$A,">="&'Copy of Reporte SDR '!$C$5,Data!$A:$A,"<="&'Copy of Reporte SDR '!$D$5,Data!$BI:$BI,$H$7,Data!$DF:$DF,C85) -> 0 | L85: =K85/$D$82 -> 0 | M85: =iferror(K85/'PT Reporte SDR'!K102-1,"") | N85: =COUNTIFS(Data!$A:$A,">="&'Copy of Reporte SDR '!$C$5,Data!$A:$A,"<="&'Copy of Reporte SDR '!$D$5,Data!$BI:$BI,$H$7,Data!$DF:$DF,C85) -> 0 | O85: =N85/$D$82 -> 0 | P85: =iferror(N85/'PT Reporte SDR'!N102-1,"")
C86: No tuvo más interés | D86: =H86+K86+N86 -> 1 | E86: =D86/$D$82 -> 0.5 | F86: =iferror(D86/'PT Reporte SDR'!D103-1,"") | H86: =COUNTIFS(Data!$A:$A,">="&'Copy of Reporte SDR '!$C$5,Data!$A:$A,"<="&'Copy of Reporte SDR '!$D$5,Data!$AD:$AD,C86)+1 -> 1 | I86: =H86/$D$82 -> 0.5 | J86: =iferror(H86/'PT Reporte SDR'!H103-1,"") | K86: =COUNTIFS(Data!$A:$A,">="&'Copy of Reporte SDR '!$C$5,Data!$A:$A,"<="&'Copy of Reporte SDR '!$D$5,Data!$BI:$BI,$H$7,Data!$DF:$DF,C86) -> 0 | L86: =K86/$D$82 -> 0 | M86: =iferror(K86/'PT Reporte SDR'!K103-1,"") | N86: =COUNTIFS(Data!$A:$A,">="&'Copy of Reporte SDR '!$C$5,Data!$A:$A,"<="&'Copy of Reporte SDR '!$D$5,Data!$BI:$BI,$H$7,Data!$DF:$DF,C86) -> 0 | O86: =N86/$D$82 -> 0 | P86: =iferror(N86/'PT Reporte SDR'!N103-1,"")
C87: Desconoce el registro | D87: =H87+K87+N87 -> 1 | E87: =D87/$D$82 -> 0.5 | F87: =iferror(D87/'PT Reporte SDR'!D104-1,"") | H87: =COUNTIFS(Data!$A:$A,">="&'Copy of Reporte SDR '!$C$5,Data!$A:$A,"<="&'Copy of Reporte SDR '!$D$5,Data!$AD:$AD,C87)+1 -> 1 | I87: =H87/$D$82 -> 0.5 | J87: =iferror(H87/'PT Reporte SDR'!H104-1,"") | K87: =COUNTIFS(Data!$A:$A,">="&'Copy of Reporte SDR '!$C$5,Data!$A:$A,"<="&'Copy of Reporte SDR '!$D$5,Data!$BI:$BI,$H$7,Data!$DF:$DF,C87) -> 0 | L87: =K87/$D$82 -> 0 | M87: =iferror(K87/'PT Reporte SDR'!K104-1,"") | N87: =COUNTIFS(Data!$A:$A,">="&'Copy of Reporte SDR '!$C$5,Data!$A:$A,"<="&'Copy of Reporte SDR '!$D$5,Data!$BI:$BI,$H$7,Data!$DF:$DF,C87) -> 0 | O87: =N87/$D$82 -> 0 | P87: =iferror(N87/'PT Reporte SDR'!N104-1,"")
C88: Ya resolvió su necesidad | D88: =H88+K88+N88 -> 0 | E88: =D88/$D$82 -> 0 | F88: =iferror(D88/'PT Reporte SDR'!D105-1,"") | H88: =COUNTIFS(Data!$A:$A,">="&'Copy of Reporte SDR '!$C$5,Data!$A:$A,"<="&'Copy of Reporte SDR '!$D$5,Data!$AD:$AD,C88) -> 0 | I88: =H88/$D$82 -> 0 | J88: =iferror(H88/'PT Reporte SDR'!H105-1,"") | K88: =COUNTIFS(Data!$A:$A,">="&'Copy of Reporte SDR '!$C$5,Data!$A:$A,"<="&'Copy of Reporte SDR '!$D$5,Data!$BI:$BI,$H$7,Data!$DF:$DF,C88) -> 0 | L88: =K88/$D$82 -> 0 | M88: =iferror(K88/'PT Reporte SDR'!K105-1,"") | N88: =COUNTIFS(Data!$A:$A,">="&'Copy of Reporte SDR '!$C$5,Data!$A:$A,"<="&'Copy of Reporte SDR '!$D$5,Data!$BI:$BI,$H$7,Data!$DF:$DF,C88) -> 0 | O88: =N88/$D$82 -> 0 | P88: =iferror(N88/'PT Reporte SDR'!N105-1,"")
C89: No se cuenta con el servicio | D89: =H89+K89+N89 -> 0 | E89: =D89/$D$82 -> 0 | F89: =iferror(D89/'PT Reporte SDR'!D106-1,"") | H89: =COUNTIFS(Data!$A:$A,">="&'Copy of Reporte SDR '!$C$5,Data!$A:$A,"<="&'Copy of Reporte SDR '!$D$5,Data!$AD:$AD,C89) -> 0 | I89: =H89/$D$82 -> 0 | J89: =iferror(H89/'PT Reporte SDR'!H106-1,"") | K89: =COUNTIFS(Data!$A:$A,">="&'Copy of Reporte SDR '!$C$5,Data!$A:$A,"<="&'Copy of Reporte SDR '!$D$5,Data!$BI:$BI,$H$7,Data!$DF:$DF,C89) -> 0 | L89: =K89/$D$82 -> 0 | M89: =iferror(K89/'PT Reporte SDR'!K106-1,"") | N89: =COUNTIFS(Data!$A:$A,">="&'Copy of Reporte SDR '!$C$5,Data!$A:$A,"<="&'Copy of Reporte SDR '!$D$5,Data!$BI:$BI,$H$7,Data!$DF:$DF,C89) -> 0 | O89: =N89/$D$82 -> 0 | P89: =iferror(N89/'PT Reporte SDR'!N106-1,"")
C90: Busca ser proveedor | D90: =H90+K90+N90 -> 0 | E90: =D90/$D$82 -> 0 | F90: =iferror(D90/'PT Reporte SDR'!D107-1,"") | H90: =COUNTIFS(Data!$A:$A,">="&'Copy of Reporte SDR '!$C$5,Data!$A:$A,"<="&'Copy of Reporte SDR '!$D$5,Data!$AE:$AE,C90) -> 0 | I90: =H90/$D$82 -> 0 | J90: =iferror(H90/'PT Reporte SDR'!H107-1,"") | K90: =COUNTIFS(Data!$A:$A,">="&'Copy of Reporte SDR '!$C$5,Data!$A:$A,"<="&'Copy of Reporte SDR '!$D$5,Data!$BI:$BI,$H$7,Data!$DF:$DF,C90) -> 0 | L90: =K90/$D$82 -> 0 | M90: =iferror(K90/'PT Reporte SDR'!K107-1,"") | N90: =COUNTIFS(Data!$A:$A,">="&'Copy of Reporte SDR '!$C$5,Data!$A:$A,"<="&'Copy of Reporte SDR '!$D$5,Data!$BI:$BI,$H$7,Data!$DF:$DF,C90) -> 0 | O90: =N90/$D$82 -> 0 | P90: =iferror(N90/'PT Reporte SDR'!N107-1,"")
C91: Busca empleo | D91: =H91+K91+N91 -> 0 | E91: =D91/$D$82 -> 0 | F91: =iferror(D91/'PT Reporte SDR'!D108-1,"") | H91: =COUNTIFS(Data!$A:$A,">="&'Copy of Reporte SDR '!$C$5,Data!$A:$A,"<="&'Copy of Reporte SDR '!$D$5,Data!$AD:$AD,C91) -> 0 | I91: =H91/$D$82 -> 0 | J91: =iferror(H91/'PT Reporte SDR'!H108-1,"") | K91: =COUNTIFS(Data!$A:$A,">="&'Copy of Reporte SDR '!$C$5,Data!$A:$A,"<="&'Copy of Reporte SDR '!$D$5,Data!$BI:$BI,$H$7,Data!$DF:$DF,C91) -> 0 | L91: =K91/$D$82 -> 0 | M91: =iferror(K91/'PT Reporte SDR'!K108-1,"") | N91: =COUNTIFS(Data!$A:$A,">="&'Copy of Reporte SDR '!$C$5,Data!$A:$A,"<="&'Copy of Reporte SDR '!$D$5,Data!$BI:$BI,$H$7,Data!$DF:$DF,C91) -> 0 | O91: =N91/$D$82 -> 0 | P91: =iferror(N91/'PT Reporte SDR'!N108-1,"")
C92: Pidió no volver a llamar | D92: =H92+K92+N92 -> 0 | E92: =D92/$D$82 -> 0 | F92: =iferror(D92/'PT Reporte SDR'!D109-1,"") | H92: =COUNTIFS(Data!$A:$A,">="&'Copy of Reporte SDR '!$C$5,Data!$A:$A,"<="&'Copy of Reporte SDR '!$D$5,Data!$AD:$AD,C92) -> 0 | I92: =H92/$D$82 -> 0 | J92: =iferror(H92/'PT Reporte SDR'!H109-1,"") | K92: =COUNTIFS(Data!$A:$A,">="&'Copy of Reporte SDR '!$C$5,Data!$A:$A,"<="&'Copy of Reporte SDR '!$D$5,Data!$BI:$BI,$H$7,Data!$DF:$DF,C92) -> 0 | L92: =K92/$D$82 -> 0 | M92: =iferror(K92/'PT Reporte SDR'!K109-1,"") | N92: =COUNTIFS(Data!$A:$A,">="&'Copy of Reporte SDR '!$C$5,Data!$A:$A,"<="&'Copy of Reporte SDR '!$D$5,Data!$BI:$BI,$H$7,Data!$DF:$DF,C92) -> 0 | O92: =N92/$D$82 -> 0 | P92: =iferror(N92/'PT Reporte SDR'!N109-1,"")
C93: Motivos Personales | D93: =H93+K93+N93 -> 0 | E93: =D93/$D$82 -> 0 | F93: =iferror(D93/'PT Reporte SDR'!D110-1,"") | H93: =COUNTIFS(Data!$A:$A,">="&'Copy of Reporte SDR '!$C$5,Data!$A:$A,"<="&'Copy of Reporte SDR '!$D$5,Data!$AD:$AD,C93) -> 0 | I93: =H93/$D$82 -> 0 | J93: =iferror(H93/'PT Reporte SDR'!H110-1,"") | K93: =COUNTIFS(Data!$A:$A,">="&'Copy of Reporte SDR '!$C$5,Data!$A:$A,"<="&'Copy of Reporte SDR '!$D$5,Data!$BI:$BI,$H$7,Data!$DF:$DF,C93) -> 0 | L93: =K93/$D$82 -> 0 | M93: =iferror(K93/'PT Reporte SDR'!K110-1,"") | N93: =COUNTIFS(Data!$A:$A,">="&'Copy of Reporte SDR '!$C$5,Data!$A:$A,"<="&'Copy of Reporte SDR '!$D$5,Data!$BI:$BI,$H$7,Data!$DF:$DF,C93) -> 0 | O93: =N93/$D$82 -> 0 | P93: =iferror(N93/'PT Reporte SDR'!N110-1,"")
C94: No me llames, yo te llamo | D94: =H94+K94+N94 -> 0 | E94: =D94/$D$82 -> 0 | F94: =iferror(D94/'PT Reporte SDR'!D111-1,"") | H94: =COUNTIFS(Data!$A:$A,">="&'Copy of Reporte SDR '!$C$5,Data!$A:$A,"<="&'Copy of Reporte SDR '!$D$5,Data!$AD:$AD,C94) -> 0 | I94: =H94/$D$82 -> 0 | J94: =iferror(H94/'PT Reporte SDR'!H111-1,"") | K94: =COUNTIFS(Data!$A:$A,">="&'Copy of Reporte SDR '!$C$5,Data!$A:$A,"<="&'Copy of Reporte SDR '!$D$5,Data!$BI:$BI,$H$7,Data!$DF:$DF,C94) -> 0 | L94: =K94/$D$82 -> 0 | M94: =iferror(K94/'PT Reporte SDR'!K111-1,"") | N94: =COUNTIFS(Data!$A:$A,">="&'Copy of Reporte SDR '!$C$5,Data!$A:$A,"<="&'Copy of Reporte SDR '!$D$5,Data!$BI:$BI,$H$7,Data!$DF:$DF,C94) -> 0 | O94: =N94/$D$82 -> 0 | P94: =iferror(N94/'PT Reporte SDR'!N111-1,"")
C95: No cuenta con el dinero | D95: =H95+K95+N95 -> 0 | E95: =D95/$D$82 -> 0 | F95: =iferror(D95/'PT Reporte SDR'!D112-1,"") | H95: =COUNTIFS(Data!$A:$A,">="&'Copy of Reporte SDR '!$C$5,Data!$A:$A,"<="&'Copy of Reporte SDR '!$D$5,Data!$AD:$AD,C95) -> 0 | I95: =H95/$D$82 -> 0 | J95: =iferror(H95/'PT Reporte SDR'!H112-1,"") | K95: =COUNTIFS(Data!$A:$A,">="&'Copy of Reporte SDR '!$C$5,Data!$A:$A,"<="&'Copy of Reporte SDR '!$D$5,Data!$BI:$BI,$H$7,Data!$DF:$DF,C95) -> 0 | L95: =K95/$D$82 -> 0 | M95: =iferror(K95/'PT Reporte SDR'!K112-1,"") | N95: =COUNTIFS(Data!$A:$A,">="&'Copy of Reporte SDR '!$C$5,Data!$A:$A,"<="&'Copy of Reporte SDR '!$D$5,Data!$BI:$BI,$H$7,Data!$DF:$DF,C95) -> 0 | O95: =N95/$D$82 -> 0 | P95: =iferror(N95/'PT Reporte SDR'!N112-1,"")
F96: =iferror(D96/'PT Reporte SDR'!D112-1,"") | J96: =iferror(H96/'PT Reporte SDR'!H112-1,"") | M96: =iferror(K96/'PT Reporte SDR'!K112-1,"") | P96: =iferror(N96/'PT Reporte SDR'!N112-1,"")
F97: =iferror(D97/'PT Reporte SDR'!D113-1,"") | J97: =iferror(H97/'PT Reporte SDR'!H113-1,"") | M97: =iferror(K97/'PT Reporte SDR'!K113-1,"") | P97: =iferror(N97/'PT Reporte SDR'!N113-1,"")
C98: ¿Por qué se perdió la venta? | D98: =H98+K98+N98 -> 0 | E98: =D98/$D$82 -> 0 | F98: =iferror(D98/'PT Reporte SDR'!D114-1,"") | H98: =COUNTIFS(Data!$A:$A,">="&'Copy of Reporte SDR '!$C$5,Data!$A:$A,"<="&'Copy of Reporte SDR '!$D$5,Data!$BI:$BI,$H$7,Data!$DF:$DF,C98) -> 0 | I98: =H98/$D$82 -> 0 | J98: =iferror(H98/'PT Reporte SDR'!H114-1,"") | K98: =COUNTIFS(Data!$A:$A,">="&'Copy of Reporte SDR '!$C$5,Data!$A:$A,"<="&'Copy of Reporte SDR '!$D$5,Data!$BI:$BI,$H$7,Data!$DF:$DF,C98) -> 0 | L98: =K98/$D$82 -> 0 | M98: =iferror(K98/'PT Reporte SDR'!K114-1,"") | N98: =COUNTIFS(Data!$A:$A,">="&'Copy of Reporte SDR '!$C$5,Data!$A:$A,"<="&'Copy of Reporte SDR '!$D$5,Data!$BI:$BI,$H$7,Data!$DF:$DF,C98) -> 0 | O98: =N98/$D$82 -> 0 | P98: =iferror(N98/'PT Reporte SDR'!N114-1,"")
C99: No le interesó la cotización | D99: =H99+K99+N99 -> 0 | E99: =D99/$D$82 -> 0 | F99: =iferror(D99/'PT Reporte SDR'!D115-1,"") | H99: =COUNTIFS(Data!$A:$A,">="&'Copy of Reporte SDR '!$C$5,Data!$A:$A,"<="&'Copy of Reporte SDR '!$D$5,Data!$BR:$BR,C99) -> 0 | I99: =H99/$D$82 -> 0 | J99: =iferror(H99/'PT Reporte SDR'!H115-1,"") | K99: =COUNTIFS(Data!$A:$A,">="&'Copy of Reporte SDR '!$C$5,Data!$A:$A,"<="&'Copy of Reporte SDR '!$D$5,Data!$BI:$BI,$H$7,Data!$DF:$DF,C99) -> 0 | L99: =K99/$D$82 -> 0 | M99: =iferror(K99/'PT Reporte SDR'!K115-1,"") | N99: =COUNTIFS(Data!$A:$A,">="&'Copy of Reporte SDR '!$C$5,Data!$A:$A,"<="&'Copy of Reporte SDR '!$D$5,Data!$BI:$BI,$H$7,Data!$DF:$DF,C99) -> 0 | O99: =N99/$D$82 -> 0 | P99: =iferror(N99/'PT Reporte SDR'!N115-1,"")
C100: Le pareció costoso | D100: =H100+K100+N100 -> 0 | E100: =D100/$D$82 -> 0 | F100: =iferror(D100/'PT Reporte SDR'!D116-1,"") | H100: =COUNTIFS(Data!$A:$A,">="&'Copy of Reporte SDR '!$C$5,Data!$A:$A,"<="&'Copy of Reporte SDR '!$D$5,Data!$BR:$BR,C100) -> 0 | I100: =H100/$D$82 -> 0 | J100: =iferror(H100/'PT Reporte SDR'!H116-1,"") | K100: =COUNTIFS(Data!$A:$A,">="&'Copy of Reporte SDR '!$C$5,Data!$A:$A,"<="&'Copy of Reporte SDR '!$D$5,Data!$BI:$BI,$H$7,Data!$DF:$DF,C100) -> 0 | L100: =K100/$D$82 -> 0 | M100: =iferror(K100/'PT Reporte SDR'!K116-1,"") | N100: =COUNTIFS(Data!$A:$A,">="&'Copy of Reporte SDR '!$C$5,Data!$A:$A,"<="&'Copy of Reporte SDR '!$D$5,Data!$BI:$BI,$H$7,Data!$DF:$DF,C100) -> 0 | O100: =N100/$D$82 -> 0 | P100: =iferror(N100/'PT Reporte SDR'!N116-1,"")
C101: No tenía suficiente presupuesto | D101: =H101+K101+N101 -> 0 | E101: =D101/$D$82 -> 0 | F101: =iferror(D101/'PT Reporte SDR'!D117-1,"") | H101: =COUNTIFS(Data!$A:$A,">="&'Copy of Reporte SDR '!$C$5,Data!$A:$A,"<="&'Copy of Reporte SDR '!$D$5,Data!$BR:$BR,C101) -> 0 | I101: =H101/$D$82 -> 0 | J101: =iferror(H101/'PT Reporte SDR'!H117-1,"") | K101: =COUNTIFS(Data!$A:$A,">="&'Copy of Reporte SDR '!$C$5,Data!$A:$A,"<="&'Copy of Reporte SDR '!$D$5,Data!$BI:$BI,$H$7,Data!$DF:$DF,C101) -> 0 | L101: =K101/$D$82 -> 0 | M101: =iferror(K101/'PT Reporte SDR'!K117-1,"") | N101: =COUNTIFS(Data!$A:$A,">="&'Copy of Reporte SDR '!$C$5,Data!$A:$A,"<="&'Copy of Reporte SDR '!$D$5,Data!$BI:$BI,$H$7,Data!$DF:$DF,C101) -> 0 | O101: =N101/$D$82 -> 0 | P101: =iferror(N101/'PT Reporte SDR'!N117-1,"")
C102: Nunca recibimos respuesta | D102: =H102+K102+N102 -> 0 | E102: =D102/$D$82 -> 0 | F102: =iferror(D102/'PT Reporte SDR'!D118-1,"") | H102: =COUNTIFS(Data!$A:$A,">="&'Copy of Reporte SDR '!$C$5,Data!$A:$A,"<="&'Copy of Reporte SDR '!$D$5,Data!$BR:$BR,C102) -> 0 | I102: =H102/$D$82 -> 0 | J102: =iferror(H102/'PT Reporte SDR'!H118-1,"") | K102: =COUNTIFS(Data!$A:$A,">="&'Copy of Reporte SDR '!$C$5,Data!$A:$A,"<="&'Copy of Reporte SDR '!$D$5,Data!$BI:$BI,$H$7,Data!$DF:$DF,C102) -> 0 | L102: =K102/$D$82 -> 0 | M102: =iferror(K102/'PT Reporte SDR'!K118-1,"") | N102: =COUNTIFS(Data!$A:$A,">="&'Copy of Reporte SDR '!$C$5,Data!$A:$A,"<="&'Copy of Reporte SDR '!$D$5,Data!$BI:$BI,$H$7,Data!$DF:$DF,C102) -> 0 | O102: =N102/$D$82 -> 0 | P102: =iferror(N102/'PT Reporte SDR'!N118-1,"")
...

Sheet 2026 Reporte SDR 
C3: IAAPA | FUNNEL REPORT | SDR | REALTIME
C4: Day In | D4: Day Out
C5: 46023 | D5: 46054
C6: =EOMONTH(C5,-2)+1 -> 45992 | D6: =EDATE(D5, -1) -> 46023
C7: MÉTRICA | D7: TOTAL | E7: % | F7: Δ% vs PP | H7: Total | I7: % | J7: Δ% vs PP | K7: Manufacturers | L7: % | M7: Δ% vs PP | N7: Individuals | O7: % | P7: Δ% vs PP | S7: Agosto
C8: Total Leads SDR | D8: =H8 -> 0 | F8: =iferror(D8/'PT Reporte SDR'!D6-1,"") | H8: =COUNTIFS(Data!$A:$A,">="&'2026 Reporte SDR '!$C$5,Data!$A:$A,"<="&'2026 Reporte SDR '!$D$5) -> 0 | J8: =iferror(H8/'PT Reporte SDR'!H6-1,"") | K8: =COUNTIFS(Data!$A:$A,">="&'2026 Reporte SDR '!$C$5,Data!$A:$A,"<="&'2026 Reporte SDR '!$D$5,Data!$BI:$BI,K7) -> 0 | M8: =iferror(K8/'PT Reporte SDR'!K6-1,"") | N8: =COUNTIFS(Data!$A:$A,">="&'2026 Reporte SDR '!$C$5,Data!$A:$A,"<="&'2026 Reporte SDR '!$D$5,Data!$BI:$BI,N7) -> 0 | P8: =iferror(N8/'PT Reporte SDR'!N6-1,"") | S8: Pagados | T8: 4 | W8: Cerrados carry over
C9: Prueba | D9: =Sum(H9+K9+N9) -> 0 | E9: =iferror(D9/$D$8,"0%") -> 0% | F9: =iferror(D9/'PT Reporte SDR'!D65-1,"") | H9: =COUNTIFS(Data!$A:$A,">="&'2026 Reporte SDR '!$C$5,Data!$A:$A,"<="&'2026 Reporte SDR '!$D$5,Data!$X:$X,C9) -> 0 | I9: =iferror(H9/$D$49,0) -> 0 | J9: =iferror(H9/'PT Reporte SDR'!H65-1,"") | K9: =COUNTIFS(Data!$A:$A,">="&'2026 Reporte SDR '!$C$5,Data!$A:$A,"<="&'2026 Reporte SDR '!$D$5,Data!$BI:$BI,$H$7,Data!$CM:$CM,C9) -> 0 | L9: =iferror(K9/$D$49,0) -> 0 | M9: =iferror(K9/'PT Reporte SDR'!K65-1,"") | N9: =COUNTIFS(Data!$A:$A,">="&'2026 Reporte SDR '!$C$5,Data!$A:$A,"<="&'2026 Reporte SDR '!$D$5,Data!$BI:$BI,$H$7,Data!$CM:$CM,C9) -> 0 | O9: =iferror(N9/$D$49,0) -> 0 | P9: =iferror(N9/'PT Reporte SDR'!N65-1,"")
C10: Total Leads Incontactables por base de datos | D10: =H10 -> 0 | E10: =iferror(D10/$D$8,"0%") -> 0% | F10: =iferror(D10/'PT Reporte SDR'!D7-1,"") | H10: =H49 -> 0 | I10: =iferror(H10/$D$8,"0%") -> 0% | J10: =iferror(H10/'PT Reporte SDR'!H7-1,"") | K10: =K49 -> 0 | L10: =iferror(K10/$D$8,"0%") -> 0% | M10: =iferror(K10/'PT Reporte SDR'!K7-1,"") | N10: =N49 -> 0 | O10: =iferror(N10/$D$8,"0%") -> 0% | P10: =iferror(N10/'PT Reporte SDR'!N7-1,"")
C11: Total Leads Contactables | D11: =H11 -> 0 | E11: =iferror(D11/$D$8,"0%") -> 0% | F11: =iferror(D11/'PT Reporte SDR'!D8-1,"") | H11: =H8-H10-H9 -> 0 | I11: =iferror(H11/$D$8,"0%") -> 0% | J11: =iferror(H11/'PT Reporte SDR'!H8-1,"") | K11: =K8-K10 -> 0 | L11: =iferror(K11/$D$8,"0%") -> 0% | M11: =iferror(K11/'PT Reporte SDR'!K8-1,"") | N11: =N8-N10 -> 0 | O11: =iferror(N11/$D$8,"0%") -> 0% | P11: =iferror(N11/'PT Reporte SDR'!N8-1,"")
C12: Total Leads Contactados (con al menos 1 Toque) | D12: =H12 -> 2 | E12: =iferror(D12/D11,"0%") -> 0% | F12: =iferror(D12/'PT Reporte SDR'!D9-1,"") | H12: =COUNTIFS(Data!$A:$A,">="&'2026 Reporte SDR '!$C$5,Data!$A:$A,"<="&'2026 Reporte SDR '!$D$5,Data!$Y:$Y,"<>")+2 -> 2 | I12: =iferror(H12/H11,"0%") -> 0% | J12: =iferror(H12/'PT Reporte SDR'!H9-1,"") | K12: =COUNTIFS(Data!$A:$A,">="&'2026 Reporte SDR '!$C$5,Data!$A:$A,"<="&'2026 Reporte SDR '!$D$5,Data!$BI:$BI,K7,Data!$AT:$AT,"<>")-K10 -> 0 | L12: =iferror(K12/K11,"0%") -> 0% | M12: =iferror(K12/'PT Reporte SDR'!K9-1,"") | N12: =COUNTIFS(Data!$A:$A,">="&'2026 Reporte SDR '!$C$5,Data!$A:$A,"<="&'2026 Reporte SDR '!$D$5,Data!$BI:$BI,N7,Data!$AT:$AT,"<>")-N10 -> 0 | O12: =iferror(N12/N11,"0%") -> 0% | P12: =iferror(N12/'PT Reporte SDR'!N9-1,"")
